Workbook

Sheet Purchase 2
A5: Louise | B5: Old | E5: New | H5: Total Purchase | I5: Total Profit | J5: Total Margin | L5: Manisha | M5: Old | P5: New | S5: Total Purchase | T5: Total Profit | U5: Total Margin
B6: Purchase | C6: Profit | D6: Margin | E6: Purchase | F6: Profit | G6: Margin | M6: Purchase | N6: Profit | O6: Margin | P6: Purchase | Q6: Profit | R6: Margin
A7: Jan | B7: 2201358 | C7: 1316676.5 | D7: 0.59812009 | E7: 16373.57 | F7: 474.97 | G7: 0.029008335 | H7: 2217731.6 | I7: 1317151.4 | J7: 0.59391832 | L7: Jan | M7: 967037.27 | N7: 102472.31 | O7: 0.10596521 | P7: 0 | Q7: 0 | R7: 0 | S7: 967037.27 | T7: 102472.31 | U7: 0.10596521
A8: Feb | B8: 2778078.7 | C8: 1473980.8 | D8: 0.53057562 | E8: 12781.88 | F8: 657.08 | G8: 0.051407148 | H8: 2790860.6 | I8: 1474637.9 | J8: 0.52838107 | L8: Feb | M8: 1099339.8 | N8: 185090 | O8: 0.16836469 | P8: 0 | Q8: 0 | R8: 0 | S8: 1099339.8 | T8: 185090 | U8: 0.16836469
A9: Mar | B9: 2636116.2 | C9: 1532995.3 | D9: 0.58153554 | E9: 30777.89 | F9: 4284.87 | G9: 0.1392191 | H9: 2666894.1 | I9: 1537280.1 | J9: 0.57643089 | L9: Mar | M9: 952578.01 | N9: 98425.613 | O9: 0.10332551 | P9: 0 | Q9: 0 | R9: 0 | S9: 952578.01 | T9: 98425.613 | U9: 0.10332551
A10: Apr | B10: 2112416.4 | C10: 1645020.2 | D10: 0.77873863 | E10: 38613.39 | F10: 16665.54 | G10: 0.43160002 | H10: 2151029.8 | I10: 1661685.8 | J10: 0.7725071 | L10: Apr | M10: 1216554.2 | N10: 131446.89 | O10: 0.10804853 | P10: 0 | Q10: 0 | R10: 0 | S10: 1216554.2 | T10: 131446.89 | U10: 0.10804853
A11: May | B11: 2695700.1 | C11: 1605401.8 | D11: 0.59554169 | E11: 163481.95 | F11: 31032.18 | G11: 0.18982022 | H11: 2859182.1 | I11: 1636434 | J11: 0.5723434 | L11: May | M11: 886917.18 | N11: 96862.18 | O11: 0.1092122 | P11: 45372 | Q11: 0 | R11: 0 | S11: 932289.18 | T11: 96862.18 | U11: 0.10389714
A12: Jun | B12: 2428765.8 | C12: 1129707.3 | D12: 0.46513638 | E12: 120395.29 | F12: 48524.65 | G12: 0.40304442 | H12: 2549161.1 | I12: 1178232 | J12: 0.46220381 | L12: Jun | M12: 1180769.1 | N12: 132576.29 | O12: 0.1122796 | P12: 0 | Q12: 0 | R12: 0 | S12: 1180769.1 | T12: 132576.29 | U12: 0.1122796
A13: Jul | B13: 2374302 | C13: 1350771.3 | D13: 0.568913 | E13: 502980.06 | F13: 411442.99 | G13: 0.81801054 | H13: 2877282.1 | I13: 1762214.3 | J13: 0.61245795 | L13: Jul | M13: 1083818.2 | N13: 112471.54 | O13: 0.10377344 | P13: 55775.12 | Q13: 6246.96 | R13: 0.11200263 | S13: 1139593.3 | T13: 118718.5 | U13: 0.1041762
A14: Aug | B14: 1960116.3 | C14: 1055441.8 | D14: 0.53845879 | E14: 462199.98 | F14: 405804.99 | G14: 0.87798574 | H14: 2422316.3 | I14: 1461246.8 | J14: 0.60324362 | L14: Aug | M14: 420238.97 | N14: 34938.3 | O14: 0.083139124 | P14: 986.01 | Q14: 0 | R14: 0 | S14: 421224.98 | T14: 34938.3 | U14: 0.082944511
A15: Grand Total | B15: 19186854 | C15: 11109995 | D15: 0.57904205 | E15: 1347604 | F15: 918887.27 | G15: 0.68186742 | H15: 20534458 | I15: 12028882 | J15: 0.58579012 | L15: Grand Total | M15: 7807252.8 | N15: 894283.12 | O15: 0.11454517 | P15: 102133.13 | Q15: 6246.96 | R15: 0.061164874 | S15: 7909385.9 | T15: 900530.08 | U15: 0.11385588
A17: Luca | B17: Old | E17: New | H17: Total Purchase | I17: Total Profit | J17: Total Margin | L17: Raffaella | M17: Old | P17: New | S17: Total Purchase | T17: Total Profit | U17: Total Margin
B18: Purchase | C18: Profit | D18: Margin | E18: Purchase | F18: Profit | G18: Margin | M18: Purchase | N18: Profit | O18: Margin | P18: Purchase | Q18: Profit | R18: Margin
A19: Jan | B19: 2792765.3 | C19: 382110.29 | D19: 0.13682148 | E19: 0 | F19: 0 | G19: 0 | H19: 2792765.3 | I19: 382110.29 | J19: 0.13682148 | L19: Jan | M19: 829570.02 | N19: 131800.38 | O19: 0.15887794 | P19: 9801.46 | Q19: 218.15 | R19: 0.022256888 | S19: 839371.48 | T19: 132018.53 | U19: 0.1572826
A20: Feb | B20: 2852746.8 | C20: 1847570.1 | D20: 0.64764604 | E20: 0 | F20: 0 | G20: 0 | H20: 2852746.8 | I20: 1847570.1 | J20: 0.64764604 | L20: Feb | M20: 1566070 | N20: 219347.4 | O20: 0.14006232 | P20: 8877.4 | Q20: 211.4 | R20: 0.023813279 | S20: 1574947.4 | T20: 219558.8 | U20: 0.13940706
A21: Mar | B21: 1893395.3 | C21: 737755.31 | D21: 0.38964673 | E21: 0 | F21: 0 | G21: 0 | H21: 1893395.3 | I21: 737755.31 | J21: 0.38964673 | L21: Mar | M21: 1271757.7 | N21: 186549.39 | O21: 0.14668627 | P21: 13170 | Q21: 340.4 | R21: 0.025846621 | S21: 1284927.7 | T21: 186889.79 | U21: 0.14544771
A22: Apr | B22: 2282257.4 | C22: 650898.67 | D22: 0.2851995 | E22: 1295.52 | F22: 0 | G22: 0 | H22: 2283552.9 | I22: 650898.67 | J22: 0.2850377 | L22: Apr | M22: 1478195.7 | N22: 275856.72 | O22: 0.18661719 | P22: 9643.2 | Q22: 1687.2 | R22: 0.17496267 | S22: 1487838.9 | T22: 277543.92 | U22: 0.18654165
A23: May | B23: 2678409.1 | C23: 674867.04 | D23: 0.25196563 | E23: 2932.52 | F23: 74.4 | G23: 0.025370671 | H23: 2681341.6 | I23: 674941.44 | J23: 0.25171781 | L23: May | M23: 1158977.8 | N23: 182799.24 | O23: 0.15772454 | P23: 90850.25 | Q23: 16113.66 | R23: 0.17736506 | S23: 1249828.1 | T23: 198912.9 | U23: 0.15915221
A24: Jun | B24: 2154404.3 | C24: 577277.63 | D24: 0.26795232 | E24: 38388.75 | F24: 7555.1 | G24: 0.19680505 | H24: 2192793.1 | I24: 584832.73 | J24: 0.26670676 | L24: Jun | M24: 1012399.3 | N24: 144398.61 | O24: 0.1426301 | P24: 49882 | Q24: 9275 | R24: 0.18593882 | S24: 1062281.3 | T24: 153673.61 | U24: 0.14466377
A25: Jul | B25: 3186268.8 | C25: 635277.72 | D25: 0.19937982 | E25: 45853.94 | F25: 22943.75 | G25: 0.50036594 | H25: 3232122.8 | I25: 658221.47 | J25: 0.2036499 | L25: Jul | M25: 1126515.5 | N25: 178770.31 | O25: 0.15869317 | P25: 70940.36 | Q25: 6287.07 | R25: 0.088624726 | S25: 1197455.8 | T25: 185057.38 | U25: 0.15454213
A26: Aug | B26: 1083001.5 | C26: 265513.77 | D26: 0.24516472 | E26: 43499.3 | F26: 9438.12 | G26: 0.21697177 | H26: 1126500.8 | I26: 274951.89 | J26: 0.24407606 | L26: Aug | M26: 358512.83 | N26: 54463.53 | O26: 0.15191515 | P26: 117255.76 | Q26: 10152.42 | R26: 0.08658355 | S26: 475768.59 | T26: 64615.95 | U26: 0.13581382
A27: Grand Total | B27: 18923249 | C27: 5771270.6 | D27: 0.30498308 | E27: 131970.03 | F27: 40011.37 | G27: 0.30318528 | H27: 19055219 | I27: 5811281.9 | J27: 0.30497062 | L27: Grand Total | M27: 8801998.8 | N27: 1373985.6 | O27: 0.15609927 | P27: 370420.43 | Q27: 44285.3 | R27: 0.11955415 | S27: 9172419.2 | T27: 1418270.9 | U27: 0.15462343

Sheet Buyer
A1: Countries | B1: Buyers | C1: Jan Purchases | D1: Jan Exp Profit | E1: Jan Exp Margin | F1: Feb Exp Purchases | G1: Feb Exp Profit | H1: Feb Exp Margin | I1: March Purchases | J1: April Purchases | K1: May Purchases | L1: June Purchases | M1: July Purchases | Q1: March Profit | R1: April Profit | S1: May Profit | T1: June Profit | U1: July Profit | Y1: March Margin | Z1: April Margin | AA1: May Margin | AB1: June Margin | AC1: July Margin | AE1: Total Purchase | AF1: Total Profit | AG1: % Margin
A2: Greece | B2: Louise | C2: 1348418.1 | D2: 204775.34 | E2: 0.15186338 | F2: 1671021.3 | G2: 254298.99 | H2: 0.15218178 | I2: 1698230.3 | J2: 1328070.8 | K2: 1501950.6 | L2: 1567569.8 | M2: 2104896.1 | Q2: 298948.72 | R2: 306208.71 | S2: 268511.22 | T2: 425100.79 | U2: 954907.05 | Y2: 0.17603544 | Z2: 0.23056655 | AA2: 0.17877501 | AB2: 0.27118461 | AC2: 0.45365995 | AE2: 11220157 | AF2: 2712750.8 | AG2: 0.24177477
A3: Spain | B3: Louise | C3: 869313.47 | D3: 1112376.1 | E3: 1.279603 | F3: 1119839.3 | G3: 1220338.9 | H3: 1.0897447 | I3: 968663.76 | J3: 822958.95 | K3: 1357231.5 | L3: 981591.34 | M3: 772386 | Q3: 1238331.4 | R3: 1355477.1 | S3: 1367922.8 | T3: 753131.19 | U3: 807307.21 | Y3: 1.2783914 | Z3: 1.6470774 | AA3: 1.0078772 | AB3: 0.76725533 | AC3: 1.0452121 | AE3: 6891984.3 | AF3: 7854884.7 | AG3: 1.1397131
A4: Louise Overall | C4: =SUM(C2:C3) -> 2217731.6 | D4: =SUM(D2:D3) -> 1317151.4 | E4: =D4/C4 -> 0.59391832 | F4: =SUM(F2:F3) -> 2790860.6 | G4: =SUM(G2:G3) -> 1474637.9 | H4: =G4/F4 -> 0.52838107 | I4: =SUM(I2:I3) -> 2666894.1 | J4: =SUM(J2:J3) -> 2151029.8 | K4: =SUM(K2:K3) -> 2859182.1 | L4: =SUM(L2:L3) -> 2549161.1 | M4: =SUM(M2:M3) -> 2877282.1 | Q4: =SUM(Q2:Q3) -> 1537280.1 | R4: =SUM(R2:R3) -> 1661685.8 | S4: =SUM(S2:S3) -> 1636434 | T4: =SUM(T2:T3) -> 1178232 | U4: =SUM(U2:U3) -> 1762214.3 | Y4: =Q4/I4 -> 0.57643089 | Z4: =R4/J4 -> 0.7725071 | AA4: =S4/K4 -> 0.5723434 | AB4: =T4/L4 -> 0.46220381 | AC4: =U4/M4 -> 0.61245795 | AE4: =SUM(AE2:AE3) -> 18112141 | AF4: =SUM(AF2:AF3) -> 10567635 | AG4: =AF4/AE4 -> 0.58345589
A5: Germany | B5: Luca | C5: 689392.21 | D5: 90575.727 | E5: 0.1313849 | F5: 874333.08 | G5: 69120.558 | H5: 0.079055179 | I5: 633817.21 | J5: 848412.21 | K5: 1299380.2 | L5: 1110479.7 | M5: 1919223.4 | Q5: 54206.657 | R5: 243255.91 | S5: 224595.89 | T5: 135560.24 | U5: 216728.3 | Y5: 0.085524116 | Z5: 0.28671901 | AA5: 0.17284848 | AB5: 0.12207358 | AC5: 0.112925 | AE5: 7375038 | AF5: 1034043.3 | AG5: 0.14020854
A6: France | B6: Luca | C6: 1290923.8 | D6: 157666.88 | E6: 0.12213493 | F6: 1157762.1 | G6: 136107.34 | H6: 0.11756071 | I6: 389072.31 | J6: 843019.2 | K6: 596988.12 | L6: 487012.9 | M6: 748452.82 | Q6: 97409.897 | R6: 109734.36 | S6: 122776.52 | T6: 76885.23 | U6: 144509.66 | Y6: 0.25036451 | Z6: 0.13016828 | AA6: 0.2056599 | AB6: 0.15787103 | AC6: 0.19307785 | AE6: 5513231.3 | AF6: 845089.89 | AG6: 0.15328395
A7: Italy | B7: Luca | C7: 699480.78 | D7: 129956.12 | E7: 0.18578941 | F7: 702747.14 | G7: 1626794.7 | H7: 2.3149076 | I7: 778492.87 | J7: 345734.45 | K7: 746345.05 | L7: 385516.58 | M7: 452901.31 | Q7: 580317.25 | R7: 288550.55 | S7: 326500.82 | T7: 361160.14 | U7: 289965.27 | Y7: 0.74543682 | Z7: 0.83460167 | AA7: 0.43746632 | AB7: 0.93682129 | AC7: 0.64023942 | AE7: 4111218.2 | AF7: 3603244.9 | AG7: 0.87644214
A8: AUSTRIA | B8: Luca | C8: 112968.55 | D8: 3911.56 | E8: 0.034625212 | F8: 117904.44 | G8: 15547.54 | H8: 0.1318656 | I8: 92012.96 | J8: 246387.05 | K8: 38628.2 | L8: 209783.88 | M8: 111545.29 | Q8: 5821.51 | R8: 9357.85 | S8: 1068.21 | T8: 11227.12 | U8: 7018.24 | Y8: 0.06326837 | Z8: 0.037980283 | AA8: 0.027653631 | AB8: 0.053517553 | AC8: 0.0629183 | AE8: 929230.37 | AF8: 53952.03 | AG8: 0.058060984
A9: Luca Overall | C9: =SUM(C5:C8) -> 2792765.3 | D9: =SUM(D5:D8) -> 382110.29 | E9: =D9/C9 -> 0.13682148 | F9: =SUM(F5:F8) -> 2852746.8 | G9: =SUM(G5:G8) -> 1847570.1 | H9: =G9/F9 -> 0.64764604 | I9: =SUM(I5:I8) -> 1893395.4 | J9: =SUM(J5:J8) -> 2283552.9 | K9: =SUM(K5:K8) -> 2681341.6 | L9: =SUM(L5:L8) -> 2192793.1 | M9: =SUM(M5:M8) -> 3232122.8 | Q9: =SUM(Q5:Q8) -> 737755.31 | R9: =SUM(R5:R8) -> 650898.67 | S9: =SUM(S5:S8) -> 674941.44 | T9: =SUM(T5:T8) -> 584832.73 | U9: =SUM(U5:U8) -> 658221.47 | Y9: =Q9/I9 -> 0.38964673 | Z9: =R9/J9 -> 0.2850377 | AA9: =S9/K9 -> 0.25171781 | AB9: =T9/L9 -> 0.26670676 | AC9: =U9/M9 -> 0.2036499 | AE9: =SUM(AE5:AE8) -> 17928718 | AF9: =SUM(AF5:AF8) -> 5536330.1 | AG9: =AF9/AE9 -> 0.30879676
A10: BELGIUM | B10: Manisha | C10: 565878.71 | D10: 43869.88 | E10: 0.077525235 | F10: 334443.8 | G10: 31337.35 | H10: 0.093699898 | I10: 348441.23 | J10: 437652.65 | K10: 264467.18 | L10: 454879.04 | M10: 416539.09 | Q10: 39180.903 | R10: 45642.36 | S10: 22343.35 | T10: 38409.76 | U10: 30916.61 | Y10: 0.11244623 | Z10: 0.10428901 | AA10: 0.084484396 | AB10: 0.084439503 | AC10: 0.07422259 | AE10: 2822301.7 | AF10: 251700.21 | AG10: 0.089182603
A11: Portugal | B11: Manisha | C11: 185239.91 | D11: 9316.75 | E11: 0.050295587 | F11: 347838.17 | G11: 39869.23 | H11: 0.11462005 | I11: 313794.71 | J11: 500964.01 | K11: 329070.9 | L11: 316846.67 | M11: 350975.54 | Q11: 27554.45 | R11: 51581.96 | S11: 34022.22 | T11: 28164.36 | U11: 33021.44 | Y11: 0.087810435 | Z11: 0.1029654 | AA11: 0.10338872 | AB11: 0.088889557 | AC11: 0.094084733 | AE11: 2344729.9 | AF11: 223530.41 | AG11: 0.095333117
A12: Ireland | B12: Manisha | C12: 106570.25 | D12: 37231.05 | E12: 0.34935688 | F12: 226334.75 | G12: 39325.23 | H12: 0.17374809 | I12: 154125.27 | J12: 174009.29 | K12: 291469.66 | L12: 164044.43 | M12: 256625.49 | Q12: 12121.79 | R12: 26002.74 | S12: 34797.7 | T12: 44610.84 | U12: 29927.63 | Y12: 0.078648946 | Z12: 0.14943306 | AA12: 0.11938704 | AB12: 0.27194364 | AC12: 0.11661987 | AE12: 1373179.1 | AF12: 224016.98 | AG12: 0.16313748
A13: Netherland | B13: Manisha | C13: 56810.73 | D13: 9372.52 | E13: 0.16497799 | F13: 174389.27 | G13: 72887.09 | H13: 0.41795628 | I13: 102890.18 | J13: 59261.72 | K13: 16707.14 | L13: 201000.12 | M13: 115453.22 | Q13: 17631.05 | R13: 4226.3 | S13: 1962.41 | T13: 17589.23 | U13: 24852.82 | Y13: 0.17135795 | Z13: 0.071315851 | AA13: 0.11745936 | AB13: 0.087508555 | AC13: 0.21526312 | AE13: 726512.38 | AF13: 148521.42 | AG13: 0.20443068
A14: Norway | B14: Manisha | C14: 52537.67 | D14: 2682.11 | E14: 0.051051179 | F14: 16333.8 | G14: 1671.1 | H14: 0.10230932 | I14: 33326.62 | J14: 44666.55 | K14: 30574.3 | L14: 43998.88 | Q14: 1937.42 | R14: 3993.53 | S14: 3736.5 | T14: 3802.1 | U14: 0 | Y14: 0.058134308 | Z14: 0.089407622 | AA14: 0.12221048 | AB14: 0.086413563 | AC14: 0 | AE14: 221437.82 | AF14: 17822.76 | AG14: 0.080486522
A15: Manisha Overall | C15: =SUM(C10:C14) -> 967037.27 | D15: =SUM(D10:D14) -> 102472.31 | E15: =D15/C15 -> 0.10596521 | F15: =SUM(F10:F14) -> 1099339.8 | G15: =SUM(G10:G14) -> 185090 | H15: =G15/F15 -> 0.16836469 | I15: =SUM(I10:I14) -> 952578.01 | J15: =SUM(J10:J14) -> 1216554.2 | K15: =SUM(K10:K14) -> 932289.18 | L15: =SUM(L10:L14) -> 1180769.1 | M15: =SUM(M10:M14) -> 1139593.3 | Q15: =SUM(Q10:Q14) -> 98425.613 | R15: =SUM(R10:R14) -> 131446.89 | S15: =SUM(S10:S14) -> 96862.18 | T15: =SUM(T10:T14) -> 132576.29 | U15: =SUM(U10:U14) -> 118718.5 | Y15: =Q15/I15 -> 0.10332551 | Z15: =R15/J15 -> 0.10804853 | AA15: =S15/K15 -> 0.10389714 | AB15: =T15/L15 -> 0.1122796 | AC15: =U15/M15 -> 0.1041762 | AE15: =SUM(AE10:AE14) -> 7488160.9 | AF15: =SUM(AF10:AF14) -> 865591.78 | AG15: =AF15/AE15 -> 0.11559471
A16: CZECH REPUBLIC | B16: Raffaella | C16: 223714.27 | D16: 46112.63 | E16: 0.20612288 | F16: 551042.65 | G16: 82877.4 | H16: 0.15040106 | I16: 567255.15 | J16: 462186.74 | K16: 376598.21 | L16: 339443.82 | M16: 228085.77 | Q16: 100039.27 | R16: 111510.59 | S16: 63744.68 | T16: 47326.69 | U16: 38644.37 | Y16: 0.17635674 | Z16: 0.24126739 | AA16: 0.16926443 | AB16: 0.13942422 | AC16: 0.16942911 | AE16: 2748326.6 | AF16: 490255.63 | AG16: 0.17838332
A17: Romania | B17: Raffaella | C17: 336338.56 | D17: 52520.12 | E17: 0.15615254 | F17: 418981.91 | G17: 59643.33 | H17: 0.142353 | I17: 234450.81 | J17: 423738.2 | K17: 400099.48 | L17: 220333.99 | M17: 332719.54 | Q17: 48836.63 | R17: 101000.43 | S17: 44988.81 | T17: 23395.51 | U17: 39895.78 | Y17: 0.20830224 | Z17: 0.23835573 | AA17: 0.11244406 | AB17: 0.10618203 | AC17: 0.11990814 | AE17: 2366662.5 | AF17: 370280.61 | AG17: 0.15645687
A18: BULGARIA | B18: Raffaella | C18: 99498.57 | D18: 10798.51 | E18: 0.1085293 | F18: 224850.44 | G18: 18667.36 | H18: 0.08302123 | I18: 83351.22 | J18: 249448.26 | K18: 179216.94 | L18: 275950.48 | M18: 140532.5 | Q18: 4588.13 | R18: 16763.5 | S18: 12713.93 | T18: 16744.42 | U18: 10355.21 | Y18: 0.055045745 | Z18: 0.067202313 | AA18: 0.070941564 | AB18: 0.060679075 | AC18: 0.073685518 | AE18: 1252848.4 | AF18: 90631.06 | AG18: 0.072340005
A19: SLOVEKIA | B19: Raffaella | C19: 73053.9 | D19: 1498.33 | E19: 0.020509925 | F19: 45401.3 | G19: 1331.33 | H19: 0.02932361 | I19: 84981.08 | J19: 110704.08 | K19: 91250.3 | L19: 68344.15 | M19: 82738.37 | Q19: 2245.94 | R19: 2775.93 | S19: 3410.43 | T19: 3045.13 | U19: 4462.57 | Y19: 0.026428706 | Z19: 0.025075228 | AA19: 0.037374452 | AB19: 0.044555825 | AC19: 0.053935919 | AE19: 556473.18 | AF19: 18769.66 | AG19: 0.033729676
A20: Poland | B20: Raffaella | C20: 9105 | D20: 4778 | E20: 0.52476661 | F20: 132859.78 | G20: 34424.26 | H20: 0.25910219 | I20: 152526.48 | J20: 58890.42 | K20: 47394.17 | L20: 43426 | M20: 79047.98 | Q20: 23074.4 | R20: 29558.48 | S20: 27862.36 | T20: 20600.2 | U20: 16710.82 | Y20: 0.15128127 | Z20: 0.5019234 | AA20: 0.58788581 | AB20: 0.4743748 | AC20: 0.21140097 | AE20: 523249.83 | AF20: 157008.52 | AG20: 0.30006416
A21: Hungary | B21: Raffaella | C21: 61919.56 | D21: 12601.54 | E21: 0.20351469 | F21: 57670.46 | G21: 7257.89 | H21: 0.12585109 | I21: 64466.79 | J21: 88777.79 | K21: 28039.54 | L21: 35702 | M21: 63773.95 | Q21: 2763.4 | R21: 3752.34 | S21: 1401.35 | T21: 1919.05 | U21: 4594.29 | Y21: 0.042865482 | Z21: 0.042266653 | AA21: 0.049977639 | AB21: 0.053751891 | AC21: 0.07204023 | AE21: 400350.09 | AF21: 34289.86 | AG21: 0.085649687
A22: Republic of Lithuania | B22: Raffaella | C22: 3319 | D22: 846 | E22: 0.25489605 | F22: 61177.6 | G22: 11276.6 | H22: 0.18432564 | I22: 75704.95 | J22: 46539.73 | K22: 53117.4 | L22: 21231.83 | M22: 110265.92 | Q22: 4233.39 | R22: 5247.45 | S22: 4490.2 | T22: 18499.81 | U22: 24089.1 | Y22: 0.055919593 | Z22: 0.11275205 | AA22: 0.084533505 | AB22: 0.87132433 | AC22: 0.21846369 | AE22: 371356.43 | AF22: 68682.55 | AG22: 0.18495048
A23: SLOVENIA | B23: Raffaella | C23: 21028.32 | D23: 1737.1 | E23: 0.082607645 | F23: 15714.72 | G23: 874.5 | H23: 0.055648462 | I23: 13432.47 | J23: 23852.26 | K23: 43224.72 | L23: 32082.9 | M23: 115147.84 | Q23: 831.78 | R23: 1192.38 | S23: 8109.66 | T23: 1363 | U23: 10422.8 | Y23: 0.061923086 | Z23: 0.049990232 | AA23: 0.18761625 | AB23: 0.042483691 | AC23: 0.090516678 | AE23: 264483.23 | AF23: 24531.22 | AG23: 0.092751514
A24: Latvia | B24: Raffaella | C24: 10813.8 | D24: 1039.3 | E24: 0.096108676 | F24: 67248.59 | G24: 3206.13 | H24: 0.047675795 | I24: 8758.75 | J24: 23701.38 | K24: 30306.79 | L24: 24618.6 | M24: 43855.67 | Q24: 276.85 | R24: 5742.82 | S24: 32077.48 | T24: 20540.8 | U24: 35613.74 | Y24: 0.031608392 | Z24: 0.24229897 | AA24: 1.0584255 | AB24: 0.83436101 | AC24: 0.81206695 | AE24: 209303.58 | AF24: 98497.12 | AG24: 0.47059453
A25: Croatia | B25: Raffaella | C25: 580.5 | D25: 87 | E25: 0.1498708 | H25: 0 | K25: 580.5 | L25: 1147.5 | M25: 1288.3 | S25: 114 | T25: 239 | U25: 268.7 | Y25: 0 | Z25: 0 | AA25: 0.19638243 | AB25: 0.20827887 | AC25: 0.20856943 | AE25: 3596.8 | AF25: 708.7 | AG25: 0.19703625
A26: Raffaella Overall | C26: =SUM(C16:C25) -> 839371.48 | D26: =SUM(D16:D25) -> 132018.53 | E26: =D26/C26 -> 0.1572826 | F26: =SUM(F16:F25) -> 1574947.5 | G26: =SUM(G16:G25) -> 219558.8 | H26: =G26/F26 -> 0.13940706 | I26: =SUM(I16:I25) -> 1284927.7 | J26: =SUM(J16:J25) -> 1487838.9 | K26: =SUM(K16:K25) -> 1249828 | L26: =SUM(L16:L25) -> 1062281.3 | M26: =SUM(M16:M25) -> 1197455.8 | Q26: =SUM(Q16:Q25) -> 186889.79 | R26: =SUM(R16:R25) -> 277543.92 | S26: =SUM(S16:S25) -> 198912.9 | T26: =SUM(T16:T25) -> 153673.61 | U26: =SUM(U16:U25) -> 185057.38 | Y26: =Q26/I26 -> 0.14544771 | Z26: =R26/J26 -> 0.18654165 | AA26: =S26/K26 -> 0.15915221 | AB26: =T26/L26 -> 0.14466377 | AC26: =U26/M26 -> 0.15454213 | AE26: =SUM(AE16:AE25) -> 8696650.7 | AF26: =SUM(AF16:AF25) -> 1353654.9 | AG26: =AF26/AE26 -> 0.15565244
A27: All Buyer Overall | C27: 6816905.7 | D27: 1933752.6 | F27: 8317894.6 | G27: 3726856.9 | I27: 6797795.2 | J27: 7138975.8 | K27: 7722640.9 | L27: 6985004.6 | M27: 8446454 | Q27: 2560350.9 | R27: 2721575.2 | S27: 2607150.5 | T27: 2049314.6 | U27: 2724211.6 | AE27: 52225671 | AF27: 18323212 | AG27: =AF27/AE27 -> 0.35084685

Sheet New License
A1: Country | B1: Buyer | C1: Lax Part No | D1: Description | E1: Country | F1: Granted Date | G1: Buying Comments | H1: Remarks
A2: France | B2: Luca | C2: L1503 | D2: Ontozry 200mg Tabs 28 | E2: France | F2: 46062 | G2: In Labelling / On Order | H2: No Stock Received | J2: CountryWise Bifurcation | M2: Status Till Jul'26
A3: Ireland | B3: Manisha | D3: Vagifem 10 micrograms vaginal tablets | E3: Ireland | F3: 46066 | G3: Price Issue | H3: No Stock Received | J3: Country | K3: No of Products | M3: Remarks | N3: No of Products
A4: Spain | B4: Louise | C4: 5028 | D4: Cholestagel 625mg Tablets 180 | E4: Spain | F4: 46079 | G4: Price Issue | H4: No Stock Received | J4: Austria | K4: 2 | M4: MAH Objection | N4: 0
A5: Spain | B5: Louise | C5: 360 | D5: Ontozry 50mg Tabs 28 | E5: Spain | F5: 46101 | G5: In Labelling / On Order | H5: No Stock Received | J5: BULGARIA | K5: 1 | M5: Price Issue | N5: 3
A6: Spain | B6: Louise | C6: 5029 | D6: Wynzora cream 0.5mg/g 60 | E6: Spain | F6: 46086 | G6: In Labelling / On Order | H6: No Stock Received | J6: Czech Republic | K6: 2 | M6: Variation | N6: 3
A7: Spain | B7: Louise | C7: 5040 | D7: Vesicare oral suspension 1mg/ml 1's | E7: Spain | F7: 46101 | G7: In Labelling / On Order | H7: No Stock Received | J7: France | K7: 9 | M7: Not On Order | N7: 4
A8: Greece | B8: Louise | C8: 163 | D8: Bicalutamide 50mg Tablets 28 | E8: Greece | F8: 46090 | G8: In Labelling / On Order | H8: No Stock Received | J8: France | K8: 2 | M8: Awaiting MAH | N8: 7
A9: France | B9: Luca | C9: L1515 | D9: Ontozry 150mg Tabs 28 | E9: France | F9: 46106 | G9: In Labelling / On Order | H9: No Stock Received | J9: Germany | K9: 2 | M9: In Labelling / On Order | N9: 26
A10: Spain | B10: Louise | C10: L7128 | D10: Lenzetto transdermal spray 1.53mg 1's | E10: Spain | F10: 46108 | G10: Not On Order | H10: No Stock Received | J10: Greece | K10: 16 | M10: Stock Received | N10: 32
A11: Poland | B11: Raffaella | C11: 1101 | D11: XONVEA 10mg/10mg tablets 20 | E11: Poland | F11: 46106 | G11: In Labelling / On Order | H11: No Stock Received | J11: Holland | K11: 2 | M11: Grand Total | N11: 75
A12: Italy | B12: Luca | C12: 5248 | D12: Stalevo® 75 mg/18,75 mg/200 mg compresse rivestite con film | E12: Italy | F12: 46121 | G12: In Labelling / On Order | H12: No Stock Received | J12: Ireland | K12: 5
A13: Germany | B13: Luca | C13: 5296 | D13: Flutiform 250mcg/dose & 10mcg/dose Inhaler 120doses | E13: Germany | F13: 46142 | G13: In Labelling / On Order | H13: No Stock Received | J13: Italy | K13: 2
A14: Greece | B14: Louise | C14: 6813 | D14: TOSTRAN 2% Gel x 60g | E14: Greece | F14: 46126 | G14: Variation | H14: No Stock Received | J14: Lithuania | K14: 1
A15: Spain | B15: Louise | C15: 8500 | D15: Elvanse Capsules 50mg 28s | E15: Spain | F15: 46134 | G15: Variation | H15: No Stock Received | J15: Netherlands | K15: 8
A16: Spain | B16: Louise | D16: Vazkepa® 998 mg cápsulas blandas | E16: Spain | F16: 46113 | G16: Not On Order | H16: No Stock Received | J16: Poland | K16: 1
A17: Austria | B17: Luca | D17: Seroquel XL 200 mg prolonged-release tablets | E17: Austria | F17: 46170 | G17: MAH Objection | H17: No Stock Received | J17: Portugal | K17: 3
A18: Austria | B18: Luca | D18: Seroquel XL 300 mg prolonged-release tablets | E18: Austria | F18: 46170 | G18: MAH Objection | H18: No Stock Received | J18: ROMANIA | K18: 5
A19: France | B19: Luca | C19: M0006 | D19: TRULICITY Solution for Injection PF Pen 0.75mg x 4's | E19: France | F19: 46156 | G19: Not On Order | H19: No Stock Received | J19: Spain | K19: 14
A20: Germany | B20: Luca | C20: 2366 | D20: Xadago tablets f/c 100 mg 30s | E20: Germany | F20: 46148 | G20: Price Issue | H20: No Stock Received | J20: Grand Total | K20: 75
A21: Greece | B21: Louise | C21: 5045 | D21: Neupro 1 mg/24 h transdermal patch | E21: Greece | F21: 46161 | G21: Not On Order | H21: No Stock Received
A22: Lithuania | B22: Raffaella | C22: 5175C | D22: Creon 25000 Gastroresistant Capsules 50 | E22: Lithuania | F22: 46162 | G22: In Labelling / On Order | H22: No Stock Received
A23: Ireland | B23: Manisha | C23: 5670B | D23: CLOPIXOL DEPOT INJECTION 200 MG/ML AMP 1ML | E23: Ireland | F23: 46157 | G23: In Labelling / On Order | H23: No Stock Received
A24: Romania | B24: Raffaella | C24: M0310 | D24: TRULICITY Solution for Injection PF Pens 1.5mg x 4's | E24: Romania | F24: 46156 | G24: In Labelling / On Order | H24: No Stock Received
A25: Spain | B25: Louise | C25: 5045 | D25: Neupro 1 mg/24 h transdermal patch | E25: Spain | F25: 46160 | G25: Not On Order | H25: No Stock Received
A26: Romania | B26: Raffaella | C26: 1237 | D26: Symbicort 200mcg/6mcg Pressurised inhaler 120 doses | E26: Romania | F26: 46195 | G26: In Labelling / On Order | H26: No Stock Received
A27: Portugal | B27: Manisha | C27: 5426 | D27: Ropinirole 2mg Filmcoated Tablets 84 | E27: Portugal | F27: 46184 | G27: In Labelling / On Order | H27: No Stock Received
A28: Netherlands | B28: Manisha | C28: 5591 | D28: Tranylcypromine 10mg Film-coated Tablets | E28: Netherlands | F28: 46184 | G28: In Labelling / On Order | H28: No Stock Received
A29: Greece | B29: Louise | C29: L0239J | D29: Canesten 500mg Pessary | E29: Greece | F29: 46177 | G29: In Labelling / On Order | H29: No Stock Received
A30: Greece | B30: Louise | C30: M0108 | D30: NovoRapid 100 units/ml solution for injection in vial | E30: Greece | F30: 46197 | G30: In Labelling / On Order | H30: No Stock Received
A31: Ireland | B31: Manisha | C31: 5458 | D31: Oestrogel (0.06%) 80g Pump Pack 64 | E31: Ireland | F31: 46185 | G31: In Labelling / On Order | H31: No Stock Received
A32: Ireland | B32: Manisha | C32: 2548B | D32: BuTrans 15 micrograms/hour transdermal patch | E32: Ireland | F32: 46178 | G32: In Labelling / On Order | H32: No Stock Received
A33: Ireland | B33: Manisha | C33: 5727A | D33: Resolor 2mg film-coated tablets | E33: Ireland | F33: 46195 | G33: Price Issue | H33: No Stock Received
A34: Czech Republic | B34: Raffaella | C34: 5337A | D34: Tresiba Flextouch 200u/ml Injection 3mlx3 | E34: Czech Republic | F34: 46178 | G34: In Labelling / On Order | H34: No Stock Received
A35: Netherlands | B35: Manisha | C35: 170 | D35: BuTrans 5mcg/hr transdermal patch | E35: Netherlands | F35: 46178 | G35: In Labelling / On Order | H35: No Stock Received
A36: Netherlands | B36: Manisha | C36: 294 | D36: BuTrans 10mcg/hr transdermal patch | E36: Netherlands | F36: 46178 | G36: In Labelling / On Order | H36: No Stock Received
A37: Netherlands | B37: Manisha | C37: 5458 | D37: Oestrogel Pump-Pack 750 micrograms/actuation Gel | E37: Netherlands | F37: 46203 | G37: In Labelling / On Order | H37: No Stock Received
A38: Netherlands | B38: Manisha | C38: 6031 | D38: BuTrans 20mcg/hr transdermal patch | E38: Netherlands | F38: 46178 | G38: In Labelling / On Order | H38: No Stock Received
A39: Netherlands | B39: Manisha | C39: 6001B | D39: Monuril 3g Granules Sachets 3g | E39: Netherlands | F39: 46192 | G39: In Labelling / On Order | H39: No Stock Received
A40: Greece | B40: Louise | C40: M0310 | D40: TRULICITY Solution for Injection PF Pens 1.5mg x 4's | E40: Greece | F40: 46185 | G40: In Labelling / On Order | H40: No Stock Received
A41: France | B41: Luca | C41: L0599 | D41: Nicorette Invisi 25mg Patch | E41: France | F41: 46224 | G41: Awaiting MAH | H41: No Stock Received
A42: France | B42: Luca | C42: L7129 | D42: Lyumjev 100 units/mL solution for injection in vial | E42: France | F42: 46206 | G42: Awaiting MAH | H42: No Stock Received
A43: France | B43: Luca | C43: M0411 | D43: EpiPen Jr. Auto-Injector 0.15mg | E43: France | F43: 46223 | G43: Awaiting MAH | H43: No Stock Received
A44: Netherlands | B44: Manisha | C44: M2487 | D44: Toujeo 300 units/ml SoloStar, solution for injection in a pre-filled pen | E44: Netherlands | F44: 46224 | G44: Awaiting MAH | H44: No Stock Received
A45: Portugal | B45: Manisha | C45: M0311 | D45: EpiPen® Auto-Injector 0.3mg | E45: Portugal | F45: 46225 | G45: Awaiting MAH | H45: No Stock Received
A46: Portugal | B46: Manisha | C46: M0411 | D46: EpiPen® Jr. Auto-Injector 0.15mg | E46: Portugal | F46: 46223 | G46: Awaiting MAH | H46: No Stock Received
A47: ROMANIA | B47: Raffaella | C47: M2487 | D47: Toujeo Sol. Inj. P/F doublestar pens 300iu/ml 3mlx3 | E47: ROMANIA | F47: 46224 | G47: Variation | H47: No Stock Received
A48: Spain | B48: Louise | C48: 927 | D48: REQUIP 5MG FILM-COATED TABLETS | E48: Spain | F48: 46225 | G48: Awaiting MAH | H48: No Stock Received
A49: Spain | B49: Louise | D49: Calcichew-D3 1000mg/800IU Once Daily chewable tablets | E49: Spain | F49: 46217 | G49: Awaiting MAH | H49: No Stock Received

Sheet Sales
A1: AVG
A2: Regular Lines | E2: Jan to Aug New Lines | I2: Overall PI
A3: Month | B3: Sales | C3: Profit | D3: % | E3: Sales | F3: Profit | G3: % | I3: Month | J3: Sales | K3: Profit | L3: %
A4: Jan | B4: 430351.95 | C4: 41838.883 | D4: 0.097220155 | E4: 25377.101 | F4: 2118.5485 | G4: 0.083482684 | I4: Jan | J4: =B4+E4 -> 455729.05 | K4: =C4+F4 -> 43957.432 | L4: =K4/J4 -> 0.096455189
A5: Feb | B5: 423523.45 | C5: 43051.943 | D5: 0.10165185 | E5: 36198.542 | F5: 2065.156 | G5: 0.057050806 | I5: Feb | J5: =B5+E5 -> 459721.99 | K5: =C5+F5 -> 45117.099 | L5: =K5/J5 -> 0.098139962
A6: Mar | B6: 453932.28 | C6: 47647.482 | D6: 0.10496606 | E6: 45983.651 | F6: 2906.8761 | G6: 0.063215426 | I6: Mar | J6: =B6+E6 -> 499915.93 | K6: =C6+F6 -> 50554.358 | L6: =K6/J6 -> 0.10112572
A7: Apr | B7: 472463.06 | C7: 55662.929 | D7: 0.11781435 | E7: 50116.838 | F7: 3088.1085 | G7: 0.061618183 | I7: Apr | J7: =B7+E7 -> 522579.9 | K7: =C7+F7 -> 58751.038 | L7: =K7/J7 -> 0.11242499
A8: May | B8: 483690.46 | C8: 58984.246 | D8: 0.12194627 | E8: 64766.922 | F8: 4655.3074 | G8: 0.071877854 | I8: May | J8: =B8+E8 -> 548457.39 | K8: =C8+F8 -> 63639.554 | L8: =K8/J8 -> 0.11603373
A9: June | B9: 466213.94 | C9: 57529.83 | D9: 0.12339792 | E9: 67126.459 | F9: 5297.5973 | G9: 0.07891966 | I9: June | J9: =B9+E9 -> 533340.4 | K9: =C9+F9 -> 62827.427 | L9: =K9/J9 -> 0.11779986
A10: July | B10: 482720.96 | C10: 54189.387 | D10: 0.1122582 | E10: 74922.156 | F10: 7609.4641 | G10: 0.10156494 | I10: July | J10: =B10+E10 -> 557643.12 | K10: =C10+F10 -> 61798.851 | L10: =K10/J10 -> 0.11082151
A11: Aug | B11: 495741.37 | C11: 55291.387 | D11: 0.11153273 | E11: 72208.684 | F11: 9952.0118 | G11: 0.13782292 | I11: Aug | J11: =B11+E11 -> 567950.06 | K11: =C11+F11 -> 65243.399 | L11: =K11/J11 -> 0.11487524

Sheet 15% PCA
E1: Daily | H1: MTD | K1: PCA Achievement
A2: catalog_no | B2: Part_description | C2: Category | D2: Current Stock | E2: Daily PCA | F2: QTY | G2: Diff | H2: 15% PCA | I2: MTD QTY | J2: Diff | K2: MTD % | L2: Daily %
A3: 5282A | B3: Janumet 50mg/1g Tablets 56 | C3: Parallel Import | D3: 850 | E3: 5 | F3: -1 | G3: =F3-E3 -> -6 | H3: 100 | I3: 895 | J3: =I3-H3 -> 795 | K3: =I3/H3 -> 8.95 | L3: =F3/E3 -> -0.2
A4: 1110F | B4: Valsartan 160mg / HCZ12.5mg Tabs 28 (PI) | C4: Generic to PI | D4: 0 | E4: 10 | F4: 0 | G4: =F4-E4 -> -10 | H4: 200 | I4: 0 | J4: =I4-H4 -> -200 | K4: =I4/H4 -> 0 | L4: =F4/E4 -> 0
A5: 5481A | B5: Dosulepin 75mg Tabs PI - 28s | C5: Generic to PI | D5: 0 | E5: 66 | F5: 0 | G5: =F5-E5 -> -66 | H5: 1320 | I5: 2 | J5: =I5-H5 -> -1318 | K5: =I5/H5 -> 0.0015151515 | L5: =F5/E5 -> 0
A6: 1062 | B6: Calcipotriol 50mcg Ointment 30g (PI) | C6: Generic to PI | D6: 0 | E6: 72 | F6: 0 | G6: =F6-E6 -> -72 | H6: 1440 | I6: 5 | J6: =I6-H6 -> -1435 | K6: =I6/H6 -> 0.0034722222 | L6: =F6/E6 -> 0
A7: 5390 | B7: Lamictal 200mg Tablets 30 | C7: Parallel Import | D7: 0 | E7: 23 | F7: 0 | G7: =F7-E7 -> -23 | H7: 460 | I7: 2 | J7: =I7-H7 -> -458 | K7: =I7/H7 -> 0.0043478261 | L7: =F7/E7 -> 0
A8: 0739 | B8: Lamotrigine 100mg Dispersible Tablets 56 (PI) | C8: Generic to PI | D8: 597 | E8: 57 | F8: 0 | G8: =F8-E8 -> -57 | H8: 1140 | I8: 7 | J8: =I8-H8 -> -1133 | K8: =I8/H8 -> 0.0061403509 | L8: =F8/E8 -> 0
A9: 4989D | B9: Co-Trimoxazole 40/200mg/5ml Oral Suspension SF 100ml | C9: Generic to PI | D9: 299 | E9: 8 | F9: 0 | G9: =F9-E9 -> -8 | H9: 160 | I9: 1 | J9: =I9-H9 -> -159 | K9: =I9/H9 -> 0.00625 | L9: =F9/E9 -> 0
A10: 5963N | B10: Arcoxia 90mg Tablets 14 | C10: Parallel Import | D10: 0 | E10: 2 | F10: 0 | G10: =F10-E10 -> -2 | H10: 40 | I10: 1 | J10: =I10-H10 -> -39 | K10: =I10/H10 -> 0.025 | L10: =F10/E10 -> 0
A11: 5578A | B11: Trileptal 300mg Tablets 50 | C11: Parallel Import | D11: 0 | E11: 2 | F11: 0 | G11: =F11-E11 -> -2 | H11: 40 | I11: 1 | J11: =I11-H11 -> -39 | K11: =I11/H11 -> 0.025 | L11: =F11/E11 -> 0
A12: 5680K | B12: Ropinirole Tablets 0.25mg 12 (PI) | C12: Generic to PI | D12: 0 | E12: 48 | F12: 0 | G12: =F12-E12 -> -48 | H12: 960 | I12: 29 | J12: =I12-H12 -> -931 | K12: =I12/H12 -> 0.030208333 | L12: =F12/E12 -> 0
A13: L6002 | B13: Nustendi tablets 180mg/10mg 28 | C13: Parallel Import | D13: 0 | E13: 404 | F13: 0 | G13: =F13-E13 -> -404 | H13: 8080 | I13: 297 | J13: =I13-H13 -> -7783 | K13: =I13/H13 -> 0.036757426 | L13: =F13/E13 -> 0
A14: 3654 | B14: Mefenamic Acid 500mg Tablets 30 | C14: Generic to PI | D14: 5 | E14: 150 | F14: 0 | G14: =F14-E14 -> -150 | H14: 3000 | I14: 137 | J14: =I14-H14 -> -2863 | K14: =I14/H14 -> 0.045666667 | L14: =F14/E14 -> 0
... A57: 5430C | B57: Utrogestan Vaginal 200mg Capsules (21) | C57: Parallel Import | D57: 260 | E57: 8 | F57: 35 | G57: =F57-E57 -> 27 | H57: 160 | I57: 640 | J57: =I57-H57 -> 480 | K57: =I57/H57 -> 4 | L57: =F57/E57 -> 4.375

Sheet Overstock
A1: Code | B1: Description | C1: Category | D1: Stock | E1: True Cost | F1: Stock Value | G1: No Of Days Stock
A2: 5119C | B2: Onbrez Inhaler 300mcg 30 Capsules+1 Inhaler | C2: Parallel Import | D2: 427 | E2: 19.46 | F2: 8309.42 | G2: 421
A3: 5679 | B3: Zyprexa 20mg Velotabs 28 | C3: Parallel Import | D3: 442 | E3: 31.29 | F3: 13830.18 | G3: 351
A4: 5193A | B4: CoDiovan 80mg/12.5mg Tablets 28 | C4: Parallel Import | D4: 421 | E4: 4.45 | F4: 1873.45 | G4: 136
A5: 5282B | B5: Januvia 25mg Tablets 28 | C5: Parallel Import | D5: 539 | E5: 11.5 | F5: 6198.5 | G5: 135
A6: 5213 | B6: Frumil 40mg/5mg Tablets 28 | C6: Parallel Import | D6: 6819 | E6: 3.61 | F6: 24616.59 | G6: 128
A7: 5855 | B7: Zyprexa 5mg Velotabs 28 | C7: Parallel Import | D7: 471 | E7: 9.03 | F7: 4253.13 | G7: 118
A8: 5613B | B8: Requip XL 8mg Tablets 28 | C8: Parallel Import | D8: 919 | E8: 19.69 | F8: 18095.11 | G8: 115
A9: D0396A | B9: FreeStyle Lite Testing Strips 50 | C9: Parallel Import | D9: 3981 | E9: 8.84 | F9: 35192.04 | G9: 104

Sheet Additional Watch Sales
I2: OVERALL
I4: Sales Analysis | R4: Sales Analysis - Removed Top 5 Profit
I5: Month | J5: Unique products | K5: Boxes | L5: AVG Sales | M5: AVG Profit | N5: Total Sales | O5: Total Profit | P5: Margin | R5: Month | S5: Unique products | T5: Boxes | U5: AVG Sales | V5: AVG Profit | W5: Total Sales | X5: Total Profit | Y5: Margin
I6: Feb | J6: 381 | K6: 339177 | L6: =N6/20 -> 316565.46 | M6: =O6/20 -> 32829.003 | N6: 6331309.2 | O6: 656580.06 | P6: =+O6/N6 -> 0.10370368 | R6: Feb | S6: 376 | T6: 327023 | U6: =W6/20 -> 288087.56 | V6: =X6/20 -> 24004.758 | W6: 5761751.1 | X6: 480095.16 | Y6: =+X6/W6 -> 0.083324522
I7: Mar | J7: 386 | K7: 397866 | L7: =N7/23 -> 329916.9 | M7: =O7/20 -> 40836.887 | N7: 7588088.7 | O7: 816737.74 | P7: =+O7/N7 -> 0.10763418 | R7: Mar | S7: 381 | T7: 383645 | U7: =W7/23 -> 297757.76 | V7: =X7/20 -> 31947.593 | W7: 6848428.5 | X7: 638951.86 | Y7: =+X7/W7 -> 0.093299048
I8: April | J8: 386 | K8: 446480 | L8: =N8/20 -> 367150.07 | M8: =O8/20 -> 43108.672 | N8: 7343001.4 | O8: 862173.44 | P8: =+O8/N8 -> 0.11741431 | R8: April | S8: 381 | T8: 436096 | U8: =W8/20 -> 338213.7 | V8: =X8/20 -> 33762.611 | W8: 6764273.9 | X8: 675252.22 | Y8: =+X8/W8 -> 0.099826268
I9: May | J9: 380 | K9: 423404 | L9: =N9/19 -> 389690.54 | M9: =O9/20 -> 46316.513 | N9: 7404120.2 | O9: 926330.26 | P9: =+O9/N9 -> 0.12511011 | R9: May | S9: 375 | T9: 411285 | U9: =W9/19 -> 354239.19 | V9: =X9/20 -> 36405.317 | W9: 6730544.5 | X9: 728106.35 | Y9: =+X9/W9 -> 0.10817941
I10: June | J10: 395 | K10: 437568 | L10: =N10/22 -> 368447.54 | M10: =O10/20 -> 51828.774 | N10: 8105846 | O10: 1036575.5 | P10: =+O10/N10 -> 0.12787999 | R10: June | S10: 390 | T10: 426174 | U10: =W10/22 -> 339946.23 | V10: =X10/20 -> 40214.483 | W10: 7478817.1 | X10: 804289.66 | Y10: =+X10/W10 -> 0.10754236
I11: July | J11: 451 | K11: 378098 | L11: =N11/22 -> 392869.36 | M11: =O11/20 -> 49372.754 | N11: 8643126 | O11: 987455.09 | P11: 0.11424745 | R11: July | S11: 443 | T11: 367439 | U11: =W11/22 -> 366829.5 | V11: =X11/20 -> 38847.561 | W11: 8070249 | X11: 776951.23 | Y11: 0.096273514
B14: Product Wise Bifurcation
B16: Sales Analysis (Regular Products) | K16: Sales Analysis - Removed Top 5 Profit (Regular Products) | T16: Sales Analysis (New Products)
B17: Month | C17: Unique products | D17: Boxes | E17: AVG Sales | F17: AVG Profit | G17: Total Sales | H17: Total Profit | I17: Margin | K17: Month | L17: Unique products | M17: Boxes | N17: AVG Sales | O17: AVG Profit | P17: Total Sales | Q17: Total Profit | R17: Margin | T17: Month | U17: Unique products | V17: Boxes | W17: AVG Sales | X17: AVG Profit | Y17: Total Sales | Z17: Total Profit | AA17: Margin
B18: Feb | C18: 351 | D18: 310056 | E18: =G18/20 -> 278613.7 | F18: =H18/20 -> 32621.801 | G18: 5572274 | H18: 652436.03 | I18: 0.11708614 | K18: Feb | L18: 344 | M18: 296790 | N18: =P18/20 -> 257378.69 | O18: =Q18/20 -> 22076.188 | P18: 5147573.8 | Q18: 441523.76 | R18: 0.085773178 | T18: Feb | U18: 25 | V18: 29556 | W18: =Y18/20 -> 15953.892 | X18: =Z18/20 -> 2065.561 | Y18: 319077.84 | Z18: 41311.22 | AA18: 0.12947066
B19: Mar | C19: 355 | D19: 352108 | E19: =G19/23 -> 300955.5 | F19: =H19/20 -> 39262.386 | G19: 6921976.4 | H19: 785247.73 | I19: 0.11344271 | K19: Mar | L19: 348 | M19: 336422 | N19: =P19/23 -> 274283.34 | O19: =Q19/20 -> 28583.91 | P19: 6308516.7 | Q19: 571678.21 | R19: 0.090620067 | T19: Mar | U19: 27 | V19: 46267 | W19: =Y19/23 -> 17629.223 | X19: =Z19/20 -> 3370.3075 | Y19: 405472.12 | Z19: 67406.15 | AA19: 0.16624115
B20: April | C20: 358 | D20: 394929 | E20: =G20/20 -> 298852.16 | F20: =H20/20 -> 40956.39 | G20: 5977043.2 | H20: 819127.8 | I20: 0.13704566 | K20: April | L20: 352 | M20: 383357 | N20: =P20/20 -> 276976.49 | O20: =Q20/20 -> 30012.414 | P20: 5539529.8 | Q20: 600248.28 | R20: 0.10835726 | T20: April | U20: 26 | V20: 52327 | W20: =Y20/20 -> 11563.398 | X20: =Z20/20 -> 3370.3075 | Y20: 231267.97 | Z20: 67406.15 | AA20: 0.2914634
B21: May | C21: 349 | D21: 370672 | E21: =G21/19 -> 308321.1 | F21: =H21/20 -> 44017.588 | G21: 5858100.9 | H21: 880351.77 | I21: 0.15027938 | K21: May | L21: 342 | M21: 355466 | N21: =P21/19 -> 280414.37 | O21: =Q21/20 -> 31397.49 | P21: 5327873 | Q21: 627949.8 | R21: 0.11786126 | T21: May | U21: 25 | V21: 53425 | W21: =Y21/19 -> 12840.582 | X21: =Z21/20 -> 4147.823 | Y21: 243971.05 | Z21: 82956.46 | AA21: 0.34002584
B22: June | C22: 356 | D22: 384155 | E22: =G22/22 -> 295908.13 | F22: =H22/20 -> 48267.767 | G22: 6509978.8 | H22: 965355.35 | I22: 0.14828856 | K22: June | L22: 349 | M22: 370620 | N22: =P22/22 -> 275813.53 | O22: =Q22/20 -> 33575.391 | P22: 6067897.6 | Q22: 671507.83 | R22: 0.11066565 | T22: June | U22: 31 | V22: 54297 | W22: =Y22/22 -> 24534.317 | X22: =Z22/20 -> 4633.3905 | Y22: 539754.97 | Z22: 92667.81 | AA22: 0.17168496
B23: July | C23: 361 | D23: 420696 | E23: =G23/22 -> 314105.85 | F23: =H23/20 -> 42034.375 | G23: 6910328.7 | H23: 840687.5 | I23: 0.12165666 | K23: July | L23: 354 | M23: 410543 | N23: =P23/22 -> 299730.31 | O23: =Q23/20 -> 31421.425 | P23: 6594066.7 | Q23: 628428.5 | R23: 0.095302114 | T23: July | U23: 32 | V23: 73382 | W23: =Y23/22 -> 28039.541 | X23: =Z23/20 -> 8185.438 | Y23: 616869.91 | Z23: 163708.76 | AA23: 0.2653862

Sheet Additional watch Purchase
E2: OVERALL
E4: Purchase Analysis | L4: Purchase Analysis - Removed Top 5
E5: Month | F5: Unique products | G5: Boxes | H5: Purchase Value | I5: Potential Profit | J5: Margin | L5: Month | M5: Unique products | N5: Boxes | O5: Purchase Value | P5: Potential Profit | Q5: Margin
E6: Feb | F6: 295 | G6: 418514.39 | H6: 8210000 | I6: 1699175 | J6: =+I6/H6 -> 0.20696407 | L6: Feb | M6: 292 | N6: 410551.89 | O6: 8162031.5 | P6: 984751.58 | Q6: =+P6/O6 -> 0.1206503
E7: Mar | F7: 260 | G7: 343636.91 | H7: 6700000 | I7: 1063643.7 | J7: =+I7/H7 -> 0.1587528 | L7: Mar | M7: 258 | N7: 340223.91 | O7: 6627463.3 | P7: 776968.22 | Q7: =+P7/O7 -> 0.11723463
E8: April | F8: 253 | G8: 297521.18 | H8: 7010000 | I8: 1140054.8 | J8: =+I8/H8 -> 0.16263263 | L8: April | M8: 251 | N8: 293708.18 | O8: 6943915.6 | P8: 818471.24 | Q8: =+P8/O8 -> 0.11786883
E9: May | F9: 268 | G9: 377950.98 | H9: 7630000 | I9: 1304619 | J9: =+I9/H9 -> 0.17098545 | L9: May | M9: 265 | N9: 372135.23 | O9: 7568451 | P9: 924932.31 | Q9: =+P9/O9 -> 0.12220893
E10: June | F10: 281 | G10: 336499.92 | H10: 6930000 | I10: 1153510.1 | J10: =+I10/H10 -> 0.16645167 | L10: June | M10: 278 | N10: 330230.67 | O10: 6804735.8 | P10: 820789.71 | Q10: =+P10/O10 -> 0.12062036
E11: July | F11: 319 | G11: 496145.71 | H11: 8446978.4 | I11: 2030463.7 | J11: =+I11/H11 -> 0.24037752 | L11: July | M11: =+F11-5 -> 314 | N11: 480227.71 | O11: 8340365 | P11: 1295944.4 | Q11: =+P11/O11 -> 0.15538222
B14: Product Wise Bifurcation
B16: Purchase Analysis (Regular Products) | I16: Purchase Analysis - Removed Top 5 (Regular Products) | P16: Purchase Analysis (New Products)
B17: Month | C17: Unique products | D17: Boxes | E17: Purchase Value | F17: Potential Profit | G17: Margin | I17: Month | J17: Unique products | K17: Boxes | L17: Purchase Value | M17: Potential Profit | N17: Margin | P17: Month | Q17: Unique products | R17: Boxes | S17: Purchase Value | T17: Potential Profit | U17: Margin
B18: Feb | C18: 279 | D18: 367568.06 | E18: 7055393 | F18: 1616962.7 | G18: 0.22918109 | I18: Feb | J18: 273 | K18: 345672.36 | L18: 6468748.1 | M18: 784284.86 | N18: 0.12124214 | P18: Feb | Q18: 16 | R18: 50946.333 | S18: 1017299.9 | T18: 80906.82 | U18: 0.079530943
B19: Mar | C19: 243 | D19: 294215.25 | E19: 5546326.8 | F19: 981990.41 | G19: 0.17705239 | I19: Mar | J19: 238 | K19: 281476.91 | L19: 5166717 | M19: 614441.36 | N19: 0.11892298 | P19: Mar | Q19: 17 | R19: 49421.667 | S19: 996797.81 | T19: 77882.45 | U19: 0.078132646
B20: April | C20: 230 | D20: 254854.52 | E20: 6181422.4 | F20: 1037936.2 | G20: 0.1679122 | I20: April | J20: 225 | K20: 243274.72 | L20: 5852920 | M20: 654815.95 | N20: 0.11187851 | P20: April | Q20: 23 | R20: 42666.667 | S20: 780542.79 | T20: 98694.21 | U20: 0.12644305
B21: May | C21: 238 | D21: 325821.86 | E21: 6323811.2 | F21: 1162311.8 | G21: 0.18379925 | I21: May | J21: 232 | K21: 314379.44 | L21: 6100277.3 | M21: 740707.8 | N21: 0.12142199 | P21: May | Q21: 30 | R21: 52129.121 | S21: 933522.83 | T21: 133483.6 | U21: 0.14298911
B22: June | C22: 253 | D22: 293587.58 | E22: 5744574.2 | F22: 1019523.3 | G22: 0.17747587 | I22: June | J22: 246 | K22: 281227.67 | L22: 5521600.1 | M22: 629816.79 | N22: 0.11406418 | P22: June | Q22: 28 | R22: 42912.333 | S22: 878155.92 | T22: 130182.13 | U22: 0.14824489
B23: July | C23: 280 | D23: 402727 | E23: 6958472 | F23: 1646964.9 | G23: 0.23668485 | I23: July | J23: 273 | K23: 377665 | L23: 6177057.7 | M23: 844908.83 | N23: 0.13678176 | P23: July | Q23: 35 | R23: 79258.71 | S23: 1321022.5 | T23: 274037.32 | U23: 0.20744335

Sheet Updated Summary
A1: OVERALL
A3: Purchase Analysis | H3: Purchase Analysis - Removed Top 5
A4: Month | B4: Unique products | C4: Boxes | D4: Purchase Value | E4: Potential Profit | F4: Margin | H4: Month | I4: Unique products | J4: Boxes | K4: Purchase Value | L4: Potential Profit | M4: Margin
A5: Feb | B5: 295 | C5: 418514.39 | D5: 8210000 | E5: 1699175 | F5: =+E5/D5 -> 0.20696407 | H5: Feb | I5: 292 | J5: 410551.89 | K5: 8162031.5 | L5: 984751.58 | M5: =+L5/K5 -> 0.1206503
A6: Mar | B6: 260 | C6: 343636.91 | D6: 6700000 | E6: 1063643.7 | F6: =+E6/D6 -> 0.1587528 | H6: Mar | I6: 258 | J6: 340223.91 | K6: 6627463.3 | L6: 776968.22 | M6: =+L6/K6 -> 0.11723463
A7: April | B7: 253 | C7: 297521.18 | D7: 7010000 | E7: 1140054.8 | F7: =+E7/D7 -> 0.16263263 | H7: April | I7: 251 | J7: 293708.18 | K7: 6943915.6 | L7: 818471.24 | M7: =+L7/K7 -> 0.11786883
A8: May | B8: 268 | C8: 377950.98 | D8: 7630000 | E8: 1304619 | F8: =+E8/D8 -> 0.17098545 | H8: May | I8: 265 | J8: 372135.23 | K8: 7568451 | L8: 924932.31 | M8: =+L8/K8 -> 0.12220893
A9: June | B9: 281 | C9: 336499.92 | D9: 6930000 | E9: 1153510.1 | F9: =+E9/D9 -> 0.16645167 | H9: June | I9: 278 | J9: 330230.67 | K9: 6804735.8 | L9: 820789.71 | M9: =+L9/K9 -> 0.12062036
A10: July | B10: 319 | C10: 496145.71 | D10: 8446978.4 | E10: 2030463.7 | F10: =+E10/D10 -> 0.24037752 | H10: July | I10: =+B10-5 -> 314 | J10: 480227.71 | K10: 8340365 | L10: 1295944.4 | M10: =+L10/K10 -> 0.15538222
A12: Sales Analysis | H12: Sales Analysis - Removed Top 5 Profit
A13: Month | B13: Unique products | C13: Boxes | D13: Sales Value | E13: Profit | F13: Margin | H13: Month | I13: Unique products | J13: Boxes | K13: Sales Value | L13: Profit | M13: Margin
A14: Feb | B14: 381 | C14: 339177 | D14: 6331309.2 | E14: 656580.06 | F14: =+E14/D14 -> 0.10370368 | H14: Feb | I14: 376 | J14: 327023 | K14: 5761751.1 | L14: 480095.16 | M14: =+L14/K14 -> 0.083324522
A15: Mar | B15: 386 | C15: 397866 | D15: 7588088.7 | E15: 816737.74 | F15: =+E15/D15 -> 0.10763418 | H15: Mar | I15: 381 | J15: 383645 | K15: 6848428.5 | L15: 638951.86 | M15: =+L15/K15 -> 0.093299048
A16: April | B16: 386 | C16: 446480 | D16: 7343001.4 | E16: 862173.44 | F16: =+E16/D16 -> 0.11741431 | H16: April | I16: 381 | J16: 436096 | K16: 6764273.9 | L16: 675252.22 | M16: =+L16/K16 -> 0.099826268
A17: May | B17: 380 | C17: 423404 | D17: 7404120.2 | E17: 926330.26 | F17: =+E17/D17 -> 0.12511011 | H17: May | I17: 375 | J17: 411285 | K17: 6730544.5 | L17: 728106.35 | M17: =+L17/K17 -> 0.10817941
A18: June | B18: 395 | C18: 437568 | D18: 8105846 | E18: 1036575.5 | F18: =+E18/D18 -> 0.12787999 | H18: June | I18: 390 | J18: 426174 | K18: 7478817.1 | L18: 804289.66 | M18: =+L18/K18 -> 0.10754236
A19: July | B19: 451 | C19: 378098 | D19: 8643126 | E19: 987455.09 | F19: 0.11424745 | H19: July | I19: 443 | J19: 367439 | K19: 8070249 | L19: x | M19: 0.096273514
A22: Product Wise Bifurcation
B23: Select the Product Type → | E23: Old Line
A25: Purchase Analysis | H25: Purchase Analysis - Removed Top 5
A26: Month | B26: Unique products | C26: Boxes | D26: Purchase Value | E26: Potential Profit | F26: Margin | H26: Month | I26: Unique products | J26: Boxes | K26: Purchase Value | L26: Potential Profit | M26: Margin
A27: Feb | B27: =COUNTIFS(Raw!D:D,'Updated Summary'!E23,Raw!J:J,">0") -> 279 | C27: =SUMIFS(Raw!J:J,Raw!$D:$D,'Updated Summary'!$E$23) -> 367568.06 | D27: =SUMIFS(Raw!AO:AO,Raw!$D:$D,'Updated Summary'!$E$23) -> 7055393 | E27: =SUMIFS(Raw!P:P,Raw!$D:$D,'Updated Summary'!$E$23) -> 1616962.7 | F27: =+E27/D27 -> 0.22918109 | H27: Feb | I27: =COUNTIFS(Raw!D:D,'Updated Summary'!E23,Raw!J:J,">0",Raw!C:C,"<>Top 5") -> 273 | J27: =SUMIFS(Raw!J:J,Raw!$D:$D,'Updated Summary'!$E$23,Raw!C:C,"<>Top 5") -> 345672.36 | K27: =SUMIFS(Raw!AO:AO,Raw!$D:$D,'Updated Summary'!$E$23,Raw!C:C,"<>Top 5") -> 6468748.1 | L27: =SUMIFS(Raw!P:P,Raw!$D:$D,'Updated Summary'!$E$23,Raw!C:C,"<>Top 5") -> 784284.86 | M27: =+L27/K27 -> 0.12124214
A28: Mar | B28: =COUNTIFS(Raw!D:D,'Updated Summary'!E23,Raw!K:K,">0") -> 243 | C28: =SUMIFS(Raw!K:K,Raw!$D:$D,'Updated Summary'!$E$23) -> 294215.25 | D28: =SUMIFS(Raw!AP:AP,Raw!$D:$D,'Updated Summary'!$E$23) -> 5546326.8 | E28: =SUMIFS(Raw!Q:Q,Raw!$D:$D,'Updated Summary'!$E$23) -> 981990.41 | F28: =+E28/D28 -> 0.17705239 | H28: Mar | I28: =COUNTIFS(Raw!D:D,'Updated Summary'!E23,Raw!K:K,">0",Raw!C:C,"<> Top 5",Raw!C:C,"<>Top 5") -> 238 | J28: =SUMIFS(Raw!K:K,Raw!$D:$D,'Updated Summary'!$E$23,Raw!C:C,"<>Top 5") -> 281476.91 | K28: =SUMIFS(Raw!AP:AP,Raw!$D:$D,'Updated Summary'!$E$23,Raw!C:C,"<>Top 5") -> 5166717 | L28: =SUMIFS(Raw!Q:Q,Raw!$D:$D,'Updated Summary'!$E$23,Raw!C:C,"<>Top 5") -> 614441.36 | M28: =+L28/K28 -> 0.11892298
A29: April | B29: =COUNTIFS(Raw!D:D,'Updated Summary'!E23,Raw!L:L,">0") -> 230 | C29: =SUMIFS(Raw!L:L,Raw!$D:$D,'Updated Summary'!$E$23) -> 254854.52 | D29: =SUMIFS(Raw!AQ:AQ,Raw!$D:$D,'Updated Summary'!$E$23) -> 6181422.4 | E29: =SUMIFS(Raw!R:R,Raw!$D:$D,'Updated Summary'!$E$23) -> 1037936.2 | F29: =+E29/D29 -> 0.1679122 | H29: April | I29: =COUNTIFS(Raw!D:D,'Updated Summary'!E23,Raw!L:L,">0",Raw!C:C,"<>Top 5") -> 225 | J29: =SUMIFS(Raw!L:L,Raw!$D:$D,'Updated Summary'!$E$23,Raw!C:C,"<>Top 5") -> 243274.72 | K29: =SUMIFS(Raw!AQ:AQ,Raw!$D:$D,'Updated Summary'!$E$23,Raw!C:C,"<>Top 5") -> 5852920 | L29: =SUMIFS(Raw!R:R,Raw!$D:$D,'Updated Summary'!$E$23,Raw!C:C,"<>Top 5") -> 654815.95 | M29: =+L29/K29 -> 0.11187851
A30: May | B30: =COUNTIFS(Raw!D:D,'Updated Summary'!E23,Raw!M:M,">0") -> 238 | C30: =SUMIFS(Raw!M:M,Raw!$D:$D,'Updated Summary'!$E$23) -> 325821.86 | D30: =SUMIFS(Raw!AR:AR,Raw!$D:$D,'Updated Summary'!$E$23) -> 6323811.2 | E30: =SUMIFS(Raw!S:S,Raw!$D:$D,'Updated Summary'!$E$23) -> 1162311.8 | F30: =+E30/D30 -> 0.18379925 | H30: May | I30: =COUNTIFS(Raw!D:D,'Updated Summary'!E23,Raw!M:M,">0",Raw!C:C,"<>Top 5") -> 232 | J30: =SUMIFS(Raw!M:M,Raw!$D:$D,'Updated Summary'!$E$23,Raw!C:C,"<>Top 5") -> 314379.44 | K30: =SUMIFS(Raw!AR:AR,Raw!$D:$D,'Updated Summary'!$E$23,Raw!C:C,"<>Top 5") -> 6100277.3 | L30: =SUMIFS(Raw!S:S,Raw!$D:$D,'Updated Summary'!$E$23,Raw!C:C,"<>Top 5") -> 740707.8 | M30: =+L30/K30 -> 0.12142199
A31: June | B31: =COUNTIFS(Raw!D:D,'Updated Summary'!E23,Raw!N:N,">0") -> 253 | C31: =SUMIFS(Raw!N:N,Raw!$D:$D,'Updated Summary'!$E$23) -> 293587.58 | D31: =SUMIFS(Raw!AS:AS,Raw!$D:$D,'Updated Summary'!$E$23) -> 5744574.2 | E31: =SUMIFS(Raw!T:T,Raw!$D:$D,'Updated Summary'!$E$23) -> 1019523.3 | F31: =+E31/D31 -> 0.17747587 | H31: June | I31: =COUNTIFS(Raw!D:D,'Updated Summary'!E23,Raw!N:N,">0",Raw!C:C,"<>Top 5") -> 246 | J31: =SUMIFS(Raw!N:N,Raw!$D:$D,'Updated Summary'!$E$23,Raw!C:C,"<>Top 5") -> 281227.67 | K31: =SUMIFS(Raw!AS:AS,Raw!$D:$D,'Updated Summary'!$E$23,Raw!C:C,"<>Top 5") -> 5521600.1 | L31: =SUMIFS(Raw!T:T,Raw!$D:$D,'Updated Summary'!$E$23,Raw!C:C,"<>Top 5") -> 629816.79 | M31: =+L31/K31 -> 0.11406418
A32: July | B32: =COUNTIFS(Raw!D:D,'Updated Summary'!E23,Raw!O:O,">0") -> 280 | C32: =SUMIFS(Raw!O:O,Raw!$D:$D,'Updated Summary'!$E$23) -> 402727 | D32: =SUMIFS(Raw!AT:AT,Raw!$D:$D,'Updated Summary'!$E$23) -> 6958472 | E32: =SUMIFS(Raw!U:U,Raw!$D:$D,'Updated Summary'!$E$23) -> 1646964.9 | F32: =+E32/D32 -> 0.23668485 | H32: July | I32: =COUNTIFS(Raw!D:D,'Updated Summary'!E23,Raw!O:O,">0",Raw!C:C,"<>Top 5") -> 273 | J32: =SUMIFS(Raw!O:O,Raw!$D:$D,'Updated Summary'!$E$23,Raw!C:C,"<>Top 5") -> 377665 | K32: =SUMIFS(Raw!AT:AT,Raw!$D:$D,'Updated Summary'!$E$23,Raw!C:C,"<>Top 5") -> 6177057.7 | L32: =SUMIFS(Raw!U:U,Raw!$D:$D,'Updated Summary'!$E$23,Raw!C:C,"<>Top 5") -> 844908.83 | M32: =+L32/K32 -> 0.13678176
A34: Sales Analysis | H34: Sales Analysis - Removed Top 5 Profit
A35: Month | B35: Unique products | C35: Boxes | D35: Sales Value | E35: Profit | F35: Margin | H35: Month | I35: Unique products | J35: Boxes | K35: Sales Value | L35: Profit | M35: Margin
A36: Feb | B36: =COUNTIFS(Raw!D:D,'Updated Summary'!E23,Raw!V:V,">0") -> 351 | C36: =SUMIFS(Raw!V:V,Raw!$D:$D,'Updated Summary'!$E$23) -> 310056 | D36: =SUMIFS(Raw!AU:AU,Raw!$D:$D,'Updated Summary'!$E$23) -> 5572274 | E36: =SUMIFS(Raw!AH:AH,Raw!$D:$D,'Updated Summary'!$E$23) -> 652436.03 | F36: =+E36/D36 -> 0.11708614 | H36: Feb | I36: =COUNTIFS(Raw!D:D,'Updated Summary'!E23,Raw!V:V,">0",Raw!C:C,"<>Top 5") -> 344 | J36: =SUMIFS(Raw!V:V,Raw!$D:$D,'Updated Summary'!$E$23,Raw!C:C,"<>Top 5") -> 296790 | K36: =SUMIFS(Raw!AU:AU,Raw!$D:$D,'Updated Summary'!$E$23,Raw!C:C,"<>Top 5") -> 5147573.8 | L36: =SUMIFS(Raw!AH:AH,Raw!$D:$D,'Updated Summary'!$E$23,Raw!C:C,"<>Top 5") -> 441523.76 | M36: =+L36/K36 -> 0.085773178
A37: Mar | B37: =COUNTIFS(Raw!D:D,'Updated Summary'!E23,Raw!W:W,">0") -> 355 | C37: =SUMIFS(Raw!W:W,Raw!$D:$D,'Updated Summary'!$E$23) -> 352108 | D37: =SUMIFS(Raw!AV:AV,Raw!$D:$D,'Updated Summary'!$E$23) -> 6921976.4 | E37: =SUMIFS(Raw!AI:AI,Raw!$D:$D,'Updated Summary'!$E$23) -> 785247.73 | F37: =+E37/D37 -> 0.11344271 | H37: Mar | I37: =COUNTIFS(Raw!D:D,'Updated Summary'!E23,Raw!W:W,">0",Raw!C:C,"<>Top 5") -> 348 | J37: =SUMIFS(Raw!W:W,Raw!$D:$D,'Updated Summary'!$E$23,Raw!C:C,"<>Top 5") -> 336422 | K37: =SUMIFS(Raw!AV:AV,Raw!$D:$D,'Updated Summary'!$E$23,Raw!C:C,"<>Top 5") -> 6308516.7 | L37: =SUMIFS(Raw!AI:AI,Raw!$D:$D,'Updated Summary'!$E$23,Raw!C:C,"<>Top 5") -> 571678.21 | M37: =+L37/K37 -> 0.090620067
A38: April | B38: =COUNTIFS(Raw!D:D,'Updated Summary'!E23,Raw!X:X,">0") -> 358 | C38: =SUMIFS(Raw!X:X,Raw!$D:$D,'Updated Summary'!$E$23) -> 394929 | D38: =SUMIFS(Raw!AW:AW,Raw!$D:$D,'Updated Summary'!$E$23) -> 5977043.2 | E38: =SUMIFS(Raw!AJ:AJ,Raw!$D:$D,'Updated Summary'!$E$23) -> 819127.8 | F38: =+E38/D38 -> 0.13704566 | H38: April | I38: =COUNTIFS(Raw!D:D,'Updated Summary'!E23,Raw!X:X,">0",Raw!C:C,"<>Top 5") -> 352 | J38: =SUMIFS(Raw!X:X,Raw!$D:$D,'Updated Summary'!$E$23,Raw!C:C,"<>Top 5") -> 383357 | K38: =SUMIFS(Raw!AW:AW,Raw!$D:$D,'Updated Summary'!$E$23,Raw!C:C,"<>Top 5") -> 5539529.8 | L38: =SUMIFS(Raw!AJ:AJ,Raw!$D:$D,'Updated Summary'!$E$23,Raw!C:C,"<>Top 5") -> 600248.28 | M38: =+L38/K38 -> 0.10835726
A39: May | B39: =COUNTIFS(Raw!D:D,'Updated Summary'!E23,Raw!Y:Y,">0") -> 349 | C39: =SUMIFS(Raw!Y:Y,Raw!$D:$D,'Updated Summary'!$E$23) -> 370672 | D39: =SUMIFS(Raw!AX:AX,Raw!$D:$D,'Updated Summary'!$E$23) -> 5858100.9 | E39: =SUMIFS(Raw!AK:AK,Raw!$D:$D,'Updated Summary'!$E$23) -> 880351.77 | F39: =+E39/D39 -> 0.15027938 | H39: May | I39: =COUNTIFS(Raw!D:D,'Updated Summary'!E23,Raw!Y:Y,">0",Raw!C:C,"<>Top 5") -> 342 | J39: =SUMIFS(Raw!Y:Y,Raw!$D:$D,'Updated Summary'!$E$23,Raw!C:C,"<>Top 5") -> 355466 | K39: =SUMIFS(Raw!AX:AX,Raw!$D:$D,'Updated Summary'!$E$23,Raw!C:C,"<>Top 5") -> 5327873 | L39: =SUMIFS(Raw!AK:AK,Raw!$D:$D,'Updated Summary'!$E$23,Raw!C:C,"<>Top 5") -> 627949.8 | M39: =+L39/K39 -> 0.11786126
A40: June | B40: =COUNTIFS(Raw!D:D,'Updated Summary'!E23,Raw!Z:Z,">0") -> 356 | C40: =SUMIFS(Raw!Z:Z,Raw!$D:$D,'Updated Summary'!$E$23) -> 384155 | D40: =SUMIFS(Raw!AY:AY,Raw!$D:$D,'Updated Summary'!$E$23) -> 6509978.8 | E40: =SUMIFS(Raw!AL:AL,Raw!$D:$D,'Updated Summary'!$E$23) -> 965355.35 | F40: =+E40/D40 -> 0.14828856 | H40: June | I40: =COUNTIFS(Raw!D:D,'Updated Summary'!E23,Raw!Z:Z,">0",Raw!C:C,"<>Top 5") -> 349 | J40: =SUMIFS(Raw!Z:Z,Raw!$D:$D,'Updated Summary'!$E$23,Raw!C:C,"<>Top 5") -> 370620 | K40: =SUMIFS(Raw!AY:AY,Raw!$D:$D,'Updated Summary'!$E$23,Raw!C:C,"<>Top 5") -> 6067897.6 | L40: =SUMIFS(Raw!AL:AL,Raw!$D:$D,'Updated Summary'!$E$23,Raw!C:C,"<>Top 5") -> 671507.83 | M40: =+L40/K40 -> 0.11066565
A41: July | B41: =COUNTIFS(Raw!D:D,'Updated Summary'!E23,Raw!AA:AA,">0") -> 361 | C41: =SUMIFS(Raw!AA:AA,Raw!$D:$D,'Updated Summary'!$E$23) -> 420696 | D41: =SUMIFS(Raw!AZ:AZ,Raw!$D:$D,'Updated Summary'!$E$23) -> 6910328.7 | E41: =SUMIFS(Raw!AM:AM,Raw!$D:$D,'Updated Summary'!$E$23) -> 840687.5 | F41: =+E41/D41 -> 0.12165666 | H41: July | I41: =COUNTIFS(Raw!D:D,'Updated Summary'!E23,Raw!AA:AA,">0",Raw!C:C,"<>Top 5") -> 354 | J41: =SUMIFS(Raw!AA:AA,Raw!$D:$D,'Updated Summary'!$E$23,Raw!C:C,"<>Top 5") -> 410543 | K41: =SUMIFS(Raw!AZ:AZ,Raw!$D:$D,'Updated Summary'!$E$23,Raw!C:C,"<>Top 5") -> 6594066.7 | L41: =SUMIFS(Raw!AM:AM,Raw!$D:$D,'Updated Summary'!$E$23,Raw!C:C,"<>Top 5") -> 628428.5 | M41: =+L41/K41 -> 0.095302114

Sheet Raw
A1: Lax Part No | B1: Lax Description | C1: Top/Bottom | D1: Type | E1: Profit Per Pack | F1: Qty Target | G1: Monthly | H1: PCA | I1: Monthly Requirement Against PCA | J1: Feb'26 Received Qty | K1: March'26 Received Qty | L1: Apr'26 Received Qty | M1: May'26 Received Qty | N1: June'26 Received Qty | O1: July'26 Received Qty | P1: Feb'26 Potential Profit | Q1: March'26 Potential Profit | R1: Apr'26 Potential Profit | S1: May'26 Potential Profit | T1: June'26 Potential Profit | U1: July'26 Potential Profit | V1: Feb'26 Selling Qty | W1: March'26 Selling Qty | X1: Apr'26 Selling Qty | Y1: May'26 Selling Qty | Z1: June'26 Selling Qty | AA1: July'26 Selling Qty | AB1: Feb'26 Selling Qty | AC1: March'26 Selling Qty | AD1: Apr'26 Selling Qty | AE1: May'26 Selling Qty | AF1: June'26 Selling Qty | AG1: July'26 Selling Qty | AH1: Feb'26 Profit | AI1: March'26 Profit | AJ1: Apr'26 Profit | AK1: May'26 Profit | AL1: June'26 Profit | AM1: July'26 Profit | AN1: Category | AO1: Feb'26 Purchase Value | AP1: March'26 Purchase Value | AQ1: Apr'26 Purchase Value | AR1: May'26 Purchase Value | AS1: June'26 Purchase Value | AT1: July'26 Purchase Value | AU1: Feb'26 Sales Value | AV1: March'26 Sales Value | AW1: Apr'26 Sales Value | AX1: May'26 Sales Value | AY1: June'26 Sales Value | AZ1: July'26 Sales Value
A2: 1459 | B2: Trihexyphenidyl 2mg Tablets 100 | C2: Top 5 | D2: Old Line | E2: 95.44 | F2: 3000 | G2: =F2/2 -> 1500 | H2: 6291 | I2: =+G2/H2 -> 0.23843586 | J2: 7002.5 | K2: 2504 | L2: 2842 | M2: 2186.75 | N2: 904.25 | O2: 3198 | P2: =+J2*E2 -> 668318.6 | Q2: =+K2*E2 -> 238981.76 | R2: =+L2*E2 -> 271240.48 | S2: =+M2*E2 -> 208703.42 | T2: =+N2*E2 -> 86301.62 | U2: =+O2*E2 -> 305217.12 | V2: =726+435 -> 1161 | W2: =991+504 -> 1495 | X2: =778+776 -> 1554 | Y2: =867+693 -> 1560 | Z2: =890+884 -> 1774 | AA2: 805 | AB2: =+IFERROR(V2/H2,"") -> 0.18454936 | AC2: =+IFERROR(W2/H2,"") -> 0.23764107 | AD2: =+IFERROR(X2/H2,"") -> 0.24701955 | AE2: =+IFERROR(Y2/H2,"") -> 0.2479733 | AF2: =+IFERROR(Z2/H2,"") -> 0.28199014 | AG2: =+IFERROR(AA2/H2,"") -> 0.12796058 | AH2: 104490 | AI2: 134550 | AJ2: 139860 | AK2: 140400 | AL2: 159660 | AM2: 70979.12 | AN2: Above 11% | AO2: 25052.72 | AP2: 11618.56 | AQ2: 13205.2 | AR2: 10137.65 | AS2: 4159.55 | AT2: 3668.1 | AU2: 0 | AV2: 0 | AW2: 0 | AX2: 0 | AY2: 0 | AZ2: 0 | BB2: Old Line
A3: L1515 | B3: Ontozry 150mg Tabs 28 | D3: New Line | E3: 90.75627 | F3: 1500 | G3: =F3/2 -> 750 | H3: 1212 | I3: =+G3/H3 -> 0.61881188 | J3: 0 | K3: 0 | L3: 0 | M3: 0 | N3: 0 | O3: 55 | U3: =+O3*E3 -> 4991.5949 | AB3: =+IFERROR(V3/H3,"") -> 0 | AC3: =+IFERROR(W3/H3,"") -> 0 | AD3: =+IFERROR(X3/H3,"") -> 0 | AE3: =+IFERROR(Y3/H3,"") -> 0 | AF3: =+IFERROR(Z3/H3,"") -> 0 | AG3: =+IFERROR(AA3/H3,"") -> 0 | AN3: Above 11% | AO3: 0 | AP3: 0 | AQ3: 0 | AR3: 0 | AS3: 0 | AT3: 4867.5 | AU3: 0 | AV3: 0 | AW3: 0 | AX3: 17383.69 | AY3: 13701.49 | AZ3: 0 | BB3: New Line
A4: 4092A | B4: Olsalazine 500mg Tablets 60 | D4: Old Line | E4: 89.98 | F4: 150 | G4: =F4/2 -> 75 | H4: 305 | I4: =+G4/H4 -> 0.24590164 | J4: 0 | K4: 0 | L4: 0 | M4: 50 | N4: 40 | O4: 0 | P4: =+J4*E4 -> 0 | Q4: =+K4*E4 -> 0 | R4: =+L4*E4 -> 0 | S4: =+M4*E4 -> 4499 | T4: =+N4*E4 -> 3599.2 | U4: =+O4*E4 -> 0 | V4: 2 | W4: 0 | X4: 0 | Y4: 0 | Z4: 49 | AA4: 39 | AB4: =+IFERROR(V4/H4,"") -> 0.006557377 | AC4: =+IFERROR(W4/H4,"") -> 0 | AD4: =+IFERROR(X4/H4,"") -> 0 | AE4: =+IFERROR(Y4/H4,"") -> 0 | AF4: =+IFERROR(Z4/H4,"") -> 0.16065574 | AG4: =+IFERROR(AA4/H4,"") -> 0.12786885 | AH4: 184.86 | AI4: 0 | AJ4: 0 | AK4: 0 | AL4: 4409.02 | AM4: 3461.86 | AN4: Above 11% | AO4: 0 | AP4: 0 | AQ4: 0 | AR4: 2809.5 | AS4: 2220.4 | AT4: 0 | AU4: 293.98 | AV4: 0 | AW4: 0 | AX4: 0 | AY4: 6872.95 | AZ4: 5626.75
A5: 5678 | B5: Olsalazine 500mg Tablets 100 | D5: Old Line | E5: 83.25 | F5: 300 | G5: =F5/2 -> 150 | H5: 305 | I5: =+G5/H5 -> 0.49180328 | J5: 273 | K5: 0 | L5: 0 | M5: 0 | O5: 0 | P5: =+J5*E5 -> 22727.25 | Q5: =+K5*E5 -> 0 | R5: =+L5*E5 -> 0 | S5: =+M5*E5 -> 0 | T5: =+N5*E5 -> 0 | U5: =+O5*E5 -> 0 | V5: 19 | W5: 36 | X5: 90 | Y5: 97 | Z5: 74 | AA5: 0 | AB5: =+IFERROR(V5/H5,"") -> 0.062295082 | AC5: =+IFERROR(W5/H5,"") -> 0.11803279 | AD5: =+IFERROR(X5/H5,"") -> 0.29508197 | AE5: =+IFERROR(Y5/H5,"") -> 0.31803279 | AF5: =+IFERROR(Z5/H5,"") -> 0.24262295 | AG5: =+IFERROR(AA5/H5,"") -> 0 | AH5: 1711.2 | AI5: 4335.88 | AJ5: 4335.88 | AK5: 8516.17 | AL5: 7774.44 | AM5: 0 | AN5: Above 11% | AO5: 15313 | AP5: 0 | AQ5: 0 | AR5: 0 | AS5: 0 | AT5: 0 | AU5: 0 | AV5: 0 | AW5: 0 | AX5: 0 | AY5: 0 | AZ5: 0
A6: 5678A | B6: Dipentum 250mg Capsules 100 | D6: Old Line | E6: 77.07 | F6: 200 | G6: =F6/2 -> 100 | H6: 305 | I6: =+G6/H6 -> 0.32786885 | J6: 353 | K6: 130 | L6: 0 | M6: 0 | O6: 0 | P6: =+J6*E6 -> 27205.71 | Q6: =+K6*E6 -> 10019.1 | R6: =+L6*E6 -> 0 | S6: =+M6*E6 -> 0 | T6: =+N6*E6 -> 0 | U6: =+O6*E6 -> 0 | V6: 0 | W6: 0 | X6: 0 | Y6: 20 | Z6: 24 | AA6: 44 | AB6: =+IFERROR(V6/H6,"") -> 0 | AC6: =+IFERROR(W6/H6,"") -> 0 | AD6: =+IFERROR(X6/H6,"") -> 0 | AE6: =+IFERROR(Y6/H6,"") -> 0.06557377 | AF6: =+IFERROR(Z6/H6,"") -> 0.078688525 | AG6: =+IFERROR(AA6/H6,"") -> 0.1442623 | AH6: 0 | AI6: 0 | AJ6: 0 | AK6: 1541.4 | AL6: 1631.4 | AM6: 3449.16 | AN6: Above 11% | AO6: 12284.81 | AP6: 4529.2 | AQ6: 0 | AR6: 0 | AS6: 0 | AT6: 0 | AU6: 0 | AV6: 0 | AW6: 0 | AX6: 2320 | AY6: 2743.5 | AZ6: 4964.08
A7: 5440 | B7: Norprolac 75mcg Tablets 30s | D7: Old Line | E7: 51.94 | F7: 400 | G7: =F7/2 -> 200 | H7: 269 | I7: =+G7/H7 -> 0.74349442 | J7: 98 | K7: 0 | L7: 0 | M7: 0 | O7: 30 | P7: =+J7*E7 -> 5090.12 | Q7: =+K7*E7 -> 0 | R7: =+L7*E7 -> 0 | S7: =+M7*E7 -> 0 | T7: =+N7*E7 -> 0 | U7: =+O7*E7 -> 1558.2 | V7: 0 | W7: 0 | X7: 0 | Y7: 1 | Z7: 0 | AA7: 0 | AB7: =+IFERROR(V7/H7,"") -> 0 | AC7: =+IFERROR(W7/H7,"") -> 0 | AD7: =+IFERROR(X7/H7,"") -> 0 | AE7: =+IFERROR(Y7/H7,"") -> 0.0037174721 | AF7: =+IFERROR(Z7/H7,"") -> 0 | AG7: =+IFERROR(AA7/H7,"") -> 0 | AH7: 0 | AI7: 0 | AJ7: 0 | AK7: 51.94 | AL7: 51.94 | AM7: 0 | AN7: Above 11% | AO7: 2316.56 | AP7: 0 | AQ7: 0 | AR7: 0 | AS7: 0 | AT7: 702.6 | AU7: 0 | AV7: 0 | AW7: 0 | AX7: 0 | AY7: 0 | AZ7: 0
A8: 5209M | B8: Exelon 9.5mg/24hrs Transdermal Patches 30 | C8: Top 5 | D8: Old Line | E8: 48.32 | F8: 3000 | G8: =F8/2 -> 1500 | H8: 485 | I8: =+G8/H8 -> 3.0927835 | J8: 565 | K8: 909 | L8: 971 | M8: 347 | N8: 1230 | O8: 796 | P8: =+J8*E8 -> 27300.8 | Q8: =+K8*E8 -> 43922.88 | R8: =+L8*E8 -> 46918.72 | S8: =+M8*E8 -> 16767.04 | T8: =+N8*E8 -> 59433.6 | U8: =+O8*E8 -> 38462.72 | V8: 215 | W8: 310 | X8: 1371 | Y8: 754 | Z8: 273 | AA8: 380 | AB8: =+IFERROR(V8/H8,"") -> 0.44329897 | AC8: =+IFERROR(W8/H8,"") -> 0.63917526 | AD8: =+IFERROR(X8/H8,"") -> 2.8268041 | AE8: =+IFERROR(Y8/H8,"") -> 1.5546392 | AF8: =+IFERROR(Z8/H8,"") -> 0.5628866 | AG8: =+IFERROR(AA8/H8,"") -> 0.78350515 | AH8: 4599.04 | AI8: 7170.14 | AJ8: 7170.14 | AK8: 33326.04 | AL8: 31149.89 | AM8: 16033.81 | AN8: Above 11% | AO8: 11732.46 | AP8: 19114.74 | AQ8: 20259.44 | AR8: 7301.22 | AS8: 25859.31 | AT8: 16720.83 | AU8: 8920.54 | AV8: 13432.42 | AW8: 62035.18 | AX8: 46911.51 | AY8: 16367.43 | AZ8: 23997.72
A9: 0680D | B9: Oxycontin 80mg Tablets 56 | D9: Old Line | E9: 47.674998 | F9: 200 | G9: =F9/2 -> 100 | H9: 322 | I9: =+G9/H9 -> 0.31055901 | J9: 0 | K9: 0 | L9: 0 | M9: 0 | N9: 0 | O9: 403 | U9: =+O9*E9 -> 19213.024 | AB9: =+IFERROR(V9/H9,"") -> 0 | AC9: =+IFERROR(W9/H9,"") -> 0 | AD9: =+IFERROR(X9/H9,"") -> 0 | AE9: =+IFERROR(Y9/H9,"") -> 0 | AF9: =+IFERROR(Z9/H9,"") -> 0 | AG9: =+IFERROR(AA9/H9,"") -> 0 | AN9: Above 11% | AO9: 0 | AP9: 0 | AQ9: 0 | AR9: 0 | AS9: 0 | AT9: 0 | AU9: 1852.44 | AV9: 1381.99 | AW9: 1144.67 | AX9: 0 | AY9: 0 | AZ9: 0
A10: 1371 | B10: Domperidone 1mg/1ml Suspension 200ml | C10: Top 5 | D10: Old Line | E10: 44.3 | F10: 8000 | G10: =F10/2 -> 4000 | H10: 1722 | I10: =+G10/H10 -> 2.3228804 | J10: 395 | K10: 0 | L10: 0 | M10: 3282 | N10: 4135 | O10: 7088 | P10: =+J10*E10 -> 17498.5 | Q10: =+K10*E10 -> 0 | R10: =+L10*E10 -> 0 | S10: =+M10*E10 -> 145392.6 | T10: =+N10*E10 -> 183180.5 | U10: =+O10*E10 -> 313998.4 | V10: 2680 | W10: 514 | X10: 683 | Y10: 838 | Z10: 1707 | AA10: 1949 | AB10: =+IFERROR(V10/H10,"") -> 1.5563298 | AC10: =+IFERROR(W10/H10,"") -> 0.29849013 | AD10: =+IFERROR(X10/H10,"") -> 0.39663182 | AE10: =+IFERROR(Y10/H10,"") -> 0.48664344 | AF10: =+IFERROR(Z10/H10,"") -> 0.9912892 | AG10: =+IFERROR(AA10/H10,"") -> 1.1318235 | AH10: 66107.27 | AI10: 21703.68 | AJ10: 21703.68 | AK10: 41518.49 | AL10: 44172.43 | AM10: 89083.95 | AN10: Above 11% | AO10: 845.3 | AP10: 0 | AQ10: 0 | AR10: 6857.52 | AS10: 23528.03 | AT10: 30851.04 | AU10: 0 | AV10: 0 | AW10: 0 | AX10: 0 | AY10: 0 | AZ10: 0
A11: L7124 | B11: Fycompa oral suspension 0.5mg/ml 1's | D11: New Line | E11: 42.77 | F11: 300 | G11: =F11/2 -> 150 | H11: 391 | I11: =+G11/H11 -> 0.38363171 | J11: 0 | K11: 0 | L11: 115 | M11: 304 | N11: 307 | O11: 285 | P11: =+J11*E11 -> 0 | Q11: =+K11*E11 -> 0 | R11: =+L11*E11 -> 4918.55 | S11: =+M11*E11 -> 13002.08 | T11: =+N11*E11 -> 13130.39 | U11: =+O11*E11 -> 12189.45 | V11: 0 | W11: 0 | X11: 0 | Y11: 0 | Z11: 110 | AA11: 179 | AB11: =+IFERROR(V11/H11,"") -> 0 | AC11: =+IFERROR(W11/H11,"") -> 0 | AD11: =+IFERROR(X11/H11,"") -> 0 | AE11: =+IFERROR(Y11/H11,"") -> 0 | AF11: =+IFERROR(Z11/H11,"") -> 0.28132992 | AG11: =+IFERROR(AA11/H11,"") -> 0.45780051 | AH11: 0 | AI11: 0 | AJ11: 0 | AK11: 0 | AL11: 4704.7 | AM11: 7195.62 | AN11: Above 11% | AO11: 0 | AP11: 0 | AQ11: 7155.3 | AR11: 19456.56 | AS11: 19519.2 | AT11: 18126.6 | AU11: 0 | AV11: 0 | AW11: 0 | AX11: 0 | AY11: 12446.13 | AZ11: 18508.45
A12: 5548D | B12: Entocort CR 3mg Capsules 100 | D12: Old Line | E12: 41.11 | F12: 50 | G12: =F12/2 -> 25 | H12: 100 | I12: =+G12/H12 -> 0.25 | J12: 0 | K12: 0 | L12: 0 | M12: 74 | O12: 0 | P12: =+J12*E12 -> 0 | Q12: =+K12*E12 -> 0 | R12: =+L12*E12 -> 0 | S12: =+M12*E12 -> 3042.14 | T12: =+N12*E12 -> 0 | U12: =+O12*E12 -> 0 | V12: 0 | W12: 0 | X12: 21 | Y12: 3 | Z12: 20 | AA12: 24 | AB12: =+IFERROR(V12/H12,"") -> 0 | AC12: =+IFERROR(W12/H12,"") -> 0 | AD12: =+IFERROR(X12/H12,"") -> 0.21 | AE12: =+IFERROR(Y12/H12,"") -> 0.03 | AF12: =+IFERROR(Z12/H12,"") -> 0.2 | AG12: =+IFERROR(AA12/H12,"") -> 0.24 | AH12: 0 | AI12: 0 | AJ12: 863.31 | AK12: 305.77 | AL12: 48.58 | AM12: 771.16 | AN12: Above 11% | AO12: 0 | AP12: 0 | AQ12: 0 | AR12: 0 | AS12: 0 | AT12: 0 | AU12: 0 | AV12: 0 | AW12: 1360.39 | AX12: 199.24 | AY12: 1334.99 | AZ12: 1705.68
A13: L1502 | B13: Ontozry 100mg Tabs 28 | D13: New Line | E13: 40.95 | F13: 1000 | G13: =F13/2 -> 500 | H13: 2146 | I13: =+G13/H13 -> 0.23299161 | J13: 0 | K13: 0 | L13: 0 | M13: 0 | N13: 146 | O13: 46 | P13: =+J13*E13 -> 0 | Q13: =+K13*E13 -> 0 | R13: =+L13*E13 -> 0 | S13: =+M13*E13 -> 0 | T13: =+N13*E13 -> 5978.7 | U13: =+O13*E13 -> 1883.7 | V13: 308 | W13: 435 | X13: 221 | Y13: 105 | Z13: 15 | AA13: 145 | AB13: =+IFERROR(V13/H13,"") -> 0.14352283 | AC13: =+IFERROR(W13/H13,"") -> 0.2027027 | AD13: =+IFERROR(X13/H13,"") -> 0.10298229 | AE13: =+IFERROR(Y13/H13,"") -> 0.048928239 | AF13: =+IFERROR(Z13/H13,"") -> 0.0069897484 | AG13: =+IFERROR(AA13/H13,"") -> 0.067567568 | AH13: 3718.66 | AI13: 6245.23 | AJ13: 6245.23 | AK13: 4477.13 | AL13: 1741.52 | AM13: 5842.09 | AN13: Above 11% | AO13: 0 | AP13: 0 | AQ13: 0 | AR13: 0 | AS13: 12346.2 | AT13: 3908.16 | AU13: 36000.59 | AV13: 50751.35 | AW13: 25611.19 | AX13: 12483.52 | AY13: 1775 | AZ13: 18020.64
A14: 5686B | B14: EXELON transdermal patches 13.3mg/24h | D14: Old Line | E14: 40.29 | F14: 400 | G14: =F14/2 -> 200 | H14: 92 | I14: =+G14/H14 -> 2.173913 | J14: 1024 | K14: 1112 | L14: 0 | M14: 0 | N14: 645 | O14: 608 | P14: =+J14*E14 -> 41256.96 | Q14: =+K14*E14 -> 44802.48 | R14: =+L14*E14 -> 0 | S14: =+M14*E14 -> 0 | T14: =+N14*E14 -> 25987.05 | U14: =+O14*E14 -> 24496.32 | V14: 63 | W14: 60 | X14: 65 | Y14: 122 | Z14: 66 | AA14: 75 | AB14: =+IFERROR(V14/H14,"") -> 0.68478261 | AC14: =+IFERROR(W14/H14,"") -> 0.65217391 | AD14: =+IFERROR(X14/H14,"") -> 0.70652174 | AE14: =+IFERROR(Y14/H14,"") -> 1.326087 | AF14: =+IFERROR(Z14/H14,"") -> 0.7173913 | AG14: =+IFERROR(AA14/H14,"") -> 0.81521739 | AH14: 1464.07 | AI14: 1787.95 | AJ14: 1787.95 | AK14: 1800.08 | AL14: 3857.26 | AM14: 2025.76 | AN14: Above 11% | AO14: 30064.63 | AP14: 33037.46 | AQ14: 0 | AR14: 0 | AS14: 18190.47 | AT14: 17696.1 | AU14: 3313.25 | AV14: 3551.7 | AW14: 3712.38 | AX14: 7450.12 | AY14: 4080.68 | AZ14: 4206.95
A15: L1503 | B15: Ontozry 200mg Tabs 28 | D15: New Line | E15: 37.9 | F15: 2000 | G15: =F15/2 -> 1000 | H15: 3833 | I15: =+G15/H15 -> 0.26089225 | J15: 0 | K15: 0 | L15: 32 | M15: 0 | N15: 116 | O15: 0 | P15: =+J15*E15 -> 0 | Q15: =+K15*E15 -> 0 | R15: =+L15*E15 -> 1212.8 | S15: =+M15*E15 -> 0 | T15: =+N15*E15 -> 4396.4 | U15: =+O15*E15 -> 0 | V15: 599 | W15: 406 | X15: 40 | Y15: 149 | Z15: 51 | AA15: 50 | AB15: =+IFERROR(V15/H15,"") -> 0.15627446 | AC15: =+IFERROR(W15/H15,"") -> 0.10592225 | AD15: =+IFERROR(X15/H15,"") -> 0.01043569 | AE15: =+IFERROR(Y15/H15,"") -> 0.038872945 | AF15: =+IFERROR(Z15/H15,"") -> 0.013305505 | AG15: =+IFERROR(AA15/H15,"") -> 0.013044613 | AH15: 4975.86 | AI15: 4622.42 | AJ15: 4622.42 | AK15: 403.06 | AL15: 3183.84 | AM15: 895 | AN15: Above 11% | AO15: 0 | AP15: 0 | AQ15: 2480.96 | AR15: 0 | AS15: 10396.99 | AT15: 0 | AU15: 93284.91 | AV15: 63465.19 | AW15: 6203.06 | AX15: 24788.84 | AY15: 8350.2 | AZ15: 8045
A16: 5733C | B16: Zonegran 50mg Capsules 56 | D16: Old Line | E16: 34.48 | F16: 400 | G16: =F16/2 -> 200 | H16: 678 | I16: =+G16/H16 -> 0.29498525 | J16: 31 | K16: 0 | L16: 0 | M16: 0 | O16: 0 | P16: =+J16*E16 -> 1068.88 | Q16: =+K16*E16 -> 0 | R16: =+L16*E16 -> 0 | S16: =+M16*E16 -> 0 | T16: =+N16*E16 -> 0 | U16: =+O16*E16 -> 0 | V16: 89 | W16: 133 | X16: 105 | Y16: 69 | Z16: 16 | AA16: 15 | AB16: =+IFERROR(V16/H16,"") -> 0.13126844 | AC16: =+IFERROR(W16/H16,"") -> 0.19616519 | AD16: =+IFERROR(X16/H16,"") -> 0.15486726 | AE16: =+IFERROR(Y16/H16,"") -> 0.10176991 | AF16: =+IFERROR(Z16/H16,"") -> 0.02359882 | AG16: =+IFERROR(AA16/H16,"") -> 0.022123894 | AH16: 2252 | AI16: 3424.56 | AJ16: 3424.56 | AK16: 2449.51 | AL16: 1602.66 | AM16: 478 | AN16: Above 11% | AO16: 0 | AP16: 0 | AQ16: 0 | AR16: 0 | AS16: 0 | AT16: 0 | AU16: 3825.52 | AV16: 5776.75 | AW16: 4320.92 | AX16: 2898.48 | AY16: 607.46 | AZ16: 635.8
A17: 5092A | B17: Briviact 25mg Tablets 56 | D17: Old Line | E17: 34.02 | F17: 700 | G17: =F17/2 -> 350 | H17: 2856 | I17: =+G17/H17 -> 0.12254902 | J17: 118.18182 | K17: 164.39394 | L17: 704.75758 | M17: 987.87879 | N17: 435.24242 | O17: 504 | P17: =+J17*E17 -> 4020.5455 | Q17: =+K17*E17 -> 5592.6818 | R17: =+L17*E17 -> 23975.853 | S17: =+M17*E17 -> 33607.636 | T17: =+N17*E17 -> 14806.947 | U17: =+O17*E17 -> 17146.08 | V17: 290 | W17: 116 | X17: 164 | Y17: 478 | Z17: 429 | AA17: 1024 | AB17: =+IFERROR(V17/H17,"") -> 0.10154062 | AC17: =+IFERROR(W17/H17,"") -> 0.040616246 | AD17: =+IFERROR(X17/H17,"") -> 0.057422969 | AE17: =+IFERROR(Y17/H17,"") -> 0.16736695 | AF17: =+IFERROR(Z17/H17,"") -> 0.15021008 | AG17: =+IFERROR(AA17/H17,"") -> 0.35854342 | AH17: 4936.6 | AI17: 1652.7 | AJ17: 1652.7 | AK17: 8153.84 | AL17: 17989.07 | AM17: 34686.77 | AN17: Above 11% | AO17: 8697.39 | AP17: 12105.81 | AQ17: 51826.55 | AR17: 69767.1 | AS17: 31619.04 | AT17: 34528.33 | AU17: 26506.8 | AV17: 10271.5 | AW17: 20261.28 | AX17: 53535.71 | AY17: 51400.74 | AZ17: 107869.44
A18: 5205 | B18: Stalevo Film Coated Tabs 125mg/31.25mg/200mg 100 | D18: New Line | E18: 32.993197 | F18: 400 | G18: =F18/2 -> 200 | H18: 1004 | I18: =+G18/H18 -> 0.19920319 | J18: 0 | K18: 0 | L18: 0 | M18: 0 | N18: 0 | O18: 430 | U18: =+O18*E18 -> 14187.075 | AB18: =+IFERROR(V18/H18,"") -> 0 | AC18: =+IFERROR(W18/H18,"") -> 0 | AD18: =+IFERROR(X18/H18,"") -> 0 | AE18: =+IFERROR(Y18/H18,"") -> 0 | AF18: =+IFERROR(Z18/H18,"") -> 0 | AG18: =+IFERROR(AA18/H18,"") -> 0 | AN18: Above 11% | AO18: 0 | AP18: 0 | AQ18: 0 | AR18: 1637 | AS18: 1677.5 | AT18: 7612.3 | AU18: 0 | AV18: 0 | AW18: 0 | AX18: 0 | AY18: 0 | AZ18: 0
A19: 5092D | B19: Briviact Oral Solution 10mg/ml 300ml | C19: Top 5 | D19: New Line | E19: 32.95 | F19: 500 | G19: =F19/2 -> 250 | H19: 1500 | I19: =+G19/H19 -> 0.16666667 | J19: 0 | K19: 0 | L19: 98 | M19: 86 | N19: 557 | O19: 616 | P19: =+J19*E19 -> 0 | Q19: =+K19*E19 -> 0 | R19: =+L19*E19 -> 3229.1 | S19: =+M19*E19 -> 2833.7 | T19: =+N19*E19 -> 18353.15 | U19: =+O19*E19 -> 20297.2 | V19: 0 | W19: 0 | X19: 0 | Y19: 75 | Z19: 103 | AA19: 506 | AB19: =+IFERROR(V19/H19,"") -> 0 | AC19: =+IFERROR(W19/H19,"") -> 0 | AD19: =+IFERROR(X19/H19,"") -> 0 | AE19: =+IFERROR(Y19/H19,"") -> 0.05 | AF19: =+IFERROR(Z19/H19,"") -> 0.068666667 | AG19: =+IFERROR(AA19/H19,"") -> 0.33733333 | AH19: 0 | AI19: 0 | AJ19: 0 | AK19: 2471.25 | AL19: 2588.49 | AM19: 15132.7 | AN19: Above 11% | AO19: 0 | AP19: 0 | AQ19: 7586.96 | AR19: 6963.42 | AS19: 44039.81 | AT19: 48183.76 | AU19: 0 | AV19: 0 | AW19: 0 | AX19: 8431.74 | AY19: 11680.67 | AZ19: 55069.47
A20: L9106A | B20: Efient 5mg Tablets 28 | D20: Old Line | E20: 28.834748 | F20: 300 | G20: =F20/2 -> 150 | H20: 1769 | I20: =+G20/H20 -> 0.084793669 | J20: 0 | K20: 0 | L20: 0 | M20: 0 | N20: 0 | O20: 50 | U20: =+O20*E20 -> 1441.7374 | AB20: =+IFERROR(V20/H20,"") -> 0 | AC20: =+IFERROR(W20/H20,"") -> 0 | AD20: =+IFERROR(X20/H20,"") -> 0 | AE20: =+IFERROR(Y20/H20,"") -> 0 | AF20: =+IFERROR(Z20/H20,"") -> 0 | AG20: =+IFERROR(AA20/H20,"") -> 0 | AN20: Above 11% | AO20: 0 | AP20: 0 | AQ20: 0 | AR20: 0 | AS20: 0 | AT20: 660 | AU20: 0 | AV20: 0 | AW20: 0 | AX20: 0 | AY20: 0 | AZ20: 0
A21: 5250N | B21: Vimpat 200mg Film-coated Tablets 56 | D21: Old Line | E21: 25.83 | F21: 200 | G21: =F21/2 -> 100 | H21: 279 | I21: =+G21/H21 -> 0.35842294 | J21: 0 | K21: 0 | L21: 0 | M21: 0 | O21: 0 | P21: =+J21*E21 -> 0 | Q21: =+K21*E21 -> 0 | R21: =+L21*E21 -> 0 | S21: =+M21*E21 -> 0 | T21: =+N21*E21 -> 0 | U21: =+O21*E21 -> 0 | V21: 62 | W21: 140 | X21: 59 | Y21: 38 | Z21: 64 | AA21: 34 | AB21: =+IFERROR(V21/H21,"") -> 0.22222222 | AC21: =+IFERROR(W21/H21,"") -> 0.50179211 | AD21: =+IFERROR(X21/H21,"") -> 0.21146953 | AE21: =+IFERROR(Y21/H21,"") -> 0.13620072 | AF21: =+IFERROR(Z21/H21,"") -> 0.22939068 | AG21: =+IFERROR(AA21/H21,"") -> 0.1218638 | AH21: 2478.86 | AI21: 3503.15 | AJ21: 3503.15 | AK21: 1968.21 | AL21: 1284.83 | AM21: 902.54 | AN21: Above 11% | AO21: 0 | AP21: 0 | AQ21: 0 | AR21: 0 | AS21: 0 | AT21: 0 | AU21: 6178.1 | AV21: 11842.95 | AW21: 5482.84 | AX21: 3548.49 | AY21: 5436.54 | AZ21: 2927.92
A22: 5123E | B22: Aricept Evess Dispersible Tablets 5Mg X 28'S | D22: Old Line | E22: 25.58 | F22: 240 | G22: =F22/2 -> 120 | H22: 1315 | I22: =+G22/H22 -> 0.091254753 | J22: 149 | K22: 0 | L22: 224 | M22: 161 | O22: 0 | P22: =+J22*E22 -> 3811.42 | Q22: =+K22*E22 -> 0 | R22: =+L22*E22 -> 5729.92 | S22: =+M22*E22 -> 4118.38 | T22: =+N22*E22 -> 0 | U22: =+O22*E22 -> 0 | V22: 0 | W22: 4 | X22: 6 | Y22: 0 | Z22: 0 | AA22: 0 | AB22: =+IFERROR(V22/H22,"") -> 0 | AC22: =+IFERROR(W22/H22,"") -> 0.0030418251 | AD22: =+IFERROR(X22/H22,"") -> 0.0045627376 | AE22: =+IFERROR(Y22/H22,"") -> 0 | AF22: =+IFERROR(Z22/H22,"") -> 0 | AG22: =+IFERROR(AA22/H22,"") -> 0 | AH22: 0 | AI22: 116.9 | AJ22: 116.9 | AK22: 210 | AL22: 0 | AM22: 0 | AN22: Above 11% | AO22: 2506.03 | AP22: 0 | AQ22: 3751.36 | AR22: 2688.9 | AS22: 0 | AT22: 0 | AU22: 0 | AV22: 192.9 | AW22: 324 | AX22: 0 | AY22: 0 | AZ22: 0
A23: 5175C | B23: Creon 25000 Gastroresistant Capsules 50 | D23: New Line | E23: 25.51 | F23: 2000 | G23: =F23/2 -> 1000 | H23: 45807 | I23: =+G23/H23 -> 0.021830725 | J23: 0 | K23: 0 | L23: 999 | M23: 1040 | N23: 820 | O23: 1620 | P23: =+J23*E23 -> 0 | Q23: =+K23*E23 -> 0 | R23: =+L23*E23 -> 25484.49 | S23: =+M23*E23 -> 26530.4 | T23: =+N23*E23 -> 20918.2 | U23: =+O23*E23 -> 41326.2 | V23: 9 | W23: 0 | X23: 0 | Y23: 683 | Z23: 830 | AA23: 1339 | AB23: =+IFERROR(V23/H23,"") -> 0.00019647652 | AC23: =+IFERROR(W23/H23,"") -> 0 | AD23: =+IFERROR(X23/H23,"") -> 0 | AE23: =+IFERROR(Y23/H23,"") -> 0.014910385 | AF23: =+IFERROR(Z23/H23,"") -> 0.018119501 | AG23: =+IFERROR(AA23/H23,"") -> 0.02923134 | AH23: 224.64 | AI23: 1.59 | AJ23: 1.59 | AK23: 17423.33 | AL23: 17213 | AM23: 32944.95 | AN23: Above 11% | AO23: 0 | AP23: 0 | AQ23: 22097.88 | AR23: 23193.8 | AS23: 18240.6 | AT23: 31553.8 | AU23: 429.3 | AV23: 1.59 | AW23: 0 | AX23: 32314.13 | AY23: 38986.93 | AZ23: 62798.71
A24: 5029 | B24: Wynzora cream 0.5mg/g 60 | D24: New Line | E24: 25.25 | F24: 1500 | G24: =F24/2 -> 750 | H24: 2564 | I24: =+G24/H24 -> 0.2925117 | J24: 0 | K24: 0 | L24: 0 | M24: 60 | O24: 230 | P24: =+J24*E24 -> 0 | Q24: =+K24*E24 -> 0 | R24: =+L24*E24 -> 0 | S24: =+M24*E24 -> 1515 | T24: =+N24*E24 -> 0 | U24: =+O24*E24 -> 5807.5 | V24: 0 | W24: 0 | X24: 0 | Y24: 0 | Z24: 0 | AA24: 0 | AB24: =+IFERROR(V24/H24,"") -> 0 | AC24: =+IFERROR(W24/H24,"") -> 0 | AD24: =+IFERROR(X24/H24,"") -> 0 | AE24: =+IFERROR(Y24/H24,"") -> 0 | AF24: =+IFERROR(Z24/H24,"") -> 0 | AG24: =+IFERROR(AA24/H24,"") -> 0 | AH24: 0 | AI24: 0 | AJ24: 0 | AK24: 0 | AL24: 0 | AM24: 0 | AN24: Above 11% | AO24: 0 | AP24: 0 | AQ24: 0 | AR24: 1762.5 | AS24: 0 | AT24: 15433.9 | AU24: 0 | AV24: 0 | AW24: 0 | AX24: 0 | AY24: 0 | AZ24: 0
A25: 0920Y | B25: Donepezil 10mg Orodispersible Tablets 28 | D25: Old Line | E25: 25.2 | F25: 777.6 | G25: =F25/2 -> 388.8 | H25: 2722 | I25: =+G25/H25 -> 0.14283615 | J25: 0 | K25: 0 | L25: 0 | M25: 128 | N25: 40 | O25: 112 | P25: =+J25*E25 -> 0 | Q25: =+K25*E25 -> 0 | R25: =+L25*E25 -> 0 | S25: =+M25*E25 -> 3225.6 | T25: =+N25*E25 -> 1008 | U25: =+O25*E25 -> 2822.4 | V25: 315 | W25: 198 | X25: 349 | Y25: 506 | Z25: 576 | AA25: 599 | AB25: =+IFERROR(V25/H25,"") -> 0.11572373 | AC25: =+IFERROR(W25/H25,"") -> 0.072740632 | AD25: =+IFERROR(X25/H25,"") -> 0.12821455 | AE25: =+IFERROR(Y25/H25,"") -> 0.18589273 | AF25: =+IFERROR(Z25/H25,"") -> 0.21160911 | AG25: =+IFERROR(AA25/H25,"") -> 0.22005878 | AH25: 1890.46 | AI25: 2281.82 | AJ25: 2281.82 | AK25: 3480.16 | AL25: 3680.35 | AM25: 3899.78 | AN25: Above 11% | AO25: 0 | AP25: 0 | AQ25: 0 | AR25: 2816.62 | AS25: 838.8 | AT25: 2459.68 | AU25: 9878.85 | AV25: 6043.82 | AW25: 10111.16 | AX25: 13187.28 | AY25: 12906.82 | AZ25: 13173.86
A26: 5325 | B26: Nebido Inj 1000 mg / 4ml Amp | D26: Old Line | E26: 24.51 | F26: 3000 | G26: =F26/2 -> 1500 | H26: 9407 | I26: =+G26/H26 -> 0.15945572 | J26: 785 | K26: 290 | L26: 1145 | M26: 1969 | N26: 43 | O26: 713 | P26: =+J26*E26 -> 19240.35 | Q26: =+K26*E26 -> 7107.9 | R26: =+L26*E26 -> 28063.95 | S26: =+M26*E26 -> 48260.19 | T26: =+N26*E26 -> 1053.93 | U26: =+O26*E26 -> 17475.63 | V26: 266 | W26: 0 | X26: 803 | Y26: 1768 | Z26: 1809 | AA26: 194 | AB26: =+IFERROR(V26/H26,"") -> 0.028276815 | AC26: =+IFERROR(W26/H26,"") -> 0 | AD26: =+IFERROR(X26/H26,"") -> 0.085361964 | AE26: =+IFERROR(Y26/H26,"") -> 0.18794515 | AF26: =+IFERROR(Z26/H26,"") -> 0.1923036 | AG26: =+IFERROR(AA26/H26,"") -> 0.02062294 | AH26: 881.11 | AI26: 0 | AJ26: 19681.53 | AK26: 14415.35 | AL26: 41100.39 | AM26: 3954.39 | AN26: Above 11% | AO26: 46918.38 | AP26: 17579.4 | AQ26: 70914.72 | AR26: 124545.97 | AS26: 2576.13 | AT26: 47624.97 | AU26: 0 | AV26: 0 | AW26: 0 | AX26: 0 | AY26: 0 | AZ26: 0
A27: 5390 | B27: Lamictal 200mg Tablets 30 | D27: Old Line | E27: 23.95 | F27: 729.6 | G27: =F27/2 -> 364.8 | H27: 3648 | I27: =+G27/H27 -> 0.1 | J27: 232 | K27: 600 | L27: 0 | M27: 0 | O27: 120 | P27: =+J27*E27 -> 5556.4 | Q27: =+K27*E27 -> 14370 | R27: =+L27*E27 -> 0 | S27: =+M27*E27 -> 0 | T27: =+N27*E27 -> 0 | U27: =+O27*E27 -> 2874 | V27: 2 | W27: 3 | X27: 1 | Y27: 1 | Z27: 4 | AA27: 0 | AB27: =+IFERROR(V27/H27,"") -> 0.00054824561 | AC27: =+IFERROR(W27/H27,"") -> 0.00082236842 | AD27: =+IFERROR(X27/H27,"") -> 0.00027412281 | AE27: =+IFERROR(Y27/H27,"") -> 0.00027412281 | AF27: =+IFERROR(Z27/H27,"") -> 0.0010964912 | AG27: =+IFERROR(AA27/H27,"") -> 0 | AH27: 44.43 | AI27: 73.48 | AJ27: 73.48 | AK27: 23.4 | AL27: 30.44 | AM27: 0 | AN27: Above 11% | AO27: 2484.72 | AP27: 6676 | AQ27: 0 | AR27: 0 | AS27: 0 | AT27: 1246.8 | AU27: 0 | AV27: 0 | AW27: 0 | AX27: 0 | AY27: 0 | AZ27: 0
A28: 5007 | B28: Fusidic acid 1% modified-release eye drops 5g (PI) | D28: Old Line | E28: 23.41 | F28: 2500 | G28: =F28/2 -> 1250 | H28: 5335 | I28: =+G28/H28 -> 0.23430178 | J28: 172 | K28: 0 | L28: 216 | M28: 0 | O28: 0 | P28: =+J28*E28 -> 4026.52 | Q28: =+K28*E28 -> 0 | R28: =+L28*E28 -> 5056.56 | S28: =+M28*E28 -> 0 | T28: =+N28*E28 -> 0 | U28: =+O28*E28 -> 0 | V28: 0 | W28: 0 | X28: 0 | Y28: 0 | Z28: 0 | AA28: 325 | AB28: =+IFERROR(V28/H28,"") -> 0 | AC28: =+IFERROR(W28/H28,"") -> 0 | AD28: =+IFERROR(X28/H28,"") -> 0 | AE28: =+IFERROR(Y28/H28,"") -> 0 | AF28: =+IFERROR(Z28/H28,"") -> 0 | AG28: =+IFERROR(AA28/H28,"") -> 0.060918463 | AH28: 0 | AI28: 0 | AJ28: 0 | AK28: 0 | AL28: 0 | AM28: 7425.76 | AN28: Above 11% | AO28: 0 | AP28: 0 | AQ28: 0 | AR28: 0 | AS28: 0 | AT28: 0 | AU28: 0 | AV28: 0 | AW28: 0 | AX28: 0 | AY28: 0 | AZ28: 0
A29: 5092B | B29: Briviact F/C 100mg Tablets 56s | D29: Old Line | E29: 22.61 | F29: 2500 | G29: =F29/2 -> 1250 | H29: 7025 | I29: =+G29/H29 -> 0.17793594 | J29: 613.45455 | K29: 327.45455 | L29: 4300.6364 | M29: 2860.6061 | N29: 1993.9394 | O29: 1266 | P29: =+J29*E29 -> 13870.207 | Q29: =+K29*E29 -> 7403.7473 | R29: =+L29*E29 -> 97237.388 | S29: =+M29*E29 -> 64678.303 | T29: =+N29*E29 -> 45082.97 | U29: =+O29*E29 -> 28624.26 | V29: 1383 | W29: 1353 | X29: 243 | Y29: 1085 | Z29: 2670 | AA29: 2302 | AB29: =+IFERROR(V29/H29,"") -> 0.19686833 | AC29: =+IFERROR(W29/H29,"") -> 0.19259786 | AD29: =+IFERROR(X29/H29,"") -> 0.034590747 | AE29: =+IFERROR(Y29/H29,"") -> 0.1544484 | AF29: =+IFERROR(Z29/H29,"") -> 0.38007117 | AG29: =+IFERROR(AA29/H29,"") -> 0.32768683 | AH29: 2298.18 | AI29: 4008.55 | AJ29: 4008.55 | AK29: 11406.93 | AL29: 15626.57 | AM29: 35049.07 | AN29: Above 11% | AO29: 66410.83 | AP29: 23361.61 | AQ29: 304497.5 | AR29: 205058.1 | AS29: 143276.54 | AT29: 58532.53 | AU29: 103465.17 | AV29: 102551.25 | AW29: 28890.4 | AX29: 93408.08 | AY29: 219452.26 | AZ29: 199683.94
A30: 5250D | B30: Epilim Chronosphere MR 500mg Sachets 30 | D30: Old Line | E30: 22.46 | F30: 1000 | G30: =F30/2 -> 500 | H30: 1089 | I30: =+G30/H30 -> 0.45913682 | J30: 0 | K30: 136 | L30: 471 | M30: 145 | O30: 0 | P30: =+J30*E30 -> 0 | Q30: =+K30*E30 -> 3054.56 | R30: =+L30*E30 -> 10578.66 | S30: =+M30*E30 -> 3256.7 | T30: =+N30*E30 -> 0 | U30: =+O30*E30 -> 0 | V30: 330 | W30: 793 | X30: 90 | Y30: 358 | Z30: 189 | AA30: 0 | AB30: =+IFERROR(V30/H30,"") -> 0.3030303 | AC30: =+IFERROR(W30/H30,"") -> 0.728191 | AD30: =+IFERROR(X30/H30,"") -> 0.082644628 | AE30: =+IFERROR(Y30/H30,"") -> 0.32874197 | AF30: =+IFERROR(Z30/H30,"") -> 0.17355372 | AG30: =+IFERROR(AA30/H30,"") -> 0 | AH30: 2600.09 | AI30: 8426.86 | AJ30: 8426.86 | AK30: 1519.58 | AL30: 5557.32 | AM30: 0 | AN30: Above 11% | AO30: 0 | AP30: 953.34 | AQ30: 3331.62 | AR30: 1014.8 | AS30: 0 | AT30: 0 | AU30: 4913.39 | AV30: 13985.79 | AW30: 2149.58 | AX30: 8087.87 | AY30: 4577.95 | AZ30: 0
A31: 5139 | B31: Abilify 15mg Tablets 28 | D31: Old Line | E31: 22.34 | F31: 100 | G31: =F31/2 -> 50 | H31: 87 | I31: =+G31/H31 -> 0.57471264 | J31: 100 | K31: 122 | L31: 0 | M31: 0 | O31: 0 | P31: =+J31*E31 -> 2234 | Q31: =+K31*E31 -> 2725.48 | R31: =+L31*E31 -> 0 | S31: =+M31*E31 -> 0 | T31: =+N31*E31 -> 0 | U31: =+O31*E31 -> 0 | V31: 23 | W31: 27 | X31: 28 | Y31: 72 | Z31: 33 | AA31: 56 | AB31: =+IFERROR(V31/H31,"") -> 0.26436782 | AC31: =+IFERROR(W31/H31,"") -> 0.31034483 | AD31: =+IFERROR(X31/H31,"") -> 0.32183908 | AE31: =+IFERROR(Y31/H31,"") -> 0.82758621 | AF31: =+IFERROR(Z31/H31,"") -> 0.37931034 | AG31: =+IFERROR(AA31/H31,"") -> 0.64367816 | AH31: 42.83 | AI31: 71.52 | AJ31: 71.52 | AK31: 109.74 | AL31: 193.46 | AM31: 528.52 | AN31: Above 11% | AO31: 2252 | AP31: 2729.14 | AQ31: 0 | AR31: 0 | AS31: 0 | AT31: 0 | AU31: 0 | AV31: 0 | AW31: 0 | AX31: 0 | AY31: 0 | AZ31: 0
A32: 0906B | B32: Rifampicin 300mg Capsules ---- 60s | D32: Old Line | E32: 21.36 | F32: 300 | G32: =F32/2 -> 150 | H32: 548 | I32: =+G32/H32 -> 0.27372263 | J32: 0 | K32: 50 | L32: 0 | M32: 0 | O32: 0 | P32: =+J32*E32 -> 0 | Q32: =+K32*E32 -> 1068 | R32: =+L32*E32 -> 0 | S32: =+M32*E32 -> 0 | T32: =+N32*E32 -> 0 | U32: =+O32*E32 -> 0 | V32: 0 | W32: 0 | X32: 0 | Y32: 0 | Z32: 0 | AA32: 0 | AB32: =+IFERROR(V32/H32,"") -> 0 | AC32: =+IFERROR(W32/H32,"") -> 0 | AD32: =+IFERROR(X32/H32,"") -> 0 | AE32: =+IFERROR(Y32/H32,"") -> 0 | AF32: =+IFERROR(Z32/H32,"") -> 0 | AG32: =+IFERROR(AA32/H32,"") -> 0 | AH32: 0 | AI32: 0 | AJ32: 0 | AK32: 0 | AL32: 0 | AM32: 0 | AN32: Above 11% | AO32: 0 | AP32: 692 | AQ32: 0 | AR32: 0 | AS32: 0 | AT32: 0 | AU32: 0 | AV32: 0 | AW32: 0 | AX32: 0 | AY32: 0 | AZ32: 0
A33: 9330A | B33: Rivastigmine Patches 4.6mg/24hr 30s | D33: Old Line | E33: 21 | F33: 880.8 | G33: =F33/2 -> 440.4 | H33: 4404 | I33: =+G33/H33 -> 0.1 | J33: 415 | K33: 413 | L33: 665 | M33: 894 | N33: 595 | O33: 557 | P33: =+J33*E33 -> 8715 | Q33: =+K33*E33 -> 8673 | R33: =+L33*E33 -> 13965 | S33: =+M33*E33 -> 18774 | T33: =+N33*E33 -> 12495 | U33: =+O33*E33 -> 11697 | V33: 49 | W33: 413 | X33: 556 | Y33: 493 | Z33: 338 | AA33: 977 | AB33: =+IFERROR(V33/H33,"") -> 0.011126249 | AC33: =+IFERROR(W33/H33,"") -> 0.093778383 | AD33: =+IFERROR(X33/H33,"") -> 0.12624886 | AE33: =+IFERROR(Y33/H33,"") -> 0.11194369 | AF33: =+IFERROR(Z33/H33,"") -> 0.076748411 | AG33: =+IFERROR(AA33/H33,"") -> 0.22184378 | AH33: 1235.06 | AI33: 7135.56 | AJ33: 7135.56 | AK33: 8764.54 | AL33: 15380.39 | AM33: 18642.62 | AN33: Above 11% | AO33: 7545.05 | AP33: 7709.75 | AQ33: 12250.07 | AR33: 16882.39 | AS33: 11327.41 | AT33: 10766.92 | AU33: 2120.01 | AV33: 14678.93 | AW33: 18990.61 | AX33: 24476.77 | AY33: 14717.96 | AZ33: 37122.48
A34: 5934C | B34: Xarelto 15mg Tablets 28 | D34: Old Line | E34: 20.82 | F34: 100 | G34: =F34/2 -> 50 | H34: 167 | I34: =+G34/H34 -> 0.2994012 | J34: 700 | K34: 0 | L34: 0 | M34: 0 | N34: 800 | O34: 600 | P34: =+J34*E34 -> 14574 | Q34: =+K34*E34 -> 0 | R34: =+L34*E34 -> 0 | S34: =+M34*E34 -> 0 | T34: =+N34*E34 -> 16656 | U34: =+O34*E34 -> 12492 | V34: 112 | W34: 135 | X34: 248 | Y34: 224 | Z34: 127 | AA34: 296 | AB34: =+IFERROR(V34/H34,"") -> 0.67065868 | AC34: =+IFERROR(W34/H34,"") -> 0.80838323 | AD34: =+IFERROR(X34/H34,"") -> 1.4850299 | AE34: =+IFERROR(Y34/H34,"") -> 1.3413174 | AF34: =+IFERROR(Z34/H34,"") -> 0.76047904 | AG34: =+IFERROR(AA34/H34,"") -> 1.7724551 | AH34: 683.7 | AI34: 1372.96 | AJ34: 1372.96 | AK34: 1993.39 | AL34: 1959.73 | AM34: 5416.14 | AN34: Above 11% | AO34: 21380 | AP34: 0 | AQ34: 0 | AR34: 0 | AS34: 15331 | AT34: 8910 | AU34: 4653.78 | AV34: 5600.99 | AW34: 9639.23 | AX34: 8865.65 | AY34: 5206.36 | AZ34: 11359.78
A35: 5250B | B35: Epilim Chronosphere MR 100mg Sachets 30 | D35: Old Line | E35: 20.78 | F35: 2000 | G35: =F35/2 -> 1000 | H35: 600 | I35: =+G35/H35 -> 1.6666667 | J35: 0 | K35: 100 | L35: 494 | M35: 286 | O35: 0 | P35: =+J35*E35 -> 0 | Q35: =+K35*E35 -> 2078 | R35: =+L35*E35 -> 10265.32 | S35: =+M35*E35 -> 5943.08 | T35: =+N35*E35 -> 0 | U35: =+O35*E35 -> 0 | V35: 1137 | W35: 873 | X35: 0 | Y35: 261 | Z35: 417 | AA35: 0 | AB35: =+IFERROR(V35/H35,"") -> 1.895 | AC35: =+IFERROR(W35/H35,"") -> 1.455 | AD35: =+IFERROR(X35/H35,"") -> 0 | AE35: =+IFERROR(Y35/H35,"") -> 0.435 | AF35: =+IFERROR(Z35/H35,"") -> 0.695 | AG35: =+IFERROR(AA35/H35,"") -> 0 | AH35: 21116.64 | AI35: 20169.1 | AJ35: 20169.1 | AK35: 5423.58 | AL35: 5659.72 | AM35: 0 | AN35: Above 11% | AO35: 0 | AP35: 286 | AQ35: 1525.84 | AR35: 864.62 | AS35: 0 | AT35: 0 | AU35: 24527.64 | AV35: 22788.1 | AW35: 0 | AX35: 6485.73 | AY35: 9941.24 | AZ35: 0
A36: 5380F | B36: Lyrica 300mg Capsules 56 | D36: Old Line | E36: 20.25 | F36: 500 | G36: =F36/2 -> 250 | H36: 833 | I36: =+G36/H36 -> 0.30012005 | J36: 0 | K36: 0 | L36: 0 | M36: 144 | O36: 0 | P36: =+J36*E36 -> 0 | Q36: =+K36*E36 -> 0 | R36: =+L36*E36 -> 0 | S36: =+M36*E36 -> 2916 | T36: =+N36*E36 -> 0 | U36: =+O36*E36 -> 0 | V36: 184 | W36: 225 | X36: 126 | Y36: 183 | Z36: 150 | AA36: 129 | AB36: =+IFERROR(V36/H36,"") -> 0.22088836 | AC36: =+IFERROR(W36/H36,"") -> 0.27010804 | AD36: =+IFERROR(X36/H36,"") -> 0.1512605 | AE36: =+IFERROR(Y36/H36,"") -> 0.21968788 | AF36: =+IFERROR(Z36/H36,"") -> 0.18007203 | AG36: =+IFERROR(AA36/H36,"") -> 0.15486194 | AH36: 5948.84 | AI36: 5925.44 | AJ36: 5925.44 | AK36: 2791.88 | AL36: 3921.34 | AM36: 2540.44 | AN36: Above 11% | AO36: 0 | AP36: 0 | AQ36: 0 | AR36: 3079.78 | AS36: 0 | AT36: 0 | AU36: 9836.76 | AV36: 10679.69 | AW36: 5790.05 | AX36: 8313.34 | AY36: 6501.56 | AZ36: 5765.44
A37: 5679 | B37: Zyprexa 20mg Velotabs 28 | D37: Old Line | E37: 20.1 | F37: 93.2 | G37: =F37/2 -> 46.6 | H37: 102 | I37: =+G37/H37 -> 0.45686275 | J37: 100 | K37: 0 | L37: 0 | M37: 0 | O37: 0 | P37: =+J37*E37 -> 2010 | Q37: =+K37*E37 -> 0 | R37: =+L37*E37 -> 0 | S37: =+M37*E37 -> 0 | T37: =+N37*E37 -> 0 | U37: =+O37*E37 -> 0 | V37: 103 | W37: 44 | X37: 31 | Y37: 33 | Z37: 22 | AA37: 18 | AB37: =+IFERROR(V37/H37,"") -> 1.0098039 | AC37: =+IFERROR(W37/H37,"") -> 0.43137255 | AD37: =+IFERROR(X37/H37,"") -> 0.30392157 | AE37: =+IFERROR(Y37/H37,"") -> 0.32352941 | AF37: =+IFERROR(Z37/H37,"") -> 0.21568627 | AG37: =+IFERROR(AA37/H37,"") -> 0.17647059 | AH37: 3054.22 | AI37: 1223.83 | AJ37: 1223.83 | AK37: 827.66 | AL37: 971.14 | AM37: 364.14 | AN37: Above 11% | AO37: 3125 | AP37: 0 | AQ37: 0 | AR37: 0 | AS37: 0 | AT37: 0 | AU37: 0 | AV37: 0 | AW37: 0 | AX37: 0 | AY37: 0 | AZ37: 0
A38: 5251J | B38: EPILIM CHRONO MR 750MG GRAN SACH 30 | D38: Old Line | E38: 18.78 | F38: 600 | G38: =F38/2 -> 300 | H38: 176 | I38: =+G38/H38 -> 1.7045455 | J38: 0 | K38: 0 | L38: 0 | M38: 213 | O38: 0 | P38: =+J38*E38 -> 0 | Q38: =+K38*E38 -> 0 | R38: =+L38*E38 -> 0 | S38: =+M38*E38 -> 4000.14 | T38: =+N38*E38 -> 0 | U38: =+O38*E38 -> 0 | V38: 16 | W38: 305 | X38: 61 | Y38: 0 | Z38: 38 | AA38: 140 | AB38: =+IFERROR(V38/H38,"") -> 0.090909091 | AC38: =+IFERROR(W38/H38,"") -> 1.7329545 | AD38: =+IFERROR(X38/H38,"") -> 0.34659091 | AE38: =+IFERROR(Y38/H38,"") -> 0 | AF38: =+IFERROR(Z38/H38,"") -> 0.21590909 | AG38: =+IFERROR(AA38/H38,"") -> 0.79545455 | AH38: 255.76 | AI38: 2809.92 | AJ38: 2809.92 | AK38: 1138.8 | AL38: 713.64 | AM38: 2559.06 | AN38: Above 11% | AO38: 0 | AP38: 0 | AQ38: 0 | AR38: 2066.25 | AS38: 0 | AT38: 0 | AU38: 410 | AV38: 5750.12 | AW38: 1726.84 | AX38: 0 | AY38: 1074.2 | AZ38: 3917.06
A39: 5092 | B39: Briviact F/C 50mg Tablets 56s | D39: Old Line | E39: 18.23 | F39: 1500 | G39: =F39/2 -> 750 | H39: 4846 | I39: =+G39/H39 -> 0.15476682 | J39: 398.18182 | K39: 0 | L39: 245 | M39: 144 | N39: 490 | O39: 475 | P39: =+J39*E39 -> 7258.8545 | Q39: =+K39*E39 -> 0 | R39: =+L39*E39 -> 4466.35 | S39: =+M39*E39 -> 2625.12 | T39: =+N39*E39 -> 8932.7 | U39: =+O39*E39 -> 8659.25 | V39: 1008 | W39: 542 | X39: 49 | Y39: 975 | Z39: 1524 | AA39: 1130 | AB39: =+IFERROR(V39/H39,"") -> 0.2080066 | AC39: =+IFERROR(W39/H39,"") -> 0.11184482 | AD39: =+IFERROR(X39/H39,"") -> 0.010111432 | AE39: =+IFERROR(Y39/H39,"") -> 0.20119686 | AF39: =+IFERROR(Z39/H39,"") -> 0.31448617 | AG39: =+IFERROR(AA39/H39,"") -> 0.23318201 | AH39: 2197.37 | AI39: 2838.07 | AJ39: 2838.07 | AK39: 2158.22 | AL39: 42398.23 | AM39: 16181.12 | AN39: Above 11% | AO39: 5674.5 | AP39: 0 | AQ39: 17369.15 | AR39: 10195.2 | AS39: 34846.55 | AT39: 33335.5 | AU39: 0 | AV39: 0 | AW39: 0 | AX39: 0 | AY39: 0 | AZ39: 0
A40: 5427 | B40: Maxalt 10mg Tablets 6 | D40: Old Line | E40: 18.11 | F40: 58.2 | G40: =F40/2 -> 29.1 | H40: 291 | I40: =+G40/H40 -> 0.1 | J40: 0 | K40: 0 | L40: 0 | M40: 0 | O40: 0 | P40: =+J40*E40 -> 0 | Q40: =+K40*E40 -> 0 | R40: =+L40*E40 -> 0 | S40: =+M40*E40 -> 0 | T40: =+N40*E40 -> 0 | U40: =+O40*E40 -> 0 | V40: 0 | W40: 0 | X40: 0 | Y40: 0 | Z40: 0 | AA40: 0 | AB40: =+IFERROR(V40/H40,"") -> 0 | AC40: =+IFERROR(W40/H40,"") -> 0 | AD40: =+IFERROR(X40/H40,"") -> 0 | AE40: =+IFERROR(Y40/H40,"") -> 0 | AF40: =+IFERROR(Z40/H40,"") -> 0 | AG40: =+IFERROR(AA40/H40,"") -> 0 | AH40: 0 | AI40: 0 | AJ40: 0 | AK40: 0 | AL40: 0 | AM40: 0 | AN40: Above 11% | AO40: 0 | AP40: 0 | AQ40: 0 | AR40: 0 | AS40: 0 | AT40: 0 | AU40: 0 | AV40: 0 | AW40: 0 | AX40: 0 | AY40: 0 | AZ40: 0
A41: 5284D | B41: Buccolam 7.5Mg/1.5ml oral syringe 4s | D41: New Line | E41: 17.67 | F41: 500 | G41: =F41/2 -> 250 | H41: 469 | I41: =+G41/H41 -> 0.53304904 | J41: 0 | K41: 0 | L41: 50 | M41: 192 | O41: 0 | P41: =+J41*E41 -> 0 | Q41: =+K41*E41 -> 0 | R41: =+L41*E41 -> 883.5 | S41: =+M41*E41 -> 3392.64 | T41: =+N41*E41 -> 0 | U41: =+O41*E41 -> 0 | V41: 134 | W41: 168 | X41: 138 | Y41: 147 | Z41: 106 | AA41: 196 | AB41: =+IFERROR(V41/H41,"") -> 0.28571429 | AC41: =+IFERROR(W41/H41,"") -> 0.35820896 | AD41: =+IFERROR(X41/H41,"") -> 0.29424307 | AE41: =+IFERROR(Y41/H41,"") -> 0.31343284 | AF41: =+IFERROR(Z41/H41,"") -> 0.22601279 | AG41: =+IFERROR(AA41/H41,"") -> 0.41791045 | AH41: 626.55 | AI41: 767.84 | AJ41: 767.84 | AK41: 875.43 | AL41: 824.52 | AM41: 3350 | AN41: Above 11% | AO41: 0 | AP41: 0 | AQ41: 3009 | AR41: 11554.56 | AS41: 0 | AT41: 0 | AU41: 11611.87 | AV41: 14540.48 | AW41: 11917.41 | AX41: 12571.47 | AY41: 8952.65 | AZ41: 16546.68
A42: 1050 | B42: Ursodeoxycholic Acid 150mg Tablets 60 | C42: Top 5 | D42: Old Line | E42: 17.12 | F42: 1946.4 | G42: =F42/2 -> 973.2 | H42: 2199 | I42: =+G42/H42 -> 0.4425648 | J42: 0 | K42: 0 | L42: 0 | M42: 0 | N42: 160 | O42: 1016 | P42: =+J42*E42 -> 0 | Q42: =+K42*E42 -> 0 | R42: =+L42*E42 -> 0 | S42: =+M42*E42 -> 0 | T42: =+N42*E42 -> 2739.2 | U42: =+O42*E42 -> 17393.92 | V42: 587 | W42: 912 | X42: 412 | Y42: 1995 | Z42: 960 | AA42: 633 | AB42: =+IFERROR(V42/H42,"") -> 0.26693952 | AC42: =+IFERROR(W42/H42,"") -> 0.41473397 | AD42: =+IFERROR(X42/H42,"") -> 0.18735789 | AE42: =+IFERROR(Y42/H42,"") -> 0.90723056 | AF42: =+IFERROR(Z42/H42,"") -> 0.43656207 | AG42: =+IFERROR(AA42/H42,"") -> 0.28785812 | AH42: 2676 | AI42: 1728.66 | AJ42: 1728.66 | AK42: 111.38 | AL42: 16435.2 | AM42: 6418.41 | AN42: Above 11% | AO42: 0 | AP42: 0 | AQ42: 0 | AR42: 0 | AS42: 803.2 | AT42: 5169.51 | AU42: 0 | AV42: 0 | AW42: 0 | AX42: 0 | AY42: 0 | AZ42: 0
A43: 0360 | B43: Ontozry 50mg Tabs 28 | D43: New Line | E43: 16.69 | F43: 1000 | G43: =F43/2 -> 500 | H43: 2287 | I43: =+G43/H43 -> 0.21862702 | J43: 0 | K43: 0 | L43: 0 | M43: 0 | N43: 60 | O43: 161 | P43: =+J43*E43 -> 0 | Q43: =+K43*E43 -> 0 | R43: =+L43*E43 -> 0 | S43: =+M43*E43 -> 0 | T43: =+N43*E43 -> 1001.4 | U43: =+O43*E43 -> 2687.09 | V43: 0 | W43: 0 | X43: 0 | Y43: 0 | Z43: 0 | AA43: 0 | AB43: =+IFERROR(V43/H43,"") -> 0 | AC43: =+IFERROR(W43/H43,"") -> 0 | AD43: =+IFERROR(X43/H43,"") -> 0 | AE43: =+IFERROR(Y43/H43,"") -> 0 | AF43: =+IFERROR(Z43/H43,"") -> 0 | AG43: =+IFERROR(AA43/H43,"") -> 0 | AH43: 0 | AI43: 0 | AJ43: 0 | AK43: 0 | AL43: 0 | AM43: 0 | AN43: Below 11% | AO43: 0 | AP43: 0 | AQ43: 0 | AR43: 0 | AS43: 4194.6 | AT43: 11265.98 | AU43: 0 | AV43: 0 | AW43: 0 | AX43: 0 | AY43: 0 | AZ43: 0
A44: L9021B | B44: Inegy 10mg/20mg Tablets 30 | D44: Old Line | E44: 15.938362 | F44: 50 | G44: =F44/2 -> 25 | H44: 14 | I44: =+G44/H44 -> 1.7857143 | J44: 0 | K44: 0 | L44: 0 | M44: 0 | N44: 0 | O44: 90 | U44: =+O44*E44 -> 1434.4526 | AB44: =+IFERROR(V44/H44,"") -> 0 | AC44: =+IFERROR(W44/H44,"") -> 0 | AD44: =+IFERROR(X44/H44,"") -> 0 | AE44: =+IFERROR(Y44/H44,"") -> 0 | AF44: =+IFERROR(Z44/H44,"") -> 0 | AG44: =+IFERROR(AA44/H44,"") -> 0 | AN44: Above 11% | AO44: 0 | AP44: 0 | AQ44: 0 | AR44: 0 | AS44: 0 | AT44: 1017 | AU44: 437.12 | AV44: 1030.9 | AW44: 436.25 | AX44: 380.07 | AY44: 883.29 | AZ44: 839.82
A45: 5733B | B45: Zonegran 100mg Capsules 56 | D45: Old Line | E45: 14.07 | F45: 1000 | G45: =F45/2 -> 500 | H45: 1313 | I45: =+G45/H45 -> 0.38080731 | J45: 183 | K45: 564 | L45: 397 | M45: 243 | N45: 53 | O45: 127 | P45: =+J45*E45 -> 2574.81 | Q45: =+K45*E45 -> 7935.48 | R45: =+L45*E45 -> 5585.79 | S45: =+M45*E45 -> 3419.01 | T45: =+N45*E45 -> 745.71 | U45: =+O45*E45 -> 1786.89 | V45: 172 | W45: 506 | X45: 487 | Y45: 249 | Z45: 608 | AA45: 168 | AB45: =+IFERROR(V45/H45,"") -> 0.13099772 | AC45: =+IFERROR(W45/H45,"") -> 0.385377 | AD45: =+IFERROR(X45/H45,"") -> 0.37090632 | AE45: =+IFERROR(Y45/H45,"") -> 0.18964204 | AF45: =+IFERROR(Z45/H45,"") -> 0.46306169 | AG45: =+IFERROR(AA45/H45,"") -> 0.12795126 | AH45: 1868.82 | AI45: 4865.32 | AJ45: 4865.32 | AK45: 4468.56 | AL45: 2282.35 | AM45: 2377.31 | AN45: Above 11% | AO45: 8301.66 | AP45: 26103.71 | AQ45: 17782.46 | AR45: 9450.8 | AS45: 2110.46 | AT45: 5062.02 | AU45: 9484.82 | AV45: 27975.66 | AW45: 26766.67 | AX45: 13608.55 | AY45: 32799.98 | AZ45: 8830.87
A46: 0211F | B46: Cabergoline 2mg Tablets 20 | D46: Old Line | E46: 14.02 | F46: 120 | G46: =F46/2 -> 60 | H46: 27 | I46: =+G46/H46 -> 2.2222222 | J46: 0 | K46: 0 | L46: 100 | M46: 95 | O46: 0 | P46: =+J46*E46 -> 0 | Q46: =+K46*E46 -> 0 | R46: =+L46*E46 -> 1402 | S46: =+M46*E46 -> 1331.9 | T46: =+N46*E46 -> 0 | U46: =+O46*E46 -> 0 | V46: 9 | W46: 11 | X46: 3 | Y46: 3 | Z46: 9 | AA46: 30 | AB46: =+IFERROR(V46/H46,"") -> 0.33333333 | AC46: =+IFERROR(W46/H46,"") -> 0.40740741 | AD46: =+IFERROR(X46/H46,"") -> 0.11111111 | AE46: =+IFERROR(Y46/H46,"") -> 0.11111111 | AF46: =+IFERROR(Z46/H46,"") -> 0.33333333 | AG46: =+IFERROR(AA46/H46,"") -> 1.1111111 | AH46: 122.14 | AI46: 117.83 | AJ46: 117.83 | AK46: 55.8 | AL46: 32.66 | AM46: 325.34 | AN46: Above 11% | AO46: 0 | AP46: 0 | AQ46: 1687 | AR46: 1608.35 | AS46: 0 | AT46: 0 | AU46: 305.38 | AV46: 324.63 | AW46: 108.3 | AX46: 83.66 | AY46: 261.94 | AZ46: 831.44
A47: L9597B | B47: Neupro 6mg/24hr Transdermal Patches 28 | D47: Old Line | E47: 13.9 | F47: 600 | G47: =F47/2 -> 300 | H47: 1585 | I47: =+G47/H47 -> 0.18927445 | J47: 0 | K47: 50 | L47: 123 | M47: 149 | O47: 400 | P47: =+J47*E47 -> 0 | Q47: =+K47*E47 -> 695 | R47: =+L47*E47 -> 1709.7 | S47: =+M47*E47 -> 2071.1 | T47: =+N47*E47 -> 0 | U47: =+O47*E47 -> 5560 | V47: 172 | W47: 191 | X47: 14 | Y47: 137 | Z47: 12 | AA47: 49 | AB47: =+IFERROR(V47/H47,"") -> 0.10851735 | AC47: =+IFERROR(W47/H47,"") -> 0.12050473 | AD47: =+IFERROR(X47/H47,"") -> 0.0088328076 | AE47: =+IFERROR(Y47/H47,"") -> 0.086435331 | AF47: =+IFERROR(Z47/H47,"") -> 0.0075709779 | AG47: =+IFERROR(AA47/H47,"") -> 0.030914826 | AH47: 1779.1 | AI47: 2145.45 | AJ47: 2145.45 | AK47: 199.95 | AL47: 1751.26 | AM47: 695.98 | AN47: Above 11% | AO47: 0 | AP47: 3141.5 | AQ47: 7722.38 | AR47: 8757.02 | AS47: 0 | AT47: 23108.5 | AU47: 13254.29 | AV47: 14623.48 | AW47: 1079.7 | AX47: 10383.63 | AY47: 881.29 | AZ47: 3571.3
A48: 5040 | B48: Vesicare oral suspension 1mg/ml 1's | D48: New Line | E48: 13.603612 | F48: 500 | G48: =F48/2 -> 250 | H48: 1202 | I48: =+G48/H48 -> 0.20798669 | J48: 0 | K48: 0 | L48: 0 | M48: 0 | N48: 0 | O48: 235 | U48: =+O48*E48 -> 3196.8488 | AB48: =+IFERROR(V48/H48,"") -> 0 | AC48: =+IFERROR(W48/H48,"") -> 0 | AD48: =+IFERROR(X48/H48,"") -> 0 | AE48: =+IFERROR(Y48/H48,"") -> 0 | AF48: =+IFERROR(Z48/H48,"") -> 0 | AG48: =+IFERROR(AA48/H48,"") -> 0 | AN48: Above 11% | AO48: 0 | AP48: 0 | AQ48: 0 | AR48: 0 | AS48: 0 | AT48: 3211.36 | AU48: 0 | AV48: 0 | AW48: 0 | AX48: 0 | AY48: 0 | AZ48: 0
A49: 5949 | B49: Loprazolam 1mg Tablets 30 | D49: Old Line | E49: 13.29 | F49: 500 | G49: =F49/2 -> 250 | H49: 704 | I49: =+G49/H49 -> 0.35511364 | J49: 0 | K49: 0 | L49: 0 | M49: 0 | N49: 500 | O49: 0 | P49: =+J49*E49 -> 0 | Q49: =+K49*E49 -> 0 | R49: =+L49*E49 -> 0 | S49: =+M49*E49 -> 0 | T49: =+N49*E49 -> 6645 | U49: =+O49*E49 -> 0 | V49: 113 | W49: 18 | X49: 105 | Y49: 77 | Z49: 0 | AA49: 108 | AB49: =+IFERROR(V49/H49,"") -> 0.16051136 | AC49: =+IFERROR(W49/H49,"") -> 0.025568182 | AD49: =+IFERROR(X49/H49,"") -> 0.14914773 | AE49: =+IFERROR(Y49/H49,"") -> 0.109375 | AF49: =+IFERROR(Z49/H49,"") -> 0 | AG49: =+IFERROR(AA49/H49,"") -> 0.15340909 | AH49: 299.48 | AI49: 140.31 | AJ49: 140.31 | AK49: 1182.11 | AL49: 372.1 | AM49: 1393.46 | AN49: Above 11% | AO49: 0 | AP49: 0 | AQ49: 0 | AR49: 0 | AS49: 1190 | AT49: 0 | AU49: 0 | AV49: 0 | AW49: 0 | AX49: 0 | AY49: 0 | AZ49: 0
A50: 5591 | B50: Tranylcypromine 10mg Tablets 28 | D50: New Line | E50: 12.76 | F50: 400 | G50: =F50/2 -> 200 | H50: 265 | I50: =+G50/H50 -> 0.75471698 | J50: 0 | K50: 0 | L50: 0 | M50: 0 | N50: 11 | O50: 0 | P50: =+J50*E50 -> 0 | Q50: =+K50*E50 -> 0 | R50: =+L50*E50 -> 0 | S50: =+M50*E50 -> 0 | T50: =+N50*E50 -> 140.36 | U50: =+O50*E50 -> 0 | V50: 62 | W50: 107 | X50: -4 | Y50: -5 | Z50: 20 | AA50: 0 | AB50: =+IFERROR(V50/H50,"") -> 0.23396226 | AC50: =+IFERROR(W50/H50,"") -> 0.40377358 | AD50: =+IFERROR(X50/H50,"") -> -0.01509434 | AE50: =+IFERROR(Y50/H50,"") -> -0.018867925 | AF50: =+IFERROR(Z50/H50,"") -> 0.075471698 | AG50: =+IFERROR(AA50/H50,"") -> 0 | AH50: 375.09 | AI50: 329 | AJ50: 329 | AK50: 0 | AL50: 255.2 | AM50: 0 | AN50: Below 11% | AO50: 0 | AP50: 0 | AQ50: 0 | AR50: 0 | AS50: 181.72 | AT50: 0 | AU50: 0 | AV50: 0 | AW50: 0 | AX50: 0 | AY50: 0 | AZ50: 0
A51: 5429A | B51: Nalcrom 100mg Capsules 100 | C51: Top 5 | D51: Old Line | E51: 12.7 | F51: 1000 | G51: =F51/2 -> 500 | H51: 1449 | I51: =+G51/H51 -> 0.34506556 | J51: 1699.2 | K51: 1620 | L51: 1022.8 | M51: 1000 | N51: 2000 | O51: 4000 | P51: =+J51*E51 -> 21579.84 | Q51: =+K51*E51 -> 20574 | R51: =+L51*E51 -> 12989.56 | S51: =+M51*E51 -> 12700 | T51: =+N51*E51 -> 25400 | U51: =+O51*E51 -> 50800 | V51: 90 | W51: 49 | X51: 0 | Y51: 399 | Z51: 297 | AA51: 712 | AB51: =+IFERROR(V51/H51,"") -> 0.062111801 | AC51: =+IFERROR(W51/H51,"") -> 0.033816425 | AD51: =+IFERROR(X51/H51,"") -> 0 | AE51: =+IFERROR(Y51/H51,"") -> 0.27536232 | AF51: =+IFERROR(Z51/H51,"") -> 0.20496894 | AG51: =+IFERROR(AA51/H51,"") -> 0.49137336 | AH51: 715.63 | AI51: 372.71 | AJ51: 372.71 | AK51: 5067.3 | AL51: 2399.2 | AM51: 5935.84 | AN51: Above 11% | AO51: 0 | AP51: 0 | AQ51: 0 | AR51: 0 | AS51: 0 | AT51: 0 | AU51: 3376.03 | AV51: 1821.15 | AW51: 0 | AX51: 12852.82 | AY51: 9284.05 | AZ51: 22018.93
A52: 5680F | B52: Adartrel 0.5mg Tablets 84 | D52: Old Line | E52: 12.02 | F52: 2000 | G52: =F52/2 -> 1000 | H52: 8803 | I52: =+G52/H52 -> 0.11359764 | J52: 0 | K52: 2778.7879 | L52: 2906.0606 | M52: 3960.6061 | N52: 4057.5758 | O52: 750 | P52: =+J52*E52 -> 0 | Q52: =+K52*E52 -> 33401.03 | R52: =+L52*E52 -> 34930.848 | S52: =+M52*E52 -> 47606.485 | T52: =+N52*E52 -> 48772.061 | U52: =+O52*E52 -> 9015 | V52: 0 | W52: 0 | X52: 0 | Y52: 0 | Z52: 0 | AA52: 0 | AB52: =+IFERROR(V52/H52,"") -> 0 | AC52: =+IFERROR(W52/H52,"") -> 0 | AD52: =+IFERROR(X52/H52,"") -> 0 | AE52: =+IFERROR(Y52/H52,"") -> 0 | AF52: =+IFERROR(Z52/H52,"") -> 0 | AG52: =+IFERROR(AA52/H52,"") -> 0 | AH52: 0 | AI52: 0 | AJ52: 0 | AK52: 0 | AL52: 0 | AM52: 0 | AN52: Above 11% | AO52: 1262.56 | AP52: 4259.8 | AQ52: 4614.05 | AR52: 6252.79 | AS52: 6440.45 | AT52: 3624.14 | AU52: 0 | AV52: 0 | AW52: 0 | AX52: 0 | AY52: 0 | AZ52: 0
A53: 5945 | B53: Innozide 20mg/12.5mg Tablets 28 | D53: Old Line | E53: 11.88 | F53: 1000 | G53: =F53/2 -> 500 | H53: 364 | I53: =+G53/H53 -> 1.3736264 | J53: 0 | K53: 0 | L53: 0 | M53: 301 | O53: 542 | P53: =+J53*E53 -> 0 | Q53: =+K53*E53 -> 0 | R53: =+L53*E53 -> 0 | S53: =+M53*E53 -> 3575.88 | T53: =+N53*E53 -> 0 | U53: =+O53*E53 -> 6438.96 | V53: 0 | W53: 8 | X53: 0 | Y53: 0 | Z53: 7 | AA53: 100 | AB53: =+IFERROR(V53/H53,"") -> 0 | AC53: =+IFERROR(W53/H53,"") -> 0.021978022 | AD53: =+IFERROR(X53/H53,"") -> 0 | AE53: =+IFERROR(Y53/H53,"") -> 0 | AF53: =+IFERROR(Z53/H53,"") -> 0.019230769 | AG53: =+IFERROR(AA53/H53,"") -> 0.27472527 | AH53: 0 | AI53: 14.16 | AJ53: 14.16 | AK53: 0 | AL53: 83.16 | AM53: 354.93 | AN53: Above 11% | AO53: 0 | AP53: 0 | AQ53: 0 | AR53: 370.23 | AS53: 0 | AT53: 659.32 | AU53: 0 | AV53: 0 | AW53: 0 | AX53: 0 | AY53: 0 | AZ53: 0
A54: 5031 | B54: Xultophy solution for injection pre-filled pens 100iu/ml/3.6mg/ml | D54: New Line | E54: 11.87 | F54: 400 | G54: =F54/2 -> 200 | H54: 849 | I54: =+G54/H54 -> 0.23557126 | J54: 0 | K54: 0 | L54: 120 | M54: 1000 | N54: 600 | O54: 0 | P54: =+J54*E54 -> 0 | Q54: =+K54*E54 -> 0 | R54: =+L54*E54 -> 1424.4 | S54: =+M54*E54 -> 11870 | T54: =+N54*E54 -> 7122 | U54: =+O54*E54 -> 0 | V54: 0 | W54: 79 | X54: 255 | Y54: 274 | Z54: 956 | AA54: 206 | AB54: =+IFERROR(V54/H54,"") -> 0 | AC54: =+IFERROR(W54/H54,"") -> 0.093050648 | AD54: =+IFERROR(X54/H54,"") -> 0.30035336 | AE54: =+IFERROR(Y54/H54,"") -> 0.32273263 | AF54: =+IFERROR(Z54/H54,"") -> 1.1260306 | AG54: =+IFERROR(AA54/H54,"") -> 0.2426384 | AH54: 0 | AI54: 230.6 | AJ54: 230.6 | AK54: 800.48 | AL54: 866.46 | AM54: 1857.23 | AN54: Above 11% | AO54: 0 | AP54: 0 | AQ54: 9643.2 | AR54: 79650 | AS54: 48216 | AT54: 0 | AU54: 0 | AV54: 0 | AW54: 0 | AX54: 0 | AY54: 0 | AZ54: 0
A55: 5284C | B55: Buccolam 5Mg /1ml oral syringe 4s | D55: Old Line | E55: 11.75 | F55: 300 | G55: =F55/2 -> 150 | H55: 367 | I55: =+G55/H55 -> 0.40871935 | J55: 100 | K55: 0 | L55: 50 | M55: 135 | O55: 0 | P55: =+J55*E55 -> 1175 | Q55: =+K55*E55 -> 0 | R55: =+L55*E55 -> 587.5 | S55: =+M55*E55 -> 1586.25 | T55: =+N55*E55 -> 0 | U55: =+O55*E55 -> 0 | V55: 174 | W55: 235 | X55: 123 | Y55: 166 | Z55: 187 | AA55: 184 | AB55: =+IFERROR(V55/H55,"") -> 0.47411444 | AC55: =+IFERROR(W55/H55,"") -> 0.64032698 | AD55: =+IFERROR(X55/H55,"") -> 0.33514986 | AE55: =+IFERROR(Y55/H55,"") -> 0.45231608 | AF55: =+IFERROR(Z55/H55,"") -> 0.50953678 | AG55: =+IFERROR(AA55/H55,"") -> 0.5013624 | AH55: 822.51 | AI55: 1075.57 | AJ55: 1075.57 | AK55: 418.41 | AL55: 1379.46 | AM55: 2109.49 | AN55: Above 11% | AO55: 7589 | AP55: 0 | AQ55: 3009 | AR55: 8124.3 | AS55: 0 | AT55: 0 | AU55: 14589.57 | AV55: 19662.48 | AW55: 10141.56 | AX55: 13894.84 | AY55: 15592.3 | AZ55: 15219.81
A56: 5427A | B56: Maxalt 5mg Tablets 6 | D56: Old Line | E56: 11.52 | F56: 66.8 | G56: =F56/2 -> 33.4 | H56: 109 | I56: =+G56/H56 -> 0.30642202 | J56: 78 | K56: 0 | L56: 0 | M56: 0 | O56: 0 | P56: =+J56*E56 -> 898.56 | Q56: =+K56*E56 -> 0 | R56: =+L56*E56 -> 0 | S56: =+M56*E56 -> 0 | T56: =+N56*E56 -> 0 | U56: =+O56*E56 -> 0 | V56: 0 | W56: 102 | X56: 65 | Y56: 0 | Z56: 0 | AA56: 0 | AB56: =+IFERROR(V56/H56,"") -> 0 | AC56: =+IFERROR(W56/H56,"") -> 0.93577982 | AD56: =+IFERROR(X56/H56,"") -> 0.59633028 | AE56: =+IFERROR(Y56/H56,"") -> 0 | AF56: =+IFERROR(Z56/H56,"") -> 0 | AG56: =+IFERROR(AA56/H56,"") -> 0 | AH56: 0 | AI56: 293.54 | AJ56: 293.54 | AK56: 686.46 | AL56: 0 | AM56: 0 | AN56: Above 11% | AO56: 673.48 | AP56: 0 | AQ56: 0 | AR56: 0 | AS56: 0 | AT56: 0 | AU56: 0 | AV56: 1172.78 | AW56: 1246.76 | AX56: 0 | AY56: 0 | AZ56: 0
A57: 5934D | B57: Xarelto 20mg Tablets 28 | D57: Old Line | E57: 11.52 | F57: 700 | G57: =F57/2 -> 350 | H57: 695 | I57: =+G57/H57 -> 0.50359712 | J57: 1285.7143 | K57: 178.57143 | L57: 0 | M57: 0 | O57: 450 | P57: =+J57*E57 -> 14811.429 | Q57: =+K57*E57 -> 2057.1429 | R57: =+L57*E57 -> 0 | S57: =+M57*E57 -> 0 | T57: =+N57*E57 -> 0 | U57: =+O57*E57 -> 5184 | V57: 116 | W57: 238 | X57: 546 | Y57: 337 | Z57: 760 | AA57: 461 | AB57: =+IFERROR(V57/H57,"") -> 0.16690647 | AC57: =+IFERROR(W57/H57,"") -> 0.34244604 | AD57: =+IFERROR(X57/H57,"") -> 0.78561151 | AE57: =+IFERROR(Y57/H57,"") -> 0.48489209 | AF57: =+IFERROR(Z57/H57,"") -> 1.0935252 | AG57: =+IFERROR(AA57/H57,"") -> 0.66330935 | AH57: 293.85 | AI57: 2579.79 | AJ57: 2579.79 | AK57: 5996.62 | AL57: 3958.27 | AM57: 5051.39 | AN57: Above 11% | AO57: 41169.56 | AP57: 4464.5 | AQ57: 0 | AR57: 0 | AS57: 0 | AT57: 11842.5 | AU57: 4645.06 | AV57: 9125.64 | AW57: 22097.4 | AX57: 13725.99 | AY57: 30644.81 | AZ57: 18413.1
A58: 5250F | B58: Targinact 10mg/5mg Modified Release Tablets 56 | D58: Old Line | E58: 11.01 | F58: 200 | G58: =F58/2 -> 100 | H58: 547 | I58: =+G58/H58 -> 0.18281536 | J58: 0 | K58: 500 | L58: 594 | M58: 0 | O58: 0 | P58: =+J58*E58 -> 0 | Q58: =+K58*E58 -> 5505 | R58: =+L58*E58 -> 6539.94 | S58: =+M58*E58 -> 0 | T58: =+N58*E58 -> 0 | U58: =+O58*E58 -> 0 | V58: 93 | W58: 0 | X58: 98 | Y58: 107 | Z58: 90 | AA58: 85 | AB58: =+IFERROR(V58/H58,"") -> 0.17001828 | AC58: =+IFERROR(W58/H58,"") -> 0 | AD58: =+IFERROR(X58/H58,"") -> 0.17915905 | AE58: =+IFERROR(Y58/H58,"") -> 0.19561243 | AF58: =+IFERROR(Z58/H58,"") -> 0.16453382 | AG58: =+IFERROR(AA58/H58,"") -> 0.15539305 | AH58: 360.89 | AI58: 0 | AJ58: 1078.98 | AK58: 341.09 | AL58: 444.39 | AM58: 888.58 | AN58: Above 11% | AO58: 0 | AP58: 7810 | AQ58: 9201.06 | AR58: 0 | AS58: 0 | AT58: 0 | AU58: 1801.46 | AV58: 0 | AW58: 1845.97 | AX58: 2084.94 | AY58: 2364.67 | AZ58: 2205.23
A59: 5754 | B59: Zyprexa 10mg (Olanzepine) Tablets 28 | D59: Old Line | E59: 10.96 | F59: 70 | G59: =F59/2 -> 35 | H59: 148 | I59: =+G59/H59 -> 0.23648649 | J59: 100 | K59: 0 | L59: 0 | M59: 0 | O59: 0 | P59: =+J59*E59 -> 1096 | Q59: =+K59*E59 -> 0 | R59: =+L59*E59 -> 0 | S59: =+M59*E59 -> 0 | T59: =+N59*E59 -> 0 | U59: =+O59*E59 -> 0 | V59: 0 | W59: 0 | X59: 0 | Y59: 0 | Z59: 55 | AA59: 64 | AB59: =+IFERROR(V59/H59,"") -> 0 | AC59: =+IFERROR(W59/H59,"") -> 0 | AD59: =+IFERROR(X59/H59,"") -> 0 | AE59: =+IFERROR(Y59/H59,"") -> 0 | AF59: =+IFERROR(Z59/H59,"") -> 0.37162162 | AG59: =+IFERROR(AA59/H59,"") -> 0.43243243 | AH59: 0 | AI59: 0 | AJ59: 0 | AK59: 0 | AL59: 602.8 | AM59: 1206.68 | AN59: Above 11% | AO59: 1250 | AP59: 0 | AQ59: 0 | AR59: 0 | AS59: 0 | AT59: 0 | AU59: 0 | AV59: 0 | AW59: 0 | AX59: 0 | AY59: 0 | AZ59: 0
A60: 5774 | B60: Relpax 40mg Tablets 6 | D60: Old Line | E60: 10.7 | F60: 500 | G60: =F60/2 -> 250 | H60: 1821 | I60: =+G60/H60 -> 0.1372872 | J60: 0 | K60: 100 | L60: 0 | M60: 0 | N60: 89 | O60: 0 | P60: =+J60*E60 -> 0 | Q60: =+K60*E60 -> 1070 | R60: =+L60*E60 -> 0 | S60: =+M60*E60 -> 0 | T60: =+N60*E60 -> 952.3 | U60: =+O60*E60 -> 0 | V60: 52 | W60: 269 | X60: 1 | Y60: 0 | Z60: 0 | AA60: 1 | AB60: =+IFERROR(V60/H60,"") -> 0.028555739 | AC60: =+IFERROR(W60/H60,"") -> 0.14772103 | AD60: =+IFERROR(X60/H60,"") -> 0.00054914882 | AE60: =+IFERROR(Y60/H60,"") -> 0 | AF60: =+IFERROR(Z60/H60,"") -> 0 | AG60: =+IFERROR(AA60/H60,"") -> 0.00054914882 | AH60: 23.55 | AI60: 220.65 | AJ60: 220.65 | AK60: 0.07 | AL60: 0 | AM60: 10.7 | AN60: Above 11% | AO60: 0 | AP60: 1205 | AQ60: 0 | AR60: 0 | AS60: 942.68 | AT60: 0 | AU60: 0 | AV60: 0 | AW60: 0 | AX60: 0 | AY60: 0 | AZ60: 0
A61: L9117 | B61: Exforge 10mg/160mg Tablets 28 | D61: Old Line | E61: 10.35 | F61: 1000 | G61: =F61/2 -> 500 | H61: 782 | I61: =+G61/H61 -> 0.63938619 | J61: 377 | K61: 711 | L61: 272 | M61: 494 | N61: 530 | O61: 303 | P61: =+J61*E61 -> 3901.95 | Q61: =+K61*E61 -> 7358.85 | R61: =+L61*E61 -> 2815.2 | S61: =+M61*E61 -> 5112.9 | T61: =+N61*E61 -> 5485.5 | U61: =+O61*E61 -> 3136.05 | V61: 53 | W61: 66 | X61: 273 | Y61: 214 | Z61: 364 | AA61: 492 | AB61: =+IFERROR(V61/H61,"") -> 0.067774936 | AC61: =+IFERROR(W61/H61,"") -> 0.084398977 | AD61: =+IFERROR(X61/H61,"") -> 0.34910486 | AE61: =+IFERROR(Y61/H61,"") -> 0.27365729 | AF61: =+IFERROR(Z61/H61,"") -> 0.46547315 | AG61: =+IFERROR(AA61/H61,"") -> 0.62915601 | AH61: 55.77 | AI61: 223.94 | AJ61: 223.94 | AK61: 1342.73 | AL61: 1149.67 | AM61: 1071.21 | AN61: Above 11% | AO61: 3688.24 | AP61: 7008.7 | AQ61: 2632.19 | AR61: 5097.06 | AS61: 5210.71 | AT61: 2956.68 | AU61: 651.49 | AV61: 874.7 | AW61: 4023.42 | AX61: 3241.36 | AY61: 4648.74 | AZ61: 5986.81
A62: 4989D | B62: Co-Trimoxazole 40/200mg/5ml Oral Suspension SF 100ml | D62: Old Line | E62: 10.3 | F62: 1000 | G62: =F62/2 -> 500 | H62: 837 | I62: =+G62/H62 -> 0.59737157 | J62: 0 | K62: 520 | L62: 50 | M62: 0 | O62: 100 | P62: =+J62*E62 -> 0 | Q62: =+K62*E62 -> 5356 | R62: =+L62*E62 -> 515 | S62: =+M62*E62 -> 0 | T62: =+N62*E62 -> 0 | U62: =+O62*E62 -> 1030 | V62: 199 | W62: 4 | X62: 0 | Y62: 0 | Z62: 0 | AA62: 0 | AB62: =+IFERROR(V62/H62,"") -> 0.23775388 | AC62: =+IFERROR(W62/H62,"") -> 0.0047789725 | AD62: =+IFERROR(X62/H62,"") -> 0 | AE62: =+IFERROR(Y62/H62,"") -> 0 | AF62: =+IFERROR(Z62/H62,"") -> 0 | AG62: =+IFERROR(AA62/H62,"") -> 0 | AH62: 240.35 | AI62: 5.44 | AJ62: 5.44 | AK62: 0 | AL62: 0 | AM62: 0 | AN62: Above 11% | AO62: 1744 | AP62: 2983 | AQ62: 221 | AR62: 0 | AS62: 0 | AT62: 439 | AU62: 1653.25 | AV62: 33.84 | AW62: 0 | AX62: 0 | AY62: 0 | AZ62: 0
A63: 5879 | B63: Multaq 400mg Tablets 60 | D63: Old Line | E63: 10.07 | F63: 279.6 | G63: =F63/2 -> 139.8 | H63: 1290 | I63: =+G63/H63 -> 0.10837209 | J63: 200 | K63: 0 | L63: 0 | M63: 0 | O63: 0 | P63: =+J63*E63 -> 2014 | Q63: =+K63*E63 -> 0 | R63: =+L63*E63 -> 0 | S63: =+M63*E63 -> 0 | T63: =+N63*E63 -> 0 | U63: =+O63*E63 -> 0 | V63: 139 | W63: 184 | X63: 125 | Y63: 40 | Z63: 211 | AA63: 84 | AB63: =+IFERROR(V63/H63,"") -> 0.10775194 | AC63: =+IFERROR(W63/H63,"") -> 0.14263566 | AD63: =+IFERROR(X63/H63,"") -> 0.096899225 | AE63: =+IFERROR(Y63/H63,"") -> 0.031007752 | AF63: =+IFERROR(Z63/H63,"") -> 0.16356589 | AG63: =+IFERROR(AA63/H63,"") -> 0.065116279 | AH63: 611.49 | AI63: 1375.2 | AJ63: 1375.2 | AK63: 1292.89 | AL63: 418 | AM63: -1021 | AN63: Below 11% | AO63: 4780 | AP63: 0 | AQ63: 0 | AR63: 0 | AS63: 0 | AT63: 0 | AU63: 0 | AV63: 0 | AW63: 0 | AX63: 0 | AY63: 0 | AZ63: 0
A64: 5854 | B64: Zyprexa 2.5mg (Olanzepine)Tablets 28 | D64: Old Line | E64: 10.01 | F64: 200 | G64: =F64/2 -> 100 | H64: 68 | I64: =+G64/H64 -> 1.4705882 | J64: 0 | K64: 0 | L64: 0 | M64: 0 | O64: 0 | P64: =+J64*E64 -> 0 | Q64: =+K64*E64 -> 0 | R64: =+L64*E64 -> 0 | S64: =+M64*E64 -> 0 | T64: =+N64*E64 -> 0 | U64: =+O64*E64 -> 0 | V64: 0 | W64: 0 | X64: 0 | Y64: 0 | Z64: 0 | AA64: 0 | AB64: =+IFERROR(V64/H64,"") -> 0 | AC64: =+IFERROR(W64/H64,"") -> 0 | AD64: =+IFERROR(X64/H64,"") -> 0 | AE64: =+IFERROR(Y64/H64,"") -> 0 | AF64: =+IFERROR(Z64/H64,"") -> 0 | AG64: =+IFERROR(AA64/H64,"") -> 0 | AH64: 0 | AI64: 0 | AJ64: 0 | AK64: 0 | AL64: 0 | AM64: 0 | AN64: Above 11% | AO64: 0 | AP64: 0 | AQ64: 0 | AR64: 0 | AS64: 0 | AT64: 0 | AU64: 0 | AV64: 0 | AW64: 0 | AX64: 0 | AY64: 0 | AZ64: 0
A65: 5832 | B65: Topamax 200mg Tablets 60 | D65: Old Line | E65: 9.96 | F65: 400 | G65: =F65/2 -> 200 | H65: 334 | I65: =+G65/H65 -> 0.5988024 | J65: 90 | K65: 0 | L65: 0 | M65: 0 | O65: 31 | P65: =+J65*E65 -> 896.4 | Q65: =+K65*E65 -> 0 | R65: =+L65*E65 -> 0 | S65: =+M65*E65 -> 0 | T65: =+N65*E65 -> 0 | U65: =+O65*E65 -> 308.76 | V65: 13 | W65: 36 | X65: 0 | Y65: 0 | Z65: 168 | AA65: 0 | AB65: =+IFERROR(V65/H65,"") -> 0.038922156 | AC65: =+IFERROR(W65/H65,"") -> 0.10778443 | AD65: =+IFERROR(X65/H65,"") -> 0 | AE65: =+IFERROR(Y65/H65,"") -> 0 | AF65: =+IFERROR(Z65/H65,"") -> 0.50299401 | AG65: =+IFERROR(AA65/H65,"") -> 0 | AH65: 94.15 | AI65: 284.9 | AJ65: 284.9 | AK65: 0 | AL65: 1673.28 | AM65: 0 | AN65: Above 11% | AO65: 3294.9 | AP65: 0 | AQ65: 0 | AR65: 0 | AS65: 0 | AT65: 1152.27 | AU65: 0 | AV65: 0 | AW65: 0 | AX65: 0 | AY65: 0 | AZ65: 0
A66: 5420L | B66: Mirapexin 1.05mg Prolonged-Release Tablets 30s | D66: Old Line | E66: 9.91 | F66: 50 | G66: =F66/2 -> 25 | H66: 27 | I66: =+G66/H66 -> 0.92592593 | J66: 0 | K66: 0 | L66: 0 | M66: 0 | N66: 50 | O66: 0 | P66: =+J66*E66 -> 0 | Q66: =+K66*E66 -> 0 | R66: =+L66*E66 -> 0 | S66: =+M66*E66 -> 0 | T66: =+N66*E66 -> 495.5 | U66: =+O66*E66 -> 0 | V66: 13 | W66: 22 | X66: 13 | Y66: 9 | Z66: 12 | AA66: 11 | AB66: =+IFERROR(V66/H66,"") -> 0.48148148 | AC66: =+IFERROR(W66/H66,"") -> 0.81481481 | AD66: =+IFERROR(X66/H66,"") -> 0.48148148 | AE66: =+IFERROR(Y66/H66,"") -> 0.33333333 | AF66: =+IFERROR(Z66/H66,"") -> 0.44444444 | AG66: =+IFERROR(AA66/H66,"") -> 0.40740741 | AH66: 280.87 | AI66: 427.23 | AJ66: 427.23 | AK66: 254.04 | AL66: 154.16 | AM66: 151.46 | AN66: Above 11% | AO66: 0 | AP66: 0 | AQ66: 0 | AR66: 0 | AS66: 661 | AT66: 0 | AU66: 454.94 | AV66: 721.81 | AW66: 428.11 | AX66: 274.67 | AY66: 398.78 | AZ66: 297.65
A67: M0007 | B67: Vitaros Cream 3mg/g 4 | D67: Old Line | E67: 9.74 | F67: 2000 | G67: =F67/2 -> 1000 | H67: 2620 | I67: =+G67/H67 -> 0.38167939 | J67: 0 | K67: 0 | L67: 0 | M67: 500 | O67: 0 | P67: =+J67*E67 -> 0 | Q67: =+K67*E67 -> 0 | R67: =+L67*E67 -> 0 | S67: =+M67*E67 -> 4870 | T67: =+N67*E67 -> 0 | U67: =+O67*E67 -> 0 | V67: 559 | W67: 435 | X67: 300 | Y67: 485 | Z67: 624 | AA67: 185 | AB67: =+IFERROR(V67/H67,"") -> 0.21335878 | AC67: =+IFERROR(W67/H67,"") -> 0.16603053 | AD67: =+IFERROR(X67/H67,"") -> 0.11450382 | AE67: =+IFERROR(Y67/H67,"") -> 0.1851145 | AF67: =+IFERROR(Z67/H67,"") -> 0.23816794 | AG67: =+IFERROR(AA67/H67,"") -> 0.070610687 | AH67: 4955 | AI67: 3707.14 | AJ67: 3707.14 | AK67: 1689.7 | AL67: 2627.08 | AM67: 1474.38 | AN67: Above 11% | AO67: 0 | AP67: 0 | AQ67: 0 | AR67: 14980 | AS67: 0 | AT67: 0 | AU67: 22172.2 | AV67: 17105.14 | AW67: 11889.7 | AX67: 19120.28 | AY67: 24282.56 | AZ67: 7016.98
A68: 5337A | B68: Tresiba Flextouch 200u/ml Injection 3mlx3 | C68: Top 5 | D68: Old Line | E68: 9.55 | F68: 8000 | G68: =F68/2 -> 4000 | H68: 11469 | I68: =+G68/H68 -> 0.34876624 | J68: 4752 | K68: 3929.3333 | L68: 1810 | M68: 2188.6667 | N68: 1991.6667 | O68: 5225 | P68: =+J68*E68 -> 45381.6 | Q68: =+K68*E68 -> 37525.133 | R68: =+L68*E68 -> 17285.5 | S68: =+M68*E68 -> 20901.767 | T68: =+N68*E68 -> 19020.417 | U68: =+O68*E68 -> 49898.75 | V68: 3278 | W68: 3971 | X68: 4841 | Y68: 3803 | Z68: 4738 | AA68: 2167 | AB68: =+IFERROR(V68/H68,"") -> 0.28581393 | AC68: =+IFERROR(W68/H68,"") -> 0.34623768 | AD68: =+IFERROR(X68/H68,"") -> 0.42209434 | AE68: =+IFERROR(Y68/H68,"") -> 0.3315895 | AF68: =+IFERROR(Z68/H68,"") -> 0.41311361 | AG68: =+IFERROR(AA68/H68,"") -> 0.18894411 | AH68: 14254.78 | AI68: 20459.73 | AJ68: 20459.73 | AK68: 20469.46 | AL68: 20059.82 | AM68: 12138.56 | AN68: Above 11% | AO68: 225834.16 | AP68: 188556.34 | AQ68: 85269.16 | AR68: 97971.14 | AS68: 87916.15 | AT68: 374562.95 | AU68: 168911.95 | AV68: 207400.25 | AW68: 249975.07 | AX68: 200394.69 | AY68: 241817.2 | AZ68: 108605.38
A69: 6000 | B69: Versatis 700mg (5%) Medicated Patches 30 | D69: Old Line | E69: 9.28 | F69: 6000 | G69: =F69/2 -> 3000 | H69: 14695 | I69: =+G69/H69 -> 0.20415107 | J69: 363.5 | K69: 1319.6667 | L69: 2668.1667 | M69: 1760.5 | N69: 564.16667 | O69: 796 | P69: =+J69*E69 -> 3373.28 | Q69: =+K69*E69 -> 12246.507 | R69: =+L69*E69 -> 24760.587 | S69: =+M69*E69 -> 16337.44 | T69: =+N69*E69 -> 5235.4667 | U69: =+O69*E69 -> 7386.88 | V69: 292 | W69: 496 | X69: 1338 | Y69: 1990 | Z69: 1996 | AA69: 918 | AB69: =+IFERROR(V69/H69,"") -> 0.019870704 | AC69: =+IFERROR(W69/H69,"") -> 0.033752977 | AD69: =+IFERROR(X69/H69,"") -> 0.091051378 | AE69: =+IFERROR(Y69/H69,"") -> 0.13542021 | AF69: =+IFERROR(Z69/H69,"") -> 0.13582851 | AG69: =+IFERROR(AA69/H69,"") -> 0.062470228 | AH69: 3198.04 | AI69: 4259.48 | AJ69: 4259.48 | AK69: 8920 | AL69: 11165.92 | AM69: 5532.1 | AN69: Above 11% | AO69: 21439.01 | AP69: 80436.38 | AQ69: 165871.6 | AR69: 105600.84 | AS69: 34411.81 | AT69: 12905.24 | AU69: 0 | AV69: 0 | AW69: 0 | AX69: 0 | AY69: 0 | AZ69: 0
A70: 5905B | B70: Clexane 60mg Solution Injection Prefilled Syringes 0.6mlx10 | D70: Old Line | E70: 9.2777949 | F70: 600 | G70: =F70/2 -> 300 | H70: 933 | I70: =+G70/H70 -> 0.32154341 | J70: 0 | K70: 0 | L70: 0 | M70: 0 | N70: 0 | O70: 0 | U70: =+O70*E70 -> 0 | AB70: =+IFERROR(V70/H70,"") -> 0 | AC70: =+IFERROR(W70/H70,"") -> 0 | AD70: =+IFERROR(X70/H70,"") -> 0 | AE70: =+IFERROR(Y70/H70,"") -> 0 | AF70: =+IFERROR(Z70/H70,"") -> 0 | AG70: =+IFERROR(AA70/H70,"") -> 0 | AN70: Below 11% | AO70: 0 | AP70: 0 | AQ70: 0 | AR70: 0 | AS70: 0 | AT70: 0 | AU70: 1221.42 | AV70: 0 | AW70: 0 | AX70: 520.5 | AY70: 4702.44 | AZ70: 6538.16
A71: 5300 | B71: Keppra 1ml Syringe 100mg/ml 150ml | D71: Old Line | E71: 9.16 | F71: 500 | G71: =F71/2 -> 250 | H71: 508 | I71: =+G71/H71 -> 0.49212598 | J71: 0 | K71: 0 | L71: 0 | M71: 0 | N71: 31 | O71: 120 | P71: =+J71*E71 -> 0 | Q71: =+K71*E71 -> 0 | R71: =+L71*E71 -> 0 | S71: =+M71*E71 -> 0 | T71: =+N71*E71 -> 283.96 | U71: =+O71*E71 -> 1099.2 | V71: 0 | W71: 0 | X71: 0 | Y71: 0 | Z71: 0 | AA71: 30 | AB71: =+IFERROR(V71/H71,"") -> 0 | AC71: =+IFERROR(W71/H71,"") -> 0 | AD71: =+IFERROR(X71/H71,"") -> 0 | AE71: =+IFERROR(Y71/H71,"") -> 0 | AF71: =+IFERROR(Z71/H71,"") -> 0 | AG71: =+IFERROR(AA71/H71,"") -> 0.059055118 | AH71: 0 | AI71: 0 | AJ71: 0 | AK71: 0 | AL71: 0 | AM71: 281 | AN71: Above 11% | AO71: 0 | AP71: 0 | AQ71: 0 | AR71: 0 | AS71: 382.23 | AT71: 1402.8 | AU71: 0 | AV71: 0 | AW71: 0 | AX71: 0 | AY71: 0 | AZ71: 0
A72: 5266 | B72: Bonviva 150mg Tablets 1 | D72: Old Line | E72: 9.11 | F72: 500 | G72: =F72/2 -> 250 | H72: 6203 | I72: =+G72/H72 -> 0.040303079 | J72: 1700 | K72: 0 | L72: 0 | M72: 0 | O72: 0 | P72: =+J72*E72 -> 15487 | Q72: =+K72*E72 -> 0 | R72: =+L72*E72 -> 0 | S72: =+M72*E72 -> 0 | T72: =+N72*E72 -> 0 | U72: =+O72*E72 -> 0 | V72: 0 | W72: 99 | X72: 158 | Y72: 311 | Z72: 591 | AA72: 455 | AB72: =+IFERROR(V72/H72,"") -> 0 | AC72: =+IFERROR(W72/H72,"") -> 0.015960019 | AD72: =+IFERROR(X72/H72,"") -> 0.025471546 | AE72: =+IFERROR(Y72/H72,"") -> 0.05013703 | AF72: =+IFERROR(Z72/H72,"") -> 0.095276479 | AG72: =+IFERROR(AA72/H72,"") -> 0.073351604 | AH72: 0 | AI72: 914.23 | AJ72: 914.23 | AK72: 1304.72 | AL72: 1934.1 | AM72: 2656.88 | AN72: Above 11% | AO72: 0 | AP72: 0 | AQ72: 0 | AR72: 0 | AS72: 0 | AT72: 0 | AU72: 0 | AV72: 0 | AW72: 0 | AX72: 0 | AY72: 0 | AZ72: 0
A73: 5900C | B73: Creon Micro Pancreatin 60.12mg Gastroresistant Granules 1 | D73: Old Line | E73: 8.95 | F73: 300 | G73: =F73/2 -> 150 | H73: 452 | I73: =+G73/H73 -> 0.33185841 | J73: 84 | K73: 0 | L73: 40 | M73: 0 | N73: 50 | O73: 340 | P73: =+J73*E73 -> 751.8 | Q73: =+K73*E73 -> 0 | R73: =+L73*E73 -> 358 | S73: =+M73*E73 -> 0 | T73: =+N73*E73 -> 447.5 | U73: =+O73*E73 -> 3043 | V73: 212 | W73: 52 | X73: 101 | Y73: 190 | Z73: 0 | AA73: 49 | AB73: =+IFERROR(V73/H73,"") -> 0.46902655 | AC73: =+IFERROR(W73/H73,"") -> 0.11504425 | AD73: =+IFERROR(X73/H73,"") -> 0.22345133 | AE73: =+IFERROR(Y73/H73,"") -> 0.42035398 | AF73: =+IFERROR(Z73/H73,"") -> 0 | AG73: =+IFERROR(AA73/H73,"") -> 0.10840708 | AH73: 1103.56 | AI73: 322.41 | AJ73: 322.41 | AK73: 437 | AL73: 789.84 | AM73: 358.7 | AN73: Above 11% | AO73: 1789.96 | AP73: 0 | AQ73: 890.8 | AR73: 0 | AS73: 1145.5 | AT73: 13973.68 | AU73: 5625.66 | AV73: 1418.05 | AW73: 2985.5 | AX73: 5663 | AY73: 0 | AZ73: 1461.2
A74: 5233C | B74: Latuda 18.5mg Tablets 28 | D74: Old Line | E74: 8.76 | F74: 41.6 | G74: =F74/2 -> 20.8 | H74: 1097 | I74: =+G74/H74 -> 0.018960802 | J74: 0 | K74: 0 | L74: 0 | M74: 0 | O74: 0 | P74: =+J74*E74 -> 0 | Q74: =+K74*E74 -> 0 | R74: =+L74*E74 -> 0 | S74: =+M74*E74 -> 0 | T74: =+N74*E74 -> 0 | U74: =+O74*E74 -> 0 | V74: 30 | W74: 28 | X74: 33 | Y74: 11 | Z74: 2 | AA74: 11 | AB74: =+IFERROR(V74/H74,"") -> 0.027347311 | AC74: =+IFERROR(W74/H74,"") -> 0.025524157 | AD74: =+IFERROR(X74/H74,"") -> 0.030082042 | AE74: =+IFERROR(Y74/H74,"") -> 0.010027347 | AF74: =+IFERROR(Z74/H74,"") -> 0.0018231541 | AG74: =+IFERROR(AA74/H74,"") -> 0.010027347 | AH74: 193.14 | AI74: 136.06 | AJ74: 136.06 | AK74: 78.35 | AL74: 13.58 | AM74: -15.87 | AN74: Below 11% | AO74: 0 | AP74: 0 | AQ74: 0 | AR74: 0 | AS74: 0 | AT74: 0 | AU74: 1298.48 | AV74: 1111.2 | AW74: 1211.57 | AX74: 391.32 | AY74: 68.42 | AZ74: 361.87
A75: 5935B | B75: Topamax 100mg Tablets 60 | D75: Old Line | E75: 8.65 | F75: 800 | G75: =F75/2 -> 400 | H75: 813 | I75: =+G75/H75 -> 0.49200492 | J75: 148 | K75: 408 | L75: 339 | M75: 920 | O75: 0 | P75: =+J75*E75 -> 1280.2 | Q75: =+K75*E75 -> 3529.2 | R75: =+L75*E75 -> 2932.35 | S75: =+M75*E75 -> 7958 | T75: =+N75*E75 -> 0 | U75: =+O75*E75 -> 0 | V75: 654 | W75: 273 | X75: 126 | Y75: 159 | Z75: 445 | AA75: 265 | AB75: =+IFERROR(V75/H75,"") -> 0.80442804 | AC75: =+IFERROR(W75/H75,"") -> 0.33579336 | AD75: =+IFERROR(X75/H75,"") -> 0.15498155 | AE75: =+IFERROR(Y75/H75,"") -> 0.19557196 | AF75: =+IFERROR(Z75/H75,"") -> 0.54735547 | AG75: =+IFERROR(AA75/H75,"") -> 0.32595326 | AH75: 1521.31 | AI75: 1911.29 | AJ75: 1911.29 | AK75: 1275.72 | AL75: 1294.4 | AM75: 1646.09 | AN75: Above 11% | AO75: 4042.88 | AP75: 11206.95 | AQ75: 9255.54 | AR75: 25245.21 | AS75: 0 | AT75: 0 | AU75: 19251.25 | AV75: 9312.32 | AW75: 4723.91 | AX75: 5641.5 | AY75: 15569.9 | AZ75: 8880.59
A76: 1479E | B76: Medikinet XL 10mg Capsules 30 | D76: Old Line | E76: 8.61 | F76: 2000 | G76: =F76/2 -> 1000 | H76: 10120 | I76: =+G76/H76 -> 0.098814229 | J76: 400 | K76: 0 | L76: 275 | M76: 0 | N76: 980 | O76: 0 | P76: =+J76*E76 -> 3444 | Q76: =+K76*E76 -> 0 | R76: =+L76*E76 -> 2367.75 | S76: =+M76*E76 -> 0 | T76: =+N76*E76 -> 8437.8 | U76: =+O76*E76 -> 0 | V76: 0 | W76: 149 | X76: 580 | Y76: 219 | Z76: 272 | AA76: 977 | AB76: =+IFERROR(V76/H76,"") -> 0 | AC76: =+IFERROR(W76/H76,"") -> 0.01472332 | AD76: =+IFERROR(X76/H76,"") -> 0.057312253 | AE76: =+IFERROR(Y76/H76,"") -> 0.021640316 | AF76: =+IFERROR(Z76/H76,"") -> 0.02687747 | AG76: =+IFERROR(AA76/H76,"") -> 0.096541502 | AH76: 0 | AI76: 131.66 | AJ76: 131.66 | AK76: 2972.19 | AL76: 689.53 | AM76: 7861.08 | AN76: Above 11% | AO76: 6372 | AP76: 0 | AQ76: 3894 | AR76: 0 | AS76: 14680.4 | AT76: 0 | AU76: 0 | AV76: 3558.66 | AW76: 13776.35 | AX76: 5203.12 | AY76: 6402.7 | AZ76: 22555.16
A77: 5193D | B77: CoDiovan 160mg/25mg Tablets 28 | D77: Old Line | E77: 8.37 | F77: 220 | G77: =F77/2 -> 110 | H77: 454 | I77: =+G77/H77 -> 0.24229075 | J77: 556 | K77: 100 | L77: 200 | M77: 276 | N77: 254 | O77: 100 | P77: =+J77*E77 -> 4653.72 | Q77: =+K77*E77 -> 837 | R77: =+L77*E77 -> 1674 | S77: =+M77*E77 -> 2310.12 | T77: =+N77*E77 -> 2125.98 | U77: =+O77*E77 -> 837 | V77: 0 | W77: 0 | X77: 206 | Y77: 275 | Z77: 229 | AA77: 146 | AB77: =+IFERROR(V77/H77,"") -> 0 | AC77: =+IFERROR(W77/H77,"") -> 0 | AD77: =+IFERROR(X77/H77,"") -> 0.45374449 | AE77: =+IFERROR(Y77/H77,"") -> 0.60572687 | AF77: =+IFERROR(Z77/H77,"") -> 0.50440529 | AG77: =+IFERROR(AA77/H77,"") -> 0.3215859 | AH77: 0 | AI77: 0 | AJ77: 1724.22 | AK77: 1534.49 | AL77: 1813.23 | AM77: 1165.84 | AN77: Above 11% | AO77: 2807.28 | AP77: 491 | AQ77: 1032.5 | AR77: 1536.44 | AS77: 1300.06 | AT77: 516.5 | AU77: 0 | AV77: 0 | AW77: 2576.85 | AX77: 3131.45 | AY77: 2690.38 | AZ77: 1911.52
A78: 0211E | B78: Cabergoline 1mg Tablets 20 | D78: Old Line | E78: 7.76 | F78: 300 | G78: =F78/2 -> 150 | H78: 263 | I78: =+G78/H78 -> 0.57034221 | J78: 50 | K78: 50 | L78: 100 | M78: 49 | O78: 50 | P78: =+J78*E78 -> 388 | Q78: =+K78*E78 -> 388 | R78: =+L78*E78 -> 776 | S78: =+M78*E78 -> 380.24 | T78: =+N78*E78 -> 0 | U78: =+O78*E78 -> 388 | V78: 36 | W78: 117 | X78: 98 | Y78: 72 | Z78: 65 | AA78: 35 | AB78: =+IFERROR(V78/H78,"") -> 0.13688213 | AC78: =+IFERROR(W78/H78,"") -> 0.44486692 | AD78: =+IFERROR(X78/H78,"") -> 0.37262357 | AE78: =+IFERROR(Y78/H78,"") -> 0.27376426 | AF78: =+IFERROR(Z78/H78,"") -> 0.24714829 | AG78: =+IFERROR(AA78/H78,"") -> 0.13307985 | AH78: 99.11 | AI78: 177.34 | AJ78: 177.34 | AK78: 155.05 | AL78: 100.91 | AM78: 283.78 | AN78: Above 11% | AO78: 417.5 | AP78: 417.5 | AQ78: 827 | AR78: 408.17 | AS78: 0 | AT78: 413.5 | AU78: 527.87 | AV78: 1570.81 | AW78: 1206.43 | AX78: 801.61 | AY78: 1132.62 | AZ78: 595.05
A79: 5224 | B79: Femara 2.5mg Tablets 30 | D79: Old Line | E79: 7.69 | F79: 800 | G79: =F79/2 -> 400 | H79: 489 | I79: =+G79/H79 -> 0.81799591 | J79: 473 | K79: 0 | L79: 0 | M79: 354 | N79: 483 | O79: 516 | P79: =+J79*E79 -> 3637.37 | Q79: =+K79*E79 -> 0 | R79: =+L79*E79 -> 0 | S79: =+M79*E79 -> 2722.26 | T79: =+N79*E79 -> 3714.27 | U79: =+O79*E79 -> 3968.04 | V79: 180 | W79: 381 | X79: 310 | Y79: 0 | Z79: 119 | AA79: 152 | AB79: =+IFERROR(V79/H79,"") -> 0.36809816 | AC79: =+IFERROR(W79/H79,"") -> 0.7791411 | AD79: =+IFERROR(X79/H79,"") -> 0.63394683 | AE79: =+IFERROR(Y79/H79,"") -> 0 | AF79: =+IFERROR(Z79/H79,"") -> 0.24335378 | AG79: =+IFERROR(AA79/H79,"") -> 0.31083845 | AH79: 1521.28 | AI79: 2993.43 | AJ79: 2993.43 | AK79: 3209.79 | AL79: 915.11 | AM79: 1055.16 | AN79: Above 11% | AO79: 13646.96 | AP79: 0 | AQ79: 0 | AR79: 10991.33 | AS79: 14300.34 | AT79: 15174.64 | AU79: 0 | AV79: 0 | AW79: 0 | AX79: 0 | AY79: 0 | AZ79: 0
A80: 0388 | B80: Levocarnitine 30% Paediatric Oral Solution - 40ml | D80: Old Line | E80: 7.65 | F80: 149.2 | G80: =F80/2 -> 74.6 | H80: 57 | I80: =+G80/H80 -> 1.3087719 | J80: 512 | K80: 290 | L80: 0 | M80: 0 | O80: 0 | P80: =+J80*E80 -> 3916.8 | Q80: =+K80*E80 -> 2218.5 | R80: =+L80*E80 -> 0 | S80: =+M80*E80 -> 0 | T80: =+N80*E80 -> 0 | U80: =+O80*E80 -> 0 | V80: 10 | W80: 35 | X80: 60 | Y80: 124 | Z80: 144 | AA80: 181 | AB80: =+IFERROR(V80/H80,"") -> 0.1754386 | AC80: =+IFERROR(W80/H80,"") -> 0.61403509 | AD80: =+IFERROR(X80/H80,"") -> 1.0526316 | AE80: =+IFERROR(Y80/H80,"") -> 2.1754386 | AF80: =+IFERROR(Z80/H80,"") -> 2.5263158 | AG80: =+IFERROR(AA80/H80,"") -> 3.1754386 | AH80: 1214.2 | AI80: 3888.4 | AJ80: 3888.4 | AK80: 942 | AL80: 3681.67 | AM80: 5184.68 | AN80: Above 11% | AO80: 3233.49 | AP80: 1871.7 | AQ80: 0 | AR80: 0 | AS80: 0 | AT80: 0 | AU80: 0 | AV80: 0 | AW80: 0 | AX80: 0 | AY80: 0 | AZ80: 0
A81: 4907M | B81: AirFluSal Fluticasone 50/500mcg Inhaler 60doses | D81: Old Line | E81: 7.59 | F81: 1000 | G81: =F81/2 -> 500 | H81: 1209 | I81: =+G81/H81 -> 0.41356493 | J81: 0 | K81: 0 | L81: 0 | M81: 300 | N81: 670 | O81: 700 | P81: =+J81*E81 -> 0 | Q81: =+K81*E81 -> 0 | R81: =+L81*E81 -> 0 | S81: =+M81*E81 -> 2277 | T81: =+N81*E81 -> 5085.3 | U81: =+O81*E81 -> 5313 | V81: 204 | W81: 280 | X81: 0 | Y81: 0 | Z81: 205 | AA81: 439 | AB81: =+IFERROR(V81/H81,"") -> 0.16873449 | AC81: =+IFERROR(W81/H81,"") -> 0.23159636 | AD81: =+IFERROR(X81/H81,"") -> 0 | AE81: =+IFERROR(Y81/H81,"") -> 0 | AF81: =+IFERROR(Z81/H81,"") -> 0.16956162 | AG81: =+IFERROR(AA81/H81,"") -> 0.36311001 | AH81: 0 | AI81: 3989.04 | AJ81: 3989.04 | AK81: 0 | AL81: 1555.95 | AM81: 2998.79 | AN81: Above 11% | AO81: 0 | AP81: 0 | AQ81: 0 | AR81: 5833 | AS81: 12984.6 | AT81: 13483 | AU81: 1654.06 | AV81: 6263.03 | AW81: 0 | AX81: 0 | AY81: 5406.72 | AZ81: 11520.61
A82: 5869B | B82: CozaarComp 100mg/25mg Tablets 28 | D82: Old Line | E82: 7.53 | F82: 80 | G82: =F82/2 -> 40 | H82: 37 | I82: =+G82/H82 -> 1.0810811 | J82: 100 | K82: 250 | L82: 0 | M82: 0 | O82: 0 | P82: =+J82*E82 -> 753 | Q82: =+K82*E82 -> 1882.5 | R82: =+L82*E82 -> 0 | S82: =+M82*E82 -> 0 | T82: =+N82*E82 -> 0 | U82: =+O82*E82 -> 0 | V82: 7 | W82: 22 | X82: 20 | Y82: 12 | Z82: 67 | AA82: 31 | AB82: =+IFERROR(V82/H82,"") -> 0.18918919 | AC82: =+IFERROR(W82/H82,"") -> 0.59459459 | AD82: =+IFERROR(X82/H82,"") -> 0.54054054 | AE82: =+IFERROR(Y82/H82,"") -> 0.32432432 | AF82: =+IFERROR(Z82/H82,"") -> 1.8108108 | AG82: =+IFERROR(AA82/H82,"") -> 0.83783784 | AH82: 30.11 | AI82: 147.79 | AJ82: 147.79 | AK82: 177.3 | AL82: 98.49 | AM82: 124.72 | AN82: Above 11% | AO82: 551.5 | AP82: 1383 | AQ82: 0 | AR82: 0 | AS82: 0 | AT82: 0 | AU82: 67 | AV82: 265.81 | AW82: 287.04 | AX82: 164.49 | AY82: 597.38 | AZ82: 295.22
A83: 5935G | B83: Topamax Sprinkle 25mg Capsules 60 | D83: Old Line | E83: 7.53 | F83: 600 | G83: =F83/2 -> 300 | H83: 386 | I83: =+G83/H83 -> 0.77720207 | J83: 70 | K83: 320 | L83: 208 | M83: 245 | N83: 261 | O83: 257 | P83: =+J83*E83 -> 527.1 | Q83: =+K83*E83 -> 2409.6 | R83: =+L83*E83 -> 1566.24 | S83: =+M83*E83 -> 1844.85 | T83: =+N83*E83 -> 1965.33 | U83: =+O83*E83 -> 1935.21 | V83: 289 | W83: 97 | X83: 109 | Y83: 412 | Z83: 264 | AA83: 337 | AB83: =+IFERROR(V83/H83,"") -> 0.74870466 | AC83: =+IFERROR(W83/H83,"") -> 0.25129534 | AD83: =+IFERROR(X83/H83,"") -> 0.28238342 | AE83: =+IFERROR(Y83/H83,"") -> 1.0673575 | AF83: =+IFERROR(Z83/H83,"") -> 0.68393782 | AG83: =+IFERROR(AA83/H83,"") -> 0.87305699 | AH83: 1889.94 | AI83: 657.87 | AJ83: 657.87 | AK83: 555.31 | AL83: 1956 | AM83: 2635.12 | AN83: Above 11% | AO83: 650.3 | AP83: 2992.34 | AQ83: 2029.12 | AR83: 2345.47 | AS83: 2420.81 | AT83: 2398.25 | AU83: 4950.41 | AV83: 1565.5 | AW83: 1939.4 | AX83: 5859.98 | AY83: 4419.7 | AZ83: 5813.42
A84: 0311 | B84: Enalapril/Hydrochlorothiazide 20mg/12.5mg Tab 28 (PI) | D84: Old Line | E84: 7.37 | F84: 110 | G84: =F84/2 -> 55 | H84: 364 | I84: =+G84/H84 -> 0.1510989 | J84: 0 | K84: 0 | L84: 79 | M84: 0 | N84: 213 | O84: 0 | P84: =+J84*E84 -> 0 | Q84: =+K84*E84 -> 0 | R84: =+L84*E84 -> 582.23 | S84: =+M84*E84 -> 0 | T84: =+N84*E84 -> 1569.81 | U84: =+O84*E84 -> 0 | V84: 126 | W84: 109 | X84: 36 | Y84: 0 | Z84: 4 | AA84: 27 | AB84: =+IFERROR(V84/H84,"") -> 0.34615385 | AC84: =+IFERROR(W84/H84,"") -> 0.29945055 | AD84: =+IFERROR(X84/H84,"") -> 0.098901099 | AE84: =+IFERROR(Y84/H84,"") -> 0 | AF84: =+IFERROR(Z84/H84,"") -> 0.010989011 | AG84: =+IFERROR(AA84/H84,"") -> 0.074175824 | AH84: 127.48 | AI84: 130.31 | AJ84: 130.31 | AK84: 94.02 | AL84: 29.48 | AM84: 184.02 | AN84: Above 11% | AO84: 0 | AP84: 0 | AQ84: 97.96 | AR84: 0 | AS84: 261.99 | AT84: 0 | AU84: 0 | AV84: 0 | AW84: 0 | AX84: 0 | AY84: 0 | AZ84: 0
A85: 5139B | B85: Abilify 10mg Tablets 28 | D85: Old Line | E85: 7.36 | F85: 200 | G85: =F85/2 -> 100 | H85: 205 | I85: =+G85/H85 -> 0.48780488 | J85: 100 | K85: 400 | L85: 150 | M85: 50 | N85: 50 | O85: 100 | P85: =+J85*E85 -> 736 | Q85: =+K85*E85 -> 2944 | R85: =+L85*E85 -> 1104 | S85: =+M85*E85 -> 368 | T85: =+N85*E85 -> 368 | U85: =+O85*E85 -> 736 | V85: 7 | W85: 0 | X85: 71 | Y85: 382 | Z85: 97 | AA85: 100 | AB85: =+IFERROR(V85/H85,"") -> 0.034146341 | AC85: =+IFERROR(W85/H85,"") -> 0 | AD85: =+IFERROR(X85/H85,"") -> 0.34634146 | AE85: =+IFERROR(Y85/H85,"") -> 1.8634146 | AF85: =+IFERROR(Z85/H85,"") -> 0.47317073 | AG85: =+IFERROR(AA85/H85,"") -> 0.48780488 | AH85: 129.5 | AI85: 0 | AJ85: 522.56 | AK85: 999.69 | AL85: 3778.74 | AM85: 838.18 | AN85: Above 11% | AO85: 1810 | AP85: 7458 | AQ85: 2791.5 | AR85: 935.5 | AS85: 925 | AT85: 1826 | AU85: 280 | AV85: 0 | AW85: 2311.64 | AX85: 10861.02 | AY85: 2679.81 | AZ85: 2695.24
A86: 5284E | B86: Buccolam 10Mg/2ml oral syringe 4s | D86: New Line | E86: 7.27 | F86: 1000 | G86: =F86/2 -> 500 | H86: 2938 | I86: =+G86/H86 -> 0.1701838 | J86: 0 | K86: 0 | L86: 0 | M86: 92 | O86: 0 | P86: =+J86*E86 -> 0 | Q86: =+K86*E86 -> 0 | R86: =+L86*E86 -> 0 | S86: =+M86*E86 -> 668.84 | T86: =+N86*E86 -> 0 | U86: =+O86*E86 -> 0 | V86: 499 | W86: 300 | X86: 300 | Y86: 19 | Z86: 281 | AA86: 390 | AB86: =+IFERROR(V86/H86,"") -> 0.16984343 | AC86: =+IFERROR(W86/H86,"") -> 0.10211028 | AD86: =+IFERROR(X86/H86,"") -> 0.10211028 | AE86: =+IFERROR(Y86/H86,"") -> 0.0064669843 | AF86: =+IFERROR(Z86/H86,"") -> 0.095643295 | AG86: =+IFERROR(AA86/H86,"") -> 0.13274336 | AH86: 2355.67 | AI86: 2577.87 | AJ86: 2577.87 | AK86: 1924.23 | AL86: 109.9 | AM86: 2560.34 | AN86: Below 11% | AO86: 0 | AP86: 0 | AQ86: 0 | AR86: 7327.8 | AS86: 0 | AT86: 0 | AU86: 44391.43 | AV86: 27177.87 | AW86: 26524.23 | AX86: 1730 | AY86: 25505.88 | AZ86: 35218.28
A87: 5626B | B87: Fycompa 6mg Tablets 28 | D87: Old Line | E87: 7.1 | F87: 500 | G87: =F87/2 -> 250 | H87: 1160 | I87: =+G87/H87 -> 0.21551724 | J87: 0 | K87: 0 | L87: 154 | M87: 322 | N87: 422 | O87: 62 | P87: =+J87*E87 -> 0 | Q87: =+K87*E87 -> 0 | R87: =+L87*E87 -> 1093.4 | S87: =+M87*E87 -> 2286.2 | T87: =+N87*E87 -> 2996.2 | U87: =+O87*E87 -> 440.2 | V87: 241 | W87: 238 | X87: 283 | Y87: 146 | Z87: 254 | AA87: 251 | AB87: =+IFERROR(V87/H87,"") -> 0.20775862 | AC87: =+IFERROR(W87/H87,"") -> 0.20517241 | AD87: =+IFERROR(X87/H87,"") -> 0.24396552 | AE87: =+IFERROR(Y87/H87,"") -> 0.12586207 | AF87: =+IFERROR(Z87/H87,"") -> 0.21896552 | AG87: =+IFERROR(AA87/H87,"") -> 0.21637931 | AH87: 0 | AI87: 16.24 | AJ87: 16.24 | AK87: 324.81 | AL87: 480.82 | AM87: 883.61 | AN87: Below 11% | AO87: 0 | AP87: 0 | AQ87: 10724.56 | AR87: 22158.35 | AS87: 28516.51 | AT87: 4279.86 | AU87: 17374.36 | AV87: 17464.02 | AW87: 20564 | AX87: 10686.04 | AY87: 18549.67 | AZ87: 17878.06
A88: 5251N | B88: Vimpat 50mg Film-coated Tablets 56 | D88: Old Line | E88: 7.07 | F88: 80 | G88: =F88/2 -> 40 | H88: 251 | I88: =+G88/H88 -> 0.15936255 | J88: 100 | K88: 532 | L88: 23 | M88: 0 | O88: 36 | P88: =+J88*E88 -> 707 | Q88: =+K88*E88 -> 3761.24 | R88: =+L88*E88 -> 162.61 | S88: =+M88*E88 -> 0 | T88: =+N88*E88 -> 0 | U88: =+O88*E88 -> 254.52 | V88: 0 | W88: 0 | X88: 0 | Y88: 0 | Z88: 0 | AA88: 0 | AB88: =+IFERROR(V88/H88,"") -> 0 | AC88: =+IFERROR(W88/H88,"") -> 0 | AD88: =+IFERROR(X88/H88,"") -> 0 | AE88: =+IFERROR(Y88/H88,"") -> 0 | AF88: =+IFERROR(Z88/H88,"") -> 0 | AG88: =+IFERROR(AA88/H88,"") -> 0 | AH88: 0 | AI88: 0 | AJ88: 0 | AK88: 0 | AL88: 0 | AM88: 0 | AN88: Above 11% | AO88: 1681 | AP88: 8997.74 | AQ88: 385.02 | AR88: 0 | AS88: 0 | AT88: 600.12 | AU88: 0 | AV88: 0 | AW88: 0 | AX88: 0 | AY88: 0 | AZ88: 0
A89: 5337B | B89: Tresiba Penfill 100u/ml Injection 3mlx5 | C89: Top 5 | D89: Old Line | E89: 7.03 | F89: 15000 | G89: =F89/2 -> 7500 | H89: 49628 | I89: =+G89/H89 -> 0.15112437 | J89: 7482 | K89: 3776 | L89: 4934 | M89: 2438 | N89: 1939 | O89: 3739 | P89: =+J89*E89 -> 52598.46 | Q89: =+K89*E89 -> 26545.28 | R89: =+L89*E89 -> 34686.02 | S89: =+M89*E89 -> 17139.14 | T89: =+N89*E89 -> 13631.17 | U89: =+O89*E89 -> 26285.17 | V89: 5255 | W89: 8435 | X89: 2711 | Y89: 5857 | Z89: 3786 | AA89: 3507 | AB89: =+IFERROR(V89/H89,"") -> 0.10588781 | AC89: =+IFERROR(W89/H89,"") -> 0.16996454 | AD89: =+IFERROR(X89/H89,"") -> 0.054626421 | AE89: =+IFERROR(Y89/H89,"") -> 0.11801805 | AF89: =+IFERROR(Z89/H89,"") -> 0.07628758 | AG89: =+IFERROR(AA89/H89,"") -> 0.070665753 | AH89: 18069.55 | AI89: 27584.6 | AJ89: 27584.6 | AK89: 11509.3 | AL89: 19970.98 | AM89: 11669.31 | AN89: Above 11% | AO89: 323180.3 | AP89: 160320.24 | AQ89: 209768.61 | AR89: 101266.36 | AS89: 80707.84 | AT89: 350441.88 | AU89: 243491.7 | AV89: 390805.85 | AW89: 125503.16 | AX89: 270068.86 | AY89: 174612.46 | AZ89: 161639.92
A90: 5800I | B90: Pentasa Granules Sachets m/r 4g x 30's | D90: Old Line | E90: 6.93 | F90: 1500 | G90: =F90/2 -> 750 | H90: 986 | I90: =+G90/H90 -> 0.76064909 | J90: 450 | K90: 63 | L90: 345 | M90: 366 | N90: 241 | O90: 426 | P90: =+J90*E90 -> 3118.5 | Q90: =+K90*E90 -> 436.59 | R90: =+L90*E90 -> 2390.85 | S90: =+M90*E90 -> 2536.38 | T90: =+N90*E90 -> 1670.13 | U90: =+O90*E90 -> 2952.18 | V90: 147 | W90: 167 | X90: 339 | Y90: 440 | Z90: 94 | AA90: 499 | AB90: =+IFERROR(V90/H90,"") -> 0.14908722 | AC90: =+IFERROR(W90/H90,"") -> 0.1693712 | AD90: =+IFERROR(X90/H90,"") -> 0.34381339 | AE90: =+IFERROR(Y90/H90,"") -> 0.44624746 | AF90: =+IFERROR(Z90/H90,"") -> 0.095334686 | AG90: =+IFERROR(AA90/H90,"") -> 0.50608519 | AH90: 484.41 | AI90: 730.7 | AJ90: 730.7 | AK90: 2193.08 | AL90: 2024.11 | AM90: 2644.16 | AN90: Below 11% | AO90: 27895.46 | AP90: 3957.97 | AQ90: 21582.6 | AR90: 22921.79 | AS90: 15360.02 | AT90: 27073.86 | AU90: 9648.29 | AV90: 11151.5 | AW90: 23348.48 | AX90: 29515.86 | AY90: 6268.84 | AZ90: 34097.91
A91: L9047A | B91: Serevent 25mcg Evohaler 120doses | D91: Old Line | E91: 6.92 | F91: 2000 | G91: =F91/2 -> 1000 | H91: 2529 | I91: =+G91/H91 -> 0.39541321 | J91: 144 | K91: 1385 | L91: 2221 | M91: 400 | N91: 820 | O91: 1807 | P91: =+J91*E91 -> 996.48 | Q91: =+K91*E91 -> 9584.2 | R91: =+L91*E91 -> 15369.32 | S91: =+M91*E91 -> 2768 | T91: =+N91*E91 -> 5674.4 | U91: =+O91*E91 -> 12504.44 | V91: 1442 | W91: 727 | X91: 1761 | Y91: 1468 | Z91: 1586 | AA91: 1308 | AB91: =+IFERROR(V91/H91,"") -> 0.57018584 | AC91: =+IFERROR(W91/H91,"") -> 0.2874654 | AD91: =+IFERROR(X91/H91,"") -> 0.69632266 | AE91: =+IFERROR(Y91/H91,"") -> 0.58046659 | AF91: =+IFERROR(Z91/H91,"") -> 0.62712535 | AG91: =+IFERROR(AA91/H91,"") -> 0.51720047 | AH91: 4351.6 | AI91: 2665.61 | AJ91: 2665.61 | AK91: 5299.25 | AL91: 4966.46 | AM91: 5733.76 | AN91: Above 11% | AO91: 1491.84 | AP91: 14357.25 | AQ91: 22885.03 | AR91: 4126 | AS91: 7162.6 | AT91: 17955.03 | AU91: 20992.28 | AV91: 10489.39 | AW91: 23621.26 | AX91: 20118.04 | AY91: 22328.21 | AZ91: 18629.98
A92: 5250I | B92: TARGINACT 5MG/2.5MG PRO REL TAB 28 | D92: Old Line | E92: 6.84 | F92: 300 | G92: =F92/2 -> 150 | H92: 442 | I92: =+G92/H92 -> 0.33936652 | J92: 0 | K92: 0 | L92: 0 | M92: 0 | N92: 0 | O92: 572 | U92: =+O92*E92 -> 3912.48 | AB92: =+IFERROR(V92/H92,"") -> 0 | AC92: =+IFERROR(W92/H92,"") -> 0 | AD92: =+IFERROR(X92/H92,"") -> 0 | AE92: =+IFERROR(Y92/H92,"") -> 0 | AF92: =+IFERROR(Z92/H92,"") -> 0 | AG92: =+IFERROR(AA92/H92,"") -> 0 | AN92: Above 11% | AO92: 0 | AP92: 0 | AQ92: 0 | AR92: 0 | AS92: 0 | AT92: 4530.24 | AU92: 831.41 | AV92: 1127.46 | AW92: 1002.9 | AX92: 1339.66 | AY92: 1234.75 | AZ92: 902.85
A93: 5976A | B93: Heminevrin 192mg Capsules 30 | D93: Old Line | E93: 6.82 | F93: 20 | G93: =F93/2 -> 10 | H93: 0 | I93: =+G93/H93 -> #DIV/0! | J93: 0 | K93: 0 | L93: 0 | M93: 0 | N93: 200 | O93: 225 | P93: =+J93*E93 -> 0 | Q93: =+K93*E93 -> 0 | R93: =+L93*E93 -> 0 | S93: =+M93*E93 -> 0 | T93: =+N93*E93 -> 1364 | U93: =+O93*E93 -> 1534.5 | V93: 0 | W93: 0 | X93: 4 | Y93: 0 | Z93: 0 | AA93: 0 | AB93: =+IFERROR(V93/H93,"") | AC93: =+IFERROR(W93/H93,"") | AD93: =+IFERROR(X93/H93,"") | AE93: =+IFERROR(Y93/H93,"") | AF93: =+IFERROR(Z93/H93,"") | AG93: =+IFERROR(AA93/H93,"") | AH93: 0 | AI93: 0 | AJ93: 27.28 | AK93: 12.52 | AL93: 0 | AM93: 0 | AN93: Above 11% | AO93: 0 | AP93: 0 | AQ93: 0 | AR93: 0 | AS93: 951 | AT93: 1026.5 | AU93: 0 | AV93: 0 | AW93: 32 | AX93: 0 | AY93: 0 | AZ93: 0
A94: 5800H | B94: PENTASA SACHETS 2G 60 | D94: Old Line | E94: 6.79 | F94: 2000 | G94: =F94/2 -> 1000 | H94: 4920 | I94: =+G94/H94 -> 0.20325203 | J94: 310 | K94: 381 | L94: 72 | M94: 461 | N94: 500 | O94: 372 | P94: =+J94*E94 -> 2104.9 | Q94: =+K94*E94 -> 2586.99 | R94: =+L94*E94 -> 488.88 | S94: =+M94*E94 -> 3130.19 | T94: =+N94*E94 -> 3395 | U94: =+O94*E94 -> 2525.88 | V94: 34 | W94: 262 | X94: 468 | Y94: 88 | Z94: 408 | AA94: 606 | AB94: =+IFERROR(V94/H94,"") -> 0.0069105691 | AC94: =+IFERROR(W94/H94,"") -> 0.053252033 | AD94: =+IFERROR(X94/H94,"") -> 0.095121951 | AE94: =+IFERROR(Y94/H94,"") -> 0.017886179 | AF94: =+IFERROR(Z94/H94,"") -> 0.082926829 | AG94: =+IFERROR(AA94/H94,"") -> 0.12317073 | AH94: 144.91 | AI94: 1160.32 | AJ94: 1160.32 | AK94: 2018.7 | AL94: 401.48 | AM94: 3711.93 | AN94: Below 11% | AO94: 20050.68 | AP94: 24610.71 | AQ94: 4642.86 | AR94: 29720.36 | AS94: 32101.58 | AT94: 24109.77 | AU94: 2355.25 | AV94: 18148.88 | AW94: 32283.74 | AX94: 6032.54 | AY94: 28108.89 | AZ94: 42617.23
A95: 5315B | B95: Lyrica 150mg Capsules 56 | D95: Old Line | E95: 6.74 | F95: 200 | G95: =F95/2 -> 100 | H95: 787 | I95: =+G95/H95 -> 0.1270648 | J95: 267 | K95: 60 | L95: 0 | M95: 0 | O95: 0 | P95: =+J95*E95 -> 1799.58 | Q95: =+K95*E95 -> 404.4 | R95: =+L95*E95 -> 0 | S95: =+M95*E95 -> 0 | T95: =+N95*E95 -> 0 | U95: =+O95*E95 -> 0 | V95: 67 | W95: 103 | X95: 100 | Y95: 178 | Z95: 148 | AA95: 178 | AB95: =+IFERROR(V95/H95,"") -> 0.085133418 | AC95: =+IFERROR(W95/H95,"") -> 0.13087675 | AD95: =+IFERROR(X95/H95,"") -> 0.1270648 | AE95: =+IFERROR(Y95/H95,"") -> 0.22617535 | AF95: =+IFERROR(Z95/H95,"") -> 0.18805591 | AG95: =+IFERROR(AA95/H95,"") -> 0.22617535 | AH95: 236.7 | AI95: 293.75 | AJ95: 293.75 | AK95: 255.03 | AL95: 948.99 | AM95: 1092.9 | AN95: Above 11% | AO95: 3575.13 | AP95: 805.2 | AQ95: 0 | AR95: 0 | AS95: 0 | AT95: 0 | AU95: 1526.45 | AV95: 2276.5 | AW95: 2180.03 | AX95: 3701.32 | AY95: 3088.61 | AZ95: 3703.06
A96: 5197 | B96: Casodex 50mg Tablets 28 | D96: Old Line | E96: 6.69 | F96: 50 | G96: =F96/2 -> 25 | H96: 11 | I96: =+G96/H96 -> 2.2727273 | J96: 0 | K96: 80 | L96: 0 | M96: 0 | O96: 0 | P96: =+J96*E96 -> 0 | Q96: =+K96*E96 -> 535.2 | R96: =+L96*E96 -> 0 | S96: =+M96*E96 -> 0 | T96: =+N96*E96 -> 0 | U96: =+O96*E96 -> 0 | V96: 4 | W96: 8 | X96: 6 | Y96: 5 | Z96: 9 | AA96: 22 | AB96: =+IFERROR(V96/H96,"") -> 0.36363636 | AC96: =+IFERROR(W96/H96,"") -> 0.72727273 | AD96: =+IFERROR(X96/H96,"") -> 0.54545455 | AE96: =+IFERROR(Y96/H96,"") -> 0.45454545 | AF96: =+IFERROR(Z96/H96,"") -> 0.81818182 | AG96: =+IFERROR(AA96/H96,"") -> 2 | AH96: 32.72 | AI96: 70.03 | AJ96: 70.03 | AK96: 51.32 | AL96: 37.4 | AM96: 105.19 | AN96: Above 11% | AO96: 0 | AP96: 2488.7 | AQ96: 0 | AR96: 0 | AS96: 0 | AT96: 0 | AU96: 0 | AV96: 0 | AW96: 0 | AX96: 0 | AY96: 0 | AZ96: 0
A97: 5200 | B97: Cozaar 50mg Tablets 28 | D97: Old Line | E97: 6.64 | F97: 300 | G97: =F97/2 -> 150 | H97: 412 | I97: =+G97/H97 -> 0.36407767 | J97: 250 | K97: 0 | L97: 150 | M97: 599 | N97: 200 | O97: 150 | P97: =+J97*E97 -> 1660 | Q97: =+K97*E97 -> 0 | R97: =+L97*E97 -> 996 | S97: =+M97*E97 -> 3977.36 | T97: =+N97*E97 -> 1328 | U97: =+O97*E97 -> 996 | V97: 149 | W97: 245 | X97: 202 | Y97: 121 | Z97: 181 | AA97: 181 | AB97: =+IFERROR(V97/H97,"") -> 0.36165049 | AC97: =+IFERROR(W97/H97,"") -> 0.59466019 | AD97: =+IFERROR(X97/H97,"") -> 0.49029126 | AE97: =+IFERROR(Y97/H97,"") -> 0.29368932 | AF97: =+IFERROR(Z97/H97,"") -> 0.43932039 | AG97: =+IFERROR(AA97/H97,"") -> 0.43932039 | AH97: 561.88 | AI97: 959.39 | AJ97: 959.39 | AK97: 666.63 | AL97: 339.31 | AM97: 863.51 | AN97: Above 11% | AO97: 640 | AP97: 0 | AQ97: 400.5 | AR97: 1658.88 | AS97: 516 | AT97: 394.5 | AU97: 0 | AV97: 0 | AW97: 0 | AX97: 0 | AY97: 0 | AZ97: 0
A98: 5383J | B98: Lescol XL 80mg Tablets 28 | D98: Old Line | E98: 6.38 | F98: 800 | G98: =F98/2 -> 400 | H98: 372 | I98: =+G98/H98 -> 1.0752688 | J98: 50 | K98: 321 | L98: 340 | M98: 710 | N98: 626 | O98: 230 | P98: =+J98*E98 -> 319 | Q98: =+K98*E98 -> 2047.98 | R98: =+L98*E98 -> 2169.2 | S98: =+M98*E98 -> 4529.8 | T98: =+N98*E98 -> 3993.88 | U98: =+O98*E98 -> 1467.4 | V98: 288 | W98: 78 | X98: 41 | Y98: 161 | Z98: 236 | AA98: 219 | AB98: =+IFERROR(V98/H98,"") -> 0.77419355 | AC98: =+IFERROR(W98/H98,"") -> 0.20967742 | AD98: =+IFERROR(X98/H98,"") -> 0.11021505 | AE98: =+IFERROR(Y98/H98,"") -> 0.4327957 | AF98: =+IFERROR(Z98/H98,"") -> 0.6344086 | AG98: =+IFERROR(AA98/H98,"") -> 0.58870968 | AH98: 935.9 | AI98: 200.49 | AJ98: 200.49 | AK98: 98.57 | AL98: 2159.97 | AM98: 1481.19 | AN98: Above 11% | AO98: 265.5 | AP98: 1714.06 | AQ98: 1812.9 | AR98: 3689.1 | AS98: 3318.06 | AT98: 1209.7 | AU98: 2458.93 | AV98: 618.57 | AW98: 318.33 | AX98: 3016.49 | AY98: 3579.12 | AZ98: 2630.44
A99: 5297B | B99: TRAJENTA 5MG FC TABLET 90 | D99: Old Line | E99: 6.37 | F99: 2000 | G99: =F99/2 -> 1000 | H99: 203101 | I99: =+G99/H99 -> 0.0049236587 | J99: 205 | K99: 535 | L99: 660 | M99: 491 | N99: 270 | O99: 840 | P99: =+J99*E99 -> 1305.85 | Q99: =+K99*E99 -> 3407.95 | R99: =+L99*E99 -> 4204.2 | S99: =+M99*E99 -> 3127.67 | T99: =+N99*E99 -> 1719.9 | U99: =+O99*E99 -> 5350.8 | V99: 569 | W99: 807 | X99: 978 | Y99: 1027 | Z99: 1237 | AA99: 1116 | AB99: =+IFERROR(V99/H99,"") -> 0.0028015618 | AC99: =+IFERROR(W99/H99,"") -> 0.0039733925 | AD99: =+IFERROR(X99/H99,"") -> 0.0048153382 | AE99: =+IFERROR(Y99/H99,"") -> 0.0050565975 | AF99: =+IFERROR(Z99/H99,"") -> 0.0060905658 | AG99: =+IFERROR(AA99/H99,"") -> 0.0054948031 | AH99: 812.62 | AI99: 2209.92 | AJ99: 2209.92 | AK99: 2514.38 | AL99: 1601.53 | AM99: 4178.68 | AN99: Below 11% | AO99: 20317.55 | AP99: 52893.61 | AQ99: 64874.43 | AR99: 47530.9 | AS99: 25690.5 | AT99: 22939.65 | AU99: 56939.45 | AV99: 80714.09 | AW99: 97490.85 | AX99: 102297.29 | AY99: 122943.42 | AZ99: 110434.95
A100: L9325B | B100: Cipralex 20mg Tablets 28 | D100: Old Line | E100: 6.07 | F100: 500 | G100: =F100/2 -> 250 | H100: 259 | I100: =+G100/H100 -> 0.96525097 | J100: 349 | K100: 80 | L100: 0 | M100: 0 | O100: 0 | P100: =+J100*E100 -> 2118.43 | Q100: =+K100*E100 -> 485.6 | R100: =+L100*E100 -> 0 | S100: =+M100*E100 -> 0 | T100: =+N100*E100 -> 0 | U100: =+O100*E100 -> 0 | V100: 108 | W100: 164 | X100: 129 | Y100: 122 | Z100: 231 | AA100: 106 | AB100: =+IFERROR(V100/H100,"") -> 0.41698842 | AC100: =+IFERROR(W100/H100,"") -> 0.63320463 | AD100: =+IFERROR(X100/H100,"") -> 0.4980695 | AE100: =+IFERROR(Y100/H100,"") -> 0.47104247 | AF100: =+IFERROR(Z100/H100,"") -> 0.89189189 | AG100: =+IFERROR(AA100/H100,"") -> 0.40926641 | AH100: 451.21 | AI100: 1083.6 | AJ100: 1083.6 | AK100: 784.45 | AL100: 797.62 | AM100: 677.88 | AN100: Above 11% | AO100: 1959.53 | AP100: 428.8 | AQ100: 0 | AR100: 0 | AS100: 0 | AT100: 0 | AU100: 1417.79 | AV100: 2084.24 | AW100: 1553.29 | AX100: 1521.22 | AY100: 2688.88 | AZ100: 1301.16
...

Sheet Raw File
F1: =+SUBTOTAL(9,F3:F453) -> 6166364 | I1: =+SUBTOTAL(9,I3:I497) -> 418514.39 | J1: =+SUBTOTAL(9,J3:J497) -> 343636.91 | K1: =+SUBTOTAL(9,K3:K497) -> 297521.18 | L1: =+SUBTOTAL(9,L3:L497) -> 377950.98 | M1: =+SUBTOTAL(9,M3:M497) -> 336499.92 | N1: =+SUBTOTAL(9,N3:N497) -> 477381.71 | P1: =+SUBTOTAL(9,P3:P502) -> 1697869.5 | Q1: =+SUBTOTAL(9,Q3:Q502) -> 1059872.9 | R1: =+SUBTOTAL(9,R3:R502) -> 1136630.4 | S1: =+SUBTOTAL(9,S3:S502) -> 1295795.4 | T1: =+SUBTOTAL(9,T3:T502) -> 1149705.4 | U1: =+SUBTOTAL(9,U3:U502) -> 1921002.2 | W1: =+SUBTOTAL(9,W3:W453) -> 276485 | X1: =+SUBTOTAL(9,X3:X453) -> 326733 | Y1: =+SUBTOTAL(9,Y3:Y453) -> 343650 | Z1: =+SUBTOTAL(9,Z3:Z453) -> 331514 | AA1: =+SUBTOTAL(9,AA3:AA453) -> 349337 | AB1: =+SUBTOTAL(9,AB3:AB453) -> 378098 | AK1: =+SUBTOTAL(9,AK3:AK453) -> 667764.63 | AL1: =+SUBTOTAL(9,AL3:AL453) -> 819782.74 | AM1: =+SUBTOTAL(9,AM3:AM453) -> 853269 | AN1: =+SUBTOTAL(9,AN3:AN453) -> 917697.05 | AO1: =+SUBTOTAL(9,AO3:AO453) -> 1018766.6 | AP1: =+SUBTOTAL(9,AP3:AP453) -> 987455.09 | AR1: =+COUNTA(AR3:AR606) -> 497 | AT1: =+SUBTOTAL(9,AT3:AT497) -> 8072692.9 | AU1: =+SUBTOTAL(9,AU3:AU497) -> 6543124.6 | AV1: =+SUBTOTAL(9,AV3:AV497) -> 6961965.2 | AW1: =+SUBTOTAL(9,AW3:AW497) -> 7211962 | AX1: =+SUBTOTAL(9,AX3:AX497) -> 6622730.1 | AY1: =+SUBTOTAL(9,AY3:AY497) -> 8226497.7
A2: Lax Part No | B2: Lax Description | C2: Profit Per Pack | D2: Qty Target | E2: Monthly | F2: PCA | G2: Monthly Requirement Against PCA | I2: Feb'26 Received Qty | J2: March'26 Received Qty | K2: Apr'26 Received Qty | L2: May'26 Received Qty | M2: June'26 Received Qty | N2: July'26 Received Qty | P2: Feb'26 Potential Profit | Q2: March'26 Potential Profit | R2: Apr'26 Potential Profit | S2: May'26 Potential Profit | T2: June'26 Potential Profit | U2: July'26 Potential Profit | W2: Feb'26 Selling Qty | X2: March'26 Selling Qty | Y2: Apr'26 Selling Qty | Z2: May'26 Selling Qty | AA2: June'26 Selling Qty | AB2: July'26 Selling Qty | AD2: Feb'26 Selling Qty | AE2: March'26 Selling Qty | AF2: Apr'26 Selling Qty | AG2: May'26 Selling Qty | AH2: June'26 Selling Qty | AI2: July'26 Selling Qty | AK2: Feb'26 Profit | AL2: March'26 Profit | AM2: Apr'26 Profit | AN2: May'26 Profit | AO2: June'26 Profit | AP2: July'26 Profit | AR2: Category | AT2: Feb'26 Purchase Value | AU2: March'26 Purchase Value | AV2: Apr'26 Purchase Value | AW2: May'26 Purchase Value | AX2: June'26 Purchase Value | AY2: July'26 Purchase Value
A3: 1459 | B3: Trihexyphenidyl 2mg Tablets 100 | C3: 95.44 | D3: 3000 | E3: =D3/2 -> 1500 | F3: 6291 | G3: =+E3/F3 -> 0.23843586 | I3: 7002.5 | J3: 2504 | K3: 2842 | L3: 2186.75 | M3: 904.25 | N3: 3198 | P3: =+I3*C3 -> 668318.6 | Q3: =+J3*C3 -> 238981.76 | R3: =+K3*C3 -> 271240.48 | S3: =+L3*C3 -> 208703.42 | T3: =+M3*C3 -> 86301.62 | U3: =+N3*C3 -> 305217.12 | W3: =726+435 -> 1161 | X3: =991+504 -> 1495 | Y3: =778+776 -> 1554 | Z3: =867+693 -> 1560 | AA3: =890+884 -> 1774 | AB3: 805 | AD3: =+IFERROR(W3/F3,"") -> 0.18454936 | AE3: =+IFERROR(X3/F3,"") -> 0.23764107 | AF3: =+IFERROR(Y3/F3,"") -> 0.24701955 | AG3: =+IFERROR(Z3/F3,"") -> 0.2479733 | AH3: =+IFERROR(AA3/F3,"") -> 0.28199014 | AI3: =+IFERROR(AB3/F3,"") -> 0.12796058 | AK3: 104490 | AL3: 134550 | AM3: 139860 | AN3: 140400 | AO3: 159660 | AP3: 70979.12 | AR3: Above 11% | AT3: 25052.72 | AU3: 11618.56 | AV3: 13205.2 | AW3: 10137.65 | AX3: 4159.55 | AY3: 3668.1
A4: L1515 | B4: Ontozry 150mg Tabs 28 | C4: 90.75627 | D4: 1500 | E4: =D4/2 -> 750 | F4: 1212 | G4: =+E4/F4 -> 0.61881188 | I4: 0 | J4: 0 | K4: 0 | L4: 0 | M4: 0 | N4: 55 | U4: =+N4*C4 -> 4991.5949 | AD4: =+IFERROR(W4/F4,"") -> 0 | AE4: =+IFERROR(X4/F4,"") -> 0 | AF4: =+IFERROR(Y4/F4,"") -> 0 | AG4: =+IFERROR(Z4/F4,"") -> 0 | AH4: =+IFERROR(AA4/F4,"") -> 0 | AI4: =+IFERROR(AB4/F4,"") -> 0 | AR4: Above 11% | AT4: 0 | AU4: 0 | AV4: 0 | AW4: 0 | AX4: 0 | AY4: 4867.5
A5: 4092A | B5: Olsalazine 500mg Tablets 60 | C5: 89.98 | D5: 150 | E5: =D5/2 -> 75 | F5: 305 | G5: =+E5/F5 -> 0.24590164 | I5: 0 | J5: 0 | K5: 0 | L5: 50 | M5: 40 | N5: 0 | P5: =+I5*C5 -> 0 | Q5: =+J5*C5 -> 0 | R5: =+K5*C5 -> 0 | S5: =+L5*C5 -> 4499 | T5: =+M5*C5 -> 3599.2 | U5: =+N5*C5 -> 0 | W5: 2 | X5: 0 | Y5: 0 | Z5: 0 | AA5: 49 | AB5: 39 | AD5: =+IFERROR(W5/F5,"") -> 0.006557377 | AE5: =+IFERROR(X5/F5,"") -> 0 | AF5: =+IFERROR(Y5/F5,"") -> 0 | AG5: =+IFERROR(Z5/F5,"") -> 0 | AH5: =+IFERROR(AA5/F5,"") -> 0.16065574 | AI5: =+IFERROR(AB5/F5,"") -> 0.12786885 | AK5: 184.86 | AL5: 0 | AM5: 0 | AN5: 0 | AO5: 4409.02 | AP5: 3461.86 | AR5: Above 11% | AT5: 0 | AU5: 0 | AV5: 0 | AW5: 2809.5 | AX5: 2220.4 | AY5: 0
A6: 5678 | B6: Olsalazine 500mg Tablets 100 | C6: 83.25 | D6: 300 | E6: =D6/2 -> 150 | F6: 305 | G6: =+E6/F6 -> 0.49180328 | I6: 273 | J6: 0 | K6: 0 | L6: 0 | N6: 0 | P6: =+I6*C6 -> 22727.25 | Q6: =+J6*C6 -> 0 | R6: =+K6*C6 -> 0 | S6: =+L6*C6 -> 0 | T6: =+M6*C6 -> 0 | U6: =+N6*C6 -> 0 | W6: 19 | X6: 36 | Y6: 90 | Z6: 97 | AA6: 74 | AB6: 0 | AD6: =+IFERROR(W6/F6,"") -> 0.062295082 | AE6: =+IFERROR(X6/F6,"") -> 0.11803279 | AF6: =+IFERROR(Y6/F6,"") -> 0.29508197 | AG6: =+IFERROR(Z6/F6,"") -> 0.31803279 | AH6: =+IFERROR(AA6/F6,"") -> 0.24262295 | AI6: =+IFERROR(AB6/F6,"") -> 0 | AK6: 1711.2 | AL6: 4335.88 | AM6: 4335.88 | AN6: 8516.17 | AO6: 7774.44 | AP6: 0 | AR6: Above 11% | AT6: 15313 | AU6: 0 | AV6: 0 | AW6: 0 | AX6: 0 | AY6: 0
A7: 5678A | B7: Dipentum 250mg Capsules 100 | C7: 77.07 | D7: 200 | E7: =D7/2 -> 100 | F7: 305 | G7: =+E7/F7 -> 0.32786885 | I7: 353 | J7: 130 | K7: 0 | L7: 0 | N7: 0 | P7: =+I7*C7 -> 27205.71 | Q7: =+J7*C7 -> 10019.1 | R7: =+K7*C7 -> 0 | S7: =+L7*C7 -> 0 | T7: =+M7*C7 -> 0 | U7: =+N7*C7 -> 0 | W7: 0 | X7: 0 | Y7: 0 | Z7: 20 | AA7: 24 | AB7: 44 | AD7: =+IFERROR(W7/F7,"") -> 0 | AE7: =+IFERROR(X7/F7,"") -> 0 | AF7: =+IFERROR(Y7/F7,"") -> 0 | AG7: =+IFERROR(Z7/F7,"") -> 0.06557377 | AH7: =+IFERROR(AA7/F7,"") -> 0.078688525 | AI7: =+IFERROR(AB7/F7,"") -> 0.1442623 | AK7: 0 | AL7: 0 | AM7: 0 | AN7: 1541.4 | AO7: 1631.4 | AP7: 3449.16 | AR7: Above 11% | AT7: 12284.81 | AU7: 4529.2 | AV7: 0 | AW7: 0 | AX7: 0 | AY7: 0
A8: 5440 | B8: Norprolac 75mcg Tablets 30s | C8: 51.94 | D8: 400 | E8: =D8/2 -> 200 | F8: 269 | G8: =+E8/F8 -> 0.74349442 | I8: 98 | J8: 0 | K8: 0 | L8: 0 | N8: 30 | P8: =+I8*C8 -> 5090.12 | Q8: =+J8*C8 -> 0 | R8: =+K8*C8 -> 0 | S8: =+L8*C8 -> 0 | T8: =+M8*C8 -> 0 | U8: =+N8*C8 -> 1558.2 | W8: 0 | X8: 0 | Y8: 0 | Z8: 1 | AA8: 0 | AB8: 0 | AD8: =+IFERROR(W8/F8,"") -> 0 | AE8: =+IFERROR(X8/F8,"") -> 0 | AF8: =+IFERROR(Y8/F8,"") -> 0 | AG8: =+IFERROR(Z8/F8,"") -> 0.0037174721 | AH8: =+IFERROR(AA8/F8,"") -> 0 | AI8: =+IFERROR(AB8/F8,"") -> 0 | AK8: 0 | AL8: 0 | AM8: 0 | AN8: 51.94 | AO8: 51.94 | AP8: 0 | AR8: Above 11% | AT8: 2316.56 | AU8: 0 | AV8: 0 | AW8: 0 | AX8: 0 | AY8: 702.6
A9: 5209M | B9: Exelon 9.5mg/24hrs Transdermal Patches 30 | C9: 48.32 | D9: 3000 | E9: =D9/2 -> 1500 | F9: 485 | G9: =+E9/F9 -> 3.0927835 | I9: 565 | J9: 909 | K9: 971 | L9: 347 | M9: 1230 | N9: 796 | P9: =+I9*C9 -> 27300.8 | Q9: =+J9*C9 -> 43922.88 | R9: =+K9*C9 -> 46918.72 | S9: =+L9*C9 -> 16767.04 | T9: =+M9*C9 -> 59433.6 | U9: =+N9*C9 -> 38462.72 | W9: 215 | X9: 310 | Y9: 1371 | Z9: 754 | AA9: 273 | AB9: 380 | AD9: =+IFERROR(W9/F9,"") -> 0.44329897 | AE9: =+IFERROR(X9/F9,"") -> 0.63917526 | AF9: =+IFERROR(Y9/F9,"") -> 2.8268041 | AG9: =+IFERROR(Z9/F9,"") -> 1.5546392 | AH9: =+IFERROR(AA9/F9,"") -> 0.5628866 | AI9: =+IFERROR(AB9/F9,"") -> 0.78350515 | AK9: 4599.04 | AL9: 7170.14 | AM9: 7170.14 | AN9: 33326.04 | AO9: 31149.89 | AP9: 16033.81 | AR9: Above 11% | AT9: 11732.46 | AU9: 19114.74 | AV9: 20259.44 | AW9: 7301.22 | AX9: 25859.31 | AY9: 16720.83
A10: 0680D | B10: Oxycontin 80mg Tablets 56 | C10: 47.674998 | D10: 200 | E10: =D10/2 -> 100 | F10: 322 | G10: =+E10/F10 -> 0.31055901 | I10: 0 | J10: 0 | K10: 0 | L10: 0 | M10: 0 | N10: 403 | U10: =+N10*C10 -> 19213.024 | AD10: =+IFERROR(W10/F10,"") -> 0 | AE10: =+IFERROR(X10/F10,"") -> 0 | AF10: =+IFERROR(Y10/F10,"") -> 0 | AG10: =+IFERROR(Z10/F10,"") -> 0 | AH10: =+IFERROR(AA10/F10,"") -> 0 | AI10: =+IFERROR(AB10/F10,"") -> 0 | AR10: Above 11% | AT10: 0 | AU10: 0 | AV10: 0 | AW10: 0 | AX10: 0 | AY10: 0
A11: 1371 | B11: Domperidone 1mg/1ml Suspension 200ml | C11: 44.3 | D11: 8000 | E11: =D11/2 -> 4000 | F11: 1722 | G11: =+E11/F11 -> 2.3228804 | I11: 395 | J11: 0 | K11: 0 | L11: 3282 | M11: 4135 | N11: 7088 | P11: =+I11*C11 -> 17498.5 | Q11: =+J11*C11 -> 0 | R11: =+K11*C11 -> 0 | S11: =+L11*C11 -> 145392.6 | T11: =+M11*C11 -> 183180.5 | U11: =+N11*C11 -> 313998.4 | W11: 2680 | X11: 514 | Y11: 683 | Z11: 838 | AA11: 1707 | AB11: 1949 | AD11: =+IFERROR(W11/F11,"") -> 1.5563298 | AE11: =+IFERROR(X11/F11,"") -> 0.29849013 | AF11: =+IFERROR(Y11/F11,"") -> 0.39663182 | AG11: =+IFERROR(Z11/F11,"") -> 0.48664344 | AH11: =+IFERROR(AA11/F11,"") -> 0.9912892 | AI11: =+IFERROR(AB11/F11,"") -> 1.1318235 | AK11: 66107.27 | AL11: 21703.68 | AM11: 21703.68 | AN11: 41518.49 | AO11: 44172.43 | AP11: 89083.95 | AR11: Above 11% | AT11: 845.3 | AU11: 0 | AV11: 0 | AW11: 6857.52 | AX11: 23528.03 | AY11: 30851.04
A12: L7124 | B12: Fycompa oral suspension 0.5mg/ml 1's | C12: 42.77 | D12: 300 | E12: =D12/2 -> 150 | F12: 391 | G12: =+E12/F12 -> 0.38363171 | I12: 0 | J12: 0 | K12: 115 | L12: 304 | M12: 307 | N12: 285 | P12: =+I12*C12 -> 0 | Q12: =+J12*C12 -> 0 | R12: =+K12*C12 -> 4918.55 | S12: =+L12*C12 -> 13002.08 | T12: =+M12*C12 -> 13130.39 | U12: =+N12*C12 -> 12189.45 | W12: 0 | X12: 0 | Y12: 0 | Z12: 0 | AA12: 110 | AB12: 179 | AD12: =+IFERROR(W12/F12,"") -> 0 | AE12: =+IFERROR(X12/F12,"") -> 0 | AF12: =+IFERROR(Y12/F12,"") -> 0 | AG12: =+IFERROR(Z12/F12,"") -> 0 | AH12: =+IFERROR(AA12/F12,"") -> 0.28132992 | AI12: =+IFERROR(AB12/F12,"") -> 0.45780051 | AK12: 0 | AL12: 0 | AM12: 0 | AN12: 0 | AO12: 4704.7 | AP12: 7195.62 | AR12: Above 11% | AT12: 0 | AU12: 0 | AV12: 7155.3 | AW12: 19456.56 | AX12: 19519.2 | AY12: 18126.6
A13: 5548D | B13: Entocort CR 3mg Capsules 100 | C13: 41.11 | D13: 50 | E13: =D13/2 -> 25 | F13: 100 | G13: =+E13/F13 -> 0.25 | I13: 0 | J13: 0 | K13: 0 | L13: 74 | N13: 0 | P13: =+I13*C13 -> 0 | Q13: =+J13*C13 -> 0 | R13: =+K13*C13 -> 0 | S13: =+L13*C13 -> 3042.14 | T13: =+M13*C13 -> 0 | U13: =+N13*C13 -> 0 | W13: 0 | X13: 0 | Y13: 21 | Z13: 3 | AA13: 20 | AB13: 24 | AD13: =+IFERROR(W13/F13,"") -> 0 | AE13: =+IFERROR(X13/F13,"") -> 0 | AF13: =+IFERROR(Y13/F13,"") -> 0.21 | AG13: =+IFERROR(Z13/F13,"") -> 0.03 | AH13: =+IFERROR(AA13/F13,"") -> 0.2 | AI13: =+IFERROR(AB13/F13,"") -> 0.24 | AK13: 0 | AL13: 0 | AM13: 863.31 | AN13: 305.77 | AO13: 48.58 | AP13: 771.16 | AR13: Above 11% | AT13: 0 | AU13: 0 | AV13: 0 | AW13: 0 | AX13: 0 | AY13: 0
A14: L1502 | B14: Ontozry 100mg Tabs 28 | C14: 40.95 | D14: 1000 | E14: =D14/2 -> 500 | F14: 2146 | G14: =+E14/F14 -> 0.23299161 | I14: 0 | J14: 0 | K14: 0 | L14: 0 | M14: 146 | N14: 46 | P14: =+I14*C14 -> 0 | Q14: =+J14*C14 -> 0 | R14: =+K14*C14 -> 0 | S14: =+L14*C14 -> 0 | T14: =+M14*C14 -> 5978.7 | U14: =+N14*C14 -> 1883.7 | W14: 308 | X14: 435 | Y14: 221 | Z14: 105 | AA14: 15 | AB14: 145 | AD14: =+IFERROR(W14/F14,"") -> 0.14352283 | AE14: =+IFERROR(X14/F14,"") -> 0.2027027 | AF14: =+IFERROR(Y14/F14,"") -> 0.10298229 | AG14: =+IFERROR(Z14/F14,"") -> 0.048928239 | AH14: =+IFERROR(AA14/F14,"") -> 0.0069897484 | AI14: =+IFERROR(AB14/F14,"") -> 0.067567568 | AK14: 3718.66 | AL14: 6245.23 | AM14: 6245.23 | AN14: 4477.13 | AO14: 1741.52 | AP14: 5842.09 | AR14: Above 11% | AT14: 0 | AU14: 0 | AV14: 0 | AW14: 0 | AX14: 12346.2 | AY14: 3908.16
A15: 5686B | B15: EXELON transdermal patches 13.3mg/24h | C15: 40.29 | D15: 400 | E15: =D15/2 -> 200 | F15: 92 | G15: =+E15/F15 -> 2.173913 | I15: 1024 | J15: 1112 | K15: 0 | L15: 0 | M15: 645 | N15: 608 | P15: =+I15*C15 -> 41256.96 | Q15: =+J15*C15 -> 44802.48 | R15: =+K15*C15 -> 0 | S15: =+L15*C15 -> 0 | T15: =+M15*C15 -> 25987.05 | U15: =+N15*C15 -> 24496.32 | W15: 63 | X15: 60 | Y15: 65 | Z15: 122 | AA15: 66 | AB15: 75 | AD15: =+IFERROR(W15/F15,"") -> 0.68478261 | AE15: =+IFERROR(X15/F15,"") -> 0.65217391 | AF15: =+IFERROR(Y15/F15,"") -> 0.70652174 | AG15: =+IFERROR(Z15/F15,"") -> 1.326087 | AH15: =+IFERROR(AA15/F15,"") -> 0.7173913 | AI15: =+IFERROR(AB15/F15,"") -> 0.81521739 | AK15: 1464.07 | AL15: 1787.95 | AM15: 1787.95 | AN15: 1800.08 | AO15: 3857.26 | AP15: 2025.76 | AR15: Above 11% | AT15: 30064.63 | AU15: 33037.46 | AV15: 0 | AW15: 0 | AX15: 18190.47 | AY15: 17696.1
A16: L1503 | B16: Ontozry 200mg Tabs 28 | C16: 37.9 | D16: 2000 | E16: =D16/2 -> 1000 | F16: 3833 | G16: =+E16/F16 -> 0.26089225 | I16: 0 | J16: 0 | K16: 32 | L16: 0 | M16: 116 | N16: 0 | P16: =+I16*C16 -> 0 | Q16: =+J16*C16 -> 0 | R16: =+K16*C16 -> 1212.8 | S16: =+L16*C16 -> 0 | T16: =+M16*C16 -> 4396.4 | U16: =+N16*C16 -> 0 | W16: 599 | X16: 406 | Y16: 40 | Z16: 149 | AA16: 51 | AB16: 50 | AD16: =+IFERROR(W16/F16,"") -> 0.15627446 | AE16: =+IFERROR(X16/F16,"") -> 0.10592225 | AF16: =+IFERROR(Y16/F16,"") -> 0.01043569 | AG16: =+IFERROR(Z16/F16,"") -> 0.038872945 | AH16: =+IFERROR(AA16/F16,"") -> 0.013305505 | AI16: =+IFERROR(AB16/F16,"") -> 0.013044613 | AK16: 4975.86 | AL16: 4622.42 | AM16: 4622.42 | AN16: 403.06 | AO16: 3183.84 | AP16: 895 | AR16: Above 11% | AT16: 0 | AU16: 0 | AV16: 2480.96 | AW16: 0 | AX16: 10396.99 | AY16: 0
A17: 5733C | B17: Zonegran 50mg Capsules 56 | C17: 34.48 | D17: 400 | E17: =D17/2 -> 200 | F17: 678 | G17: =+E17/F17 -> 0.29498525 | I17: 31 | J17: 0 | K17: 0 | L17: 0 | N17: 0 | P17: =+I17*C17 -> 1068.88 | Q17: =+J17*C17 -> 0 | R17: =+K17*C17 -> 0 | S17: =+L17*C17 -> 0 | T17: =+M17*C17 -> 0 | U17: =+N17*C17 -> 0 | W17: 89 | X17: 133 | Y17: 105 | Z17: 69 | AA17: 16 | AB17: 15 | AD17: =+IFERROR(W17/F17,"") -> 0.13126844 | AE17: =+IFERROR(X17/F17,"") -> 0.19616519 | AF17: =+IFERROR(Y17/F17,"") -> 0.15486726 | AG17: =+IFERROR(Z17/F17,"") -> 0.10176991 | AH17: =+IFERROR(AA17/F17,"") -> 0.02359882 | AI17: =+IFERROR(AB17/F17,"") -> 0.022123894 | AK17: 2252 | AL17: 3424.56 | AM17: 3424.56 | AN17: 2449.51 | AO17: 1602.66 | AP17: 478 | AR17: Above 11% | AT17: 0 | AU17: 0 | AV17: 0 | AW17: 0 | AX17: 0 | AY17: 0
A18: 5092A | B18: Briviact 25mg Tablets 56 | C18: 34.02 | D18: 700 | E18: =D18/2 -> 350 | F18: 2856 | G18: =+E18/F18 -> 0.12254902 | I18: 118.18182 | J18: 164.39394 | K18: 704.75758 | L18: 987.87879 | M18: 435.24242 | N18: 504 | P18: =+I18*C18 -> 4020.5455 | Q18: =+J18*C18 -> 5592.6818 | R18: =+K18*C18 -> 23975.853 | S18: =+L18*C18 -> 33607.636 | T18: =+M18*C18 -> 14806.947 | U18: =+N18*C18 -> 17146.08 | W18: 290 | X18: 116 | Y18: 164 | Z18: 478 | AA18: 429 | AB18: 1024 | AD18: =+IFERROR(W18/F18,"") -> 0.10154062 | AE18: =+IFERROR(X18/F18,"") -> 0.040616246 | AF18: =+IFERROR(Y18/F18,"") -> 0.057422969 | AG18: =+IFERROR(Z18/F18,"") -> 0.16736695 | AH18: =+IFERROR(AA18/F18,"") -> 0.15021008 | AI18: =+IFERROR(AB18/F18,"") -> 0.35854342 | AK18: 4936.6 | AL18: 1652.7 | AM18: 1652.7 | AN18: 8153.84 | AO18: 17989.07 | AP18: 34686.77 | AR18: Above 11% | AT18: 8697.39 | AU18: 12105.81 | AV18: 51826.55 | AW18: 69767.1 | AX18: 31619.04 | AY18: 34528.33
A19: 5205 | B19: Stalevo Film Coated Tabs 125mg/31.25mg/200mg 100 | C19: 32.993197 | D19: 400 | E19: =D19/2 -> 200 | F19: 1004 | G19: =+E19/F19 -> 0.19920319 | I19: 0 | J19: 0 | K19: 0 | L19: 0 | M19: 0 | N19: 430 | U19: =+N19*C19 -> 14187.075 | AD19: =+IFERROR(W19/F19,"") -> 0 | AE19: =+IFERROR(X19/F19,"") -> 0 | AF19: =+IFERROR(Y19/F19,"") -> 0 | AG19: =+IFERROR(Z19/F19,"") -> 0 | AH19: =+IFERROR(AA19/F19,"") -> 0 | AI19: =+IFERROR(AB19/F19,"") -> 0 | AR19: Above 11% | AT19: 0 | AU19: 0 | AV19: 0 | AW19: 1637 | AX19: 1677.5 | AY19: 7612.3
A20: 5092D | B20: Briviact Oral Solution 10mg/ml 300ml | C20: 32.95 | D20: 500 | E20: =D20/2 -> 250 | F20: 1500 | G20: =+E20/F20 -> 0.16666667 | I20: 0 | J20: 0 | K20: 98 | L20: 86 | M20: 557 | N20: 616 | P20: =+I20*C20 -> 0 | Q20: =+J20*C20 -> 0 | R20: =+K20*C20 -> 3229.1 | S20: =+L20*C20 -> 2833.7 | T20: =+M20*C20 -> 18353.15 | U20: =+N20*C20 -> 20297.2 | W20: 0 | X20: 0 | Y20: 0 | Z20: 75 | AA20: 103 | AB20: 506 | AD20: =+IFERROR(W20/F20,"") -> 0 | AE20: =+IFERROR(X20/F20,"") -> 0 | AF20: =+IFERROR(Y20/F20,"") -> 0 | AG20: =+IFERROR(Z20/F20,"") -> 0.05 | AH20: =+IFERROR(AA20/F20,"") -> 0.068666667 | AI20: =+IFERROR(AB20/F20,"") -> 0.33733333 | AK20: 0 | AL20: 0 | AM20: 0 | AN20: 2471.25 | AO20: 2588.49 | AP20: 15132.7 | AR20: Above 11% | AT20: 0 | AU20: 0 | AV20: 7586.96 | AW20: 6963.42 | AX20: 44039.81 | AY20: 48183.76
A21: L9106A | B21: Efient 5mg Tablets 28 | C21: 28.834748 | D21: 300 | E21: =D21/2 -> 150 | F21: 1769 | G21: =+E21/F21 -> 0.084793669 | I21: 0 | J21: 0 | K21: 0 | L21: 0 | M21: 0 | N21: 50 | U21: =+N21*C21 -> 1441.7374 | AD21: =+IFERROR(W21/F21,"") -> 0 | AE21: =+IFERROR(X21/F21,"") -> 0 | AF21: =+IFERROR(Y21/F21,"") -> 0 | AG21: =+IFERROR(Z21/F21,"") -> 0 | AH21: =+IFERROR(AA21/F21,"") -> 0 | AI21: =+IFERROR(AB21/F21,"") -> 0 | AR21: Above 11% | AT21: 0 | AU21: 0 | AV21: 0 | AW21: 0 | AX21: 0 | AY21: 660
A22: 5250N | B22: Vimpat 200mg Film-coated Tablets 56 | C22: 25.83 | D22: 200 | E22: =D22/2 -> 100 | F22: 279 | G22: =+E22/F22 -> 0.35842294 | I22: 0 | J22: 0 | K22: 0 | L22: 0 | N22: 0 | P22: =+I22*C22 -> 0 | Q22: =+J22*C22 -> 0 | R22: =+K22*C22 -> 0 | S22: =+L22*C22 -> 0 | T22: =+M22*C22 -> 0 | U22: =+N22*C22 -> 0 | W22: 62 | X22: 140 | Y22: 59 | Z22: 38 | AA22: 64 | AB22: 34 | AD22: =+IFERROR(W22/F22,"") -> 0.22222222 | AE22: =+IFERROR(X22/F22,"") -> 0.50179211 | AF22: =+IFERROR(Y22/F22,"") -> 0.21146953 | AG22: =+IFERROR(Z22/F22,"") -> 0.13620072 | AH22: =+IFERROR(AA22/F22,"") -> 0.22939068 | AI22: =+IFERROR(AB22/F22,"") -> 0.1218638 | AK22: 2478.86 | AL22: 3503.15 | AM22: 3503.15 | AN22: 1968.21 | AO22: 1284.83 | AP22: 902.54 | AR22: Above 11% | AT22: 0 | AU22: 0 | AV22: 0 | AW22: 0 | AX22: 0 | AY22: 0
A23: 5123E | B23: Aricept Evess Dispersible Tablets 5Mg X 28'S | C23: 25.58 | D23: 240 | E23: =D23/2 -> 120 | F23: 1315 | G23: =+E23/F23 -> 0.091254753 | I23: 149 | J23: 0 | K23: 224 | L23: 161 | N23: 0 | P23: =+I23*C23 -> 3811.42 | Q23: =+J23*C23 -> 0 | R23: =+K23*C23 -> 5729.92 | S23: =+L23*C23 -> 4118.38 | T23: =+M23*C23 -> 0 | U23: =+N23*C23 -> 0 | W23: 0 | X23: 4 | Y23: 6 | Z23: 0 | AA23: 0 | AB23: 0 | AD23: =+IFERROR(W23/F23,"") -> 0 | AE23: =+IFERROR(X23/F23,"") -> 0.0030418251 | AF23: =+IFERROR(Y23/F23,"") -> 0.0045627376 | AG23: =+IFERROR(Z23/F23,"") -> 0 | AH23: =+IFERROR(AA23/F23,"") -> 0 | AI23: =+IFERROR(AB23/F23,"") -> 0 | AK23: 0 | AL23: 116.9 | AM23: 116.9 | AN23: 210 | AO23: 0 | AP23: 0 | AR23: Above 11% | AT23: 2506.03 | AU23: 0 | AV23: 3751.36 | AW23: 2688.9 | AX23: 0 | AY23: 0
A24: 5175C | B24: Creon 25000 Gastroresistant Capsules 50 | C24: 25.51 | D24: 2000 | E24: =D24/2 -> 1000 | F24: 45807 | G24: =+E24/F24 -> 0.021830725 | I24: 0 | J24: 0 | K24: 999 | L24: 1040 | M24: 820 | N24: 1620 | P24: =+I24*C24 -> 0 | Q24: =+J24*C24 -> 0 | R24: =+K24*C24 -> 25484.49 | S24: =+L24*C24 -> 26530.4 | T24: =+M24*C24 -> 20918.2 | U24: =+N24*C24 -> 41326.2 | W24: 9 | X24: 0 | Y24: 0 | Z24: 683 | AA24: 830 | AB24: 1339 | AD24: =+IFERROR(W24/F24,"") -> 0.00019647652 | AE24: =+IFERROR(X24/F24,"") -> 0 | AF24: =+IFERROR(Y24/F24,"") -> 0 | AG24: =+IFERROR(Z24/F24,"") -> 0.014910385 | AH24: =+IFERROR(AA24/F24,"") -> 0.018119501 | AI24: =+IFERROR(AB24/F24,"") -> 0.02923134 | AK24: 224.64 | AL24: 1.59 | AM24: 1.59 | AN24: 17423.33 | AO24: 17213 | AP24: 32944.95 | AR24: Above 11% | AT24: 0 | AU24: 0 | AV24: 22097.88 | AW24: 23193.8 | AX24: 18240.6 | AY24: 31553.8
A25: 5029 | B25: Wynzora cream 0.5mg/g 60 | C25: 25.25 | D25: 1500 | E25: =D25/2 -> 750 | F25: 2564 | G25: =+E25/F25 -> 0.2925117 | I25: 0 | J25: 0 | K25: 0 | L25: 60 | N25: 230 | P25: =+I25*C25 -> 0 | Q25: =+J25*C25 -> 0 | R25: =+K25*C25 -> 0 | S25: =+L25*C25 -> 1515 | T25: =+M25*C25 -> 0 | U25: =+N25*C25 -> 5807.5 | W25: 0 | X25: 0 | Y25: 0 | Z25: 0 | AA25: 0 | AB25: 0 | AD25: =+IFERROR(W25/F25,"") -> 0 | AE25: =+IFERROR(X25/F25,"") -> 0 | AF25: =+IFERROR(Y25/F25,"") -> 0 | AG25: =+IFERROR(Z25/F25,"") -> 0 | AH25: =+IFERROR(AA25/F25,"") -> 0 | AI25: =+IFERROR(AB25/F25,"") -> 0 | AK25: 0 | AL25: 0 | AM25: 0 | AN25: 0 | AO25: 0 | AP25: 0 | AR25: Above 11% | AT25: 0 | AU25: 0 | AV25: 0 | AW25: 1762.5 | AX25: 0 | AY25: 15433.9
A26: 0920Y | B26: Donepezil 10mg Orodispersible Tablets 28 | C26: 25.2 | D26: 777.6 | E26: =D26/2 -> 388.8 | F26: 2722 | G26: =+E26/F26 -> 0.14283615 | I26: 0 | J26: 0 | K26: 0 | L26: 128 | M26: 40 | N26: 112 | P26: =+I26*C26 -> 0 | Q26: =+J26*C26 -> 0 | R26: =+K26*C26 -> 0 | S26: =+L26*C26 -> 3225.6 | T26: =+M26*C26 -> 1008 | U26: =+N26*C26 -> 2822.4 | W26: 315 | X26: 198 | Y26: 349 | Z26: 506 | AA26: 576 | AB26: 599 | AD26: =+IFERROR(W26/F26,"") -> 0.11572373 | AE26: =+IFERROR(X26/F26,"") -> 0.072740632 | AF26: =+IFERROR(Y26/F26,"") -> 0.12821455 | AG26: =+IFERROR(Z26/F26,"") -> 0.18589273 | AH26: =+IFERROR(AA26/F26,"") -> 0.21160911 | AI26: =+IFERROR(AB26/F26,"") -> 0.22005878 | AK26: 1890.46 | AL26: 2281.82 | AM26: 2281.82 | AN26: 3480.16 | AO26: 3680.35 | AP26: 3899.78 | AR26: Above 11% | AT26: 0 | AU26: 0 | AV26: 0 | AW26: 2816.62 | AX26: 838.8 | AY26: 2459.68
A27: 5325 | B27: Nebido Inj 1000 mg / 4ml Amp | C27: 24.51 | D27: 3000 | E27: =D27/2 -> 1500 | F27: 9407 | G27: =+E27/F27 -> 0.15945572 | I27: 785 | J27: 290 | K27: 1145 | L27: 1969 | M27: 43 | N27: 713 | P27: =+I27*C27 -> 19240.35 | Q27: =+J27*C27 -> 7107.9 | R27: =+K27*C27 -> 28063.95 | S27: =+L27*C27 -> 48260.19 | T27: =+M27*C27 -> 1053.93 | U27: =+N27*C27 -> 17475.63 | W27: 266 | X27: 0 | Y27: 803 | Z27: 1768 | AA27: 1809 | AB27: 194 | AD27: =+IFERROR(W27/F27,"") -> 0.028276815 | AE27: =+IFERROR(X27/F27,"") -> 0 | AF27: =+IFERROR(Y27/F27,"") -> 0.085361964 | AG27: =+IFERROR(Z27/F27,"") -> 0.18794515 | AH27: =+IFERROR(AA27/F27,"") -> 0.1923036 | AI27: =+IFERROR(AB27/F27,"") -> 0.02062294 | AK27: 881.11 | AL27: 0 | AM27: 19681.53 | AN27: 14415.35 | AO27: 41100.39 | AP27: 3954.39 | AR27: Above 11% | AT27: 46918.38 | AU27: 17579.4 | AV27: 70914.72 | AW27: 124545.97 | AX27: 2576.13 | AY27: 47624.97
A28: 5390 | B28: Lamictal 200mg Tablets 30 | C28: 23.95 | D28: 729.6 | E28: =D28/2 -> 364.8 | F28: 3648 | G28: =+E28/F28 -> 0.1 | I28: 232 | J28: 600 | K28: 0 | L28: 0 | N28: 120 | P28: =+I28*C28 -> 5556.4 | Q28: =+J28*C28 -> 14370 | R28: =+K28*C28 -> 0 | S28: =+L28*C28 -> 0 | T28: =+M28*C28 -> 0 | U28: =+N28*C28 -> 2874 | W28: 2 | X28: 3 | Y28: 1 | Z28: 1 | AA28: 4 | AB28: 0 | AD28: =+IFERROR(W28/F28,"") -> 0.00054824561 | AE28: =+IFERROR(X28/F28,"") -> 0.00082236842 | AF28: =+IFERROR(Y28/F28,"") -> 0.00027412281 | AG28: =+IFERROR(Z28/F28,"") -> 0.00027412281 | AH28: =+IFERROR(AA28/F28,"") -> 0.0010964912 | AI28: =+IFERROR(AB28/F28,"") -> 0 | AK28: 44.43 | AL28: 73.48 | AM28: 73.48 | AN28: 23.4 | AO28: 30.44 | AP28: 0 | AR28: Above 11% | AT28: 2484.72 | AU28: 6676 | AV28: 0 | AW28: 0 | AX28: 0 | AY28: 1246.8
A29: 5007 | B29: Fusidic acid 1% modified-release eye drops 5g (PI) | C29: 23.41 | D29: 2500 | E29: =D29/2 -> 1250 | F29: 5335 | G29: =+E29/F29 -> 0.23430178 | I29: 172 | J29: 0 | K29: 216 | L29: 0 | N29: 0 | P29: =+I29*C29 -> 4026.52 | Q29: =+J29*C29 -> 0 | R29: =+K29*C29 -> 5056.56 | S29: =+L29*C29 -> 0 | T29: =+M29*C29 -> 0 | U29: =+N29*C29 -> 0 | W29: 0 | X29: 0 | Y29: 0 | Z29: 0 | AA29: 0 | AB29: 325 | AD29: =+IFERROR(W29/F29,"") -> 0 | AE29: =+IFERROR(X29/F29,"") -> 0 | AF29: =+IFERROR(Y29/F29,"") -> 0 | AG29: =+IFERROR(Z29/F29,"") -> 0 | AH29: =+IFERROR(AA29/F29,"") -> 0 | AI29: =+IFERROR(AB29/F29,"") -> 0.060918463 | AK29: 0 | AL29: 0 | AM29: 0 | AN29: 0 | AO29: 0 | AP29: 7425.76 | AR29: Above 11% | AT29: 0 | AU29: 0 | AV29: 0 | AW29: 0 | AX29: 0 | AY29: 0
A30: 5092B | B30: Briviact F/C 100mg Tablets 56s | C30: 22.61 | D30: 2500 | E30: =D30/2 -> 1250 | F30: 7025 | G30: =+E30/F30 -> 0.17793594 | I30: 613.45455 | J30: 327.45455 | K30: 4300.6364 | L30: 2860.6061 | M30: 1993.9394 | N30: 1266 | P30: =+I30*C30 -> 13870.207 | Q30: =+J30*C30 -> 7403.7473 | R30: =+K30*C30 -> 97237.388 | S30: =+L30*C30 -> 64678.303 | T30: =+M30*C30 -> 45082.97 | U30: =+N30*C30 -> 28624.26 | W30: 1383 | X30: 1353 | Y30: 243 | Z30: 1085 | AA30: 2670 | AB30: 2302 | AD30: =+IFERROR(W30/F30,"") -> 0.19686833 | AE30: =+IFERROR(X30/F30,"") -> 0.19259786 | AF30: =+IFERROR(Y30/F30,"") -> 0.034590747 | AG30: =+IFERROR(Z30/F30,"") -> 0.1544484 | AH30: =+IFERROR(AA30/F30,"") -> 0.38007117 | AI30: =+IFERROR(AB30/F30,"") -> 0.32768683 | AK30: 2298.18 | AL30: 4008.55 | AM30: 4008.55 | AN30: 11406.93 | AO30: 15626.57 | AP30: 35049.07 | AR30: Above 11% | AT30: 66410.83 | AU30: 23361.61 | AV30: 304497.5 | AW30: 205058.1 | AX30: 143276.54 | AY30: 58532.53
A31: 5250D | B31: Epilim Chronosphere MR 500mg Sachets 30 | C31: 22.46 | D31: 1000 | E31: =D31/2 -> 500 | F31: 1089 | G31: =+E31/F31 -> 0.45913682 | I31: 0 | J31: 136 | K31: 471 | L31: 145 | N31: 0 | P31: =+I31*C31 -> 0 | Q31: =+J31*C31 -> 3054.56 | R31: =+K31*C31 -> 10578.66 | S31: =+L31*C31 -> 3256.7 | T31: =+M31*C31 -> 0 | U31: =+N31*C31 -> 0 | W31: 330 | X31: 793 | Y31: 90 | Z31: 358 | AA31: 189 | AB31: 0 | AD31: =+IFERROR(W31/F31,"") -> 0.3030303 | AE31: =+IFERROR(X31/F31,"") -> 0.728191 | AF31: =+IFERROR(Y31/F31,"") -> 0.082644628 | AG31: =+IFERROR(Z31/F31,"") -> 0.32874197 | AH31: =+IFERROR(AA31/F31,"") -> 0.17355372 | AI31: =+IFERROR(AB31/F31,"") -> 0 | AK31: 2600.09 | AL31: 8426.86 | AM31: 8426.86 | AN31: 1519.58 | AO31: 5557.32 | AP31: 0 | AR31: Above 11% | AT31: 0 | AU31: 953.34 | AV31: 3331.62 | AW31: 1014.8 | AX31: 0 | AY31: 0
A32: 5139 | B32: Abilify 15mg Tablets 28 | C32: 22.34 | D32: 100 | E32: =D32/2 -> 50 | F32: 87 | G32: =+E32/F32 -> 0.57471264 | I32: 100 | J32: 122 | K32: 0 | L32: 0 | N32: 0 | P32: =+I32*C32 -> 2234 | Q32: =+J32*C32 -> 2725.48 | R32: =+K32*C32 -> 0 | S32: =+L32*C32 -> 0 | T32: =+M32*C32 -> 0 | U32: =+N32*C32 -> 0 | W32: 23 | X32: 27 | Y32: 28 | Z32: 72 | AA32: 33 | AB32: 56 | AD32: =+IFERROR(W32/F32,"") -> 0.26436782 | AE32: =+IFERROR(X32/F32,"") -> 0.31034483 | AF32: =+IFERROR(Y32/F32,"") -> 0.32183908 | AG32: =+IFERROR(Z32/F32,"") -> 0.82758621 | AH32: =+IFERROR(AA32/F32,"") -> 0.37931034 | AI32: =+IFERROR(AB32/F32,"") -> 0.64367816 | AK32: 42.83 | AL32: 71.52 | AM32: 71.52 | AN32: 109.74 | AO32: 193.46 | AP32: 528.52 | AR32: Above 11% | AT32: 2252 | AU32: 2729.14 | AV32: 0 | AW32: 0 | AX32: 0 | AY32: 0
A33: 0906B | B33: Rifampicin 300mg Capsules ---- 60s | C33: 21.36 | D33: 300 | E33: =D33/2 -> 150 | F33: 548 | G33: =+E33/F33 -> 0.27372263 | I33: 0 | J33: 50 | K33: 0 | L33: 0 | N33: 0 | P33: =+I33*C33 -> 0 | Q33: =+J33*C33 -> 1068 | R33: =+K33*C33 -> 0 | S33: =+L33*C33 -> 0 | T33: =+M33*C33 -> 0 | U33: =+N33*C33 -> 0 | W33: 0 | X33: 0 | Y33: 0 | Z33: 0 | AA33: 0 | AB33: 0 | AD33: =+IFERROR(W33/F33,"") -> 0 | AE33: =+IFERROR(X33/F33,"") -> 0 | AF33: =+IFERROR(Y33/F33,"") -> 0 | AG33: =+IFERROR(Z33/F33,"") -> 0 | AH33: =+IFERROR(AA33/F33,"") -> 0 | AI33: =+IFERROR(AB33/F33,"") -> 0 | AK33: 0 | AL33: 0 | AM33: 0 | AN33: 0 | AO33: 0 | AP33: 0 | AR33: Above 11% | AT33: 0 | AU33: 692 | AV33: 0 | AW33: 0 | AX33: 0 | AY33: 0
A34: 9330A | B34: Rivastigmine Patches 4.6mg/24hr 30s | C34: 21 | D34: 880.8 | E34: =D34/2 -> 440.4 | F34: 4404 | G34: =+E34/F34 -> 0.1 | I34: 415 | J34: 413 | K34: 665 | L34: 894 | M34: 595 | N34: 557 | P34: =+I34*C34 -> 8715 | Q34: =+J34*C34 -> 8673 | R34: =+K34*C34 -> 13965 | S34: =+L34*C34 -> 18774 | T34: =+M34*C34 -> 12495 | U34: =+N34*C34 -> 11697 | W34: 49 | X34: 413 | Y34: 556 | Z34: 493 | AA34: 338 | AB34: 977 | AD34: =+IFERROR(W34/F34,"") -> 0.011126249 | AE34: =+IFERROR(X34/F34,"") -> 0.093778383 | AF34: =+IFERROR(Y34/F34,"") -> 0.12624886 | AG34: =+IFERROR(Z34/F34,"") -> 0.11194369 | AH34: =+IFERROR(AA34/F34,"") -> 0.076748411 | AI34: =+IFERROR(AB34/F34,"") -> 0.22184378 | AK34: 1235.06 | AL34: 7135.56 | AM34: 7135.56 | AN34: 8764.54 | AO34: 15380.39 | AP34: 18642.62 | AR34: Above 11% | AT34: 7545.05 | AU34: 7709.75 | AV34: 12250.07 | AW34: 16882.39 | AX34: 11327.41 | AY34: 10766.92
A35: 5934C | B35: Xarelto 15mg Tablets 28 | C35: 20.82 | D35: 100 | E35: =D35/2 -> 50 | F35: 167 | G35: =+E35/F35 -> 0.2994012 | I35: 700 | J35: 0 | K35: 0 | L35: 0 | M35: 800 | N35: 600 | P35: =+I35*C35 -> 14574 | Q35: =+J35*C35 -> 0 | R35: =+K35*C35 -> 0 | S35: =+L35*C35 -> 0 | T35: =+M35*C35 -> 16656 | U35: =+N35*C35 -> 12492 | W35: 112 | X35: 135 | Y35: 248 | Z35: 224 | AA35: 127 | AB35: 296 | AD35: =+IFERROR(W35/F35,"") -> 0.67065868 | AE35: =+IFERROR(X35/F35,"") -> 0.80838323 | AF35: =+IFERROR(Y35/F35,"") -> 1.4850299 | AG35: =+IFERROR(Z35/F35,"") -> 1.3413174 | AH35: =+IFERROR(AA35/F35,"") -> 0.76047904 | AI35: =+IFERROR(AB35/F35,"") -> 1.7724551 | AK35: 683.7 | AL35: 1372.96 | AM35: 1372.96 | AN35: 1993.39 | AO35: 1959.73 | AP35: 5416.14 | AR35: Above 11% | AT35: 21380 | AU35: 0 | AV35: 0 | AW35: 0 | AX35: 15331 | AY35: 8910
A36: 5250B | B36: Epilim Chronosphere MR 100mg Sachets 30 | C36: 20.78 | D36: 2000 | E36: =D36/2 -> 1000 | F36: 600 | G36: =+E36/F36 -> 1.6666667 | I36: 0 | J36: 100 | K36: 494 | L36: 286 | N36: 0 | P36: =+I36*C36 -> 0 | Q36: =+J36*C36 -> 2078 | R36: =+K36*C36 -> 10265.32 | S36: =+L36*C36 -> 5943.08 | T36: =+M36*C36 -> 0 | U36: =+N36*C36 -> 0 | W36: 1137 | X36: 873 | Y36: 0 | Z36: 261 | AA36: 417 | AB36: 0 | AD36: =+IFERROR(W36/F36,"") -> 1.895 | AE36: =+IFERROR(X36/F36,"") -> 1.455 | AF36: =+IFERROR(Y36/F36,"") -> 0 | AG36: =+IFERROR(Z36/F36,"") -> 0.435 | AH36: =+IFERROR(AA36/F36,"") -> 0.695 | AI36: =+IFERROR(AB36/F36,"") -> 0 | AK36: 21116.64 | AL36: 20169.1 | AM36: 20169.1 | AN36: 5423.58 | AO36: 5659.72 | AP36: 0 | AR36: Above 11% | AT36: 0 | AU36: 286 | AV36: 1525.84 | AW36: 864.62 | AX36: 0 | AY36: 0
A37: 5380F | B37: Lyrica 300mg Capsules 56 | C37: 20.25 | D37: 500 | E37: =D37/2 -> 250 | F37: 833 | G37: =+E37/F37 -> 0.30012005 | I37: 0 | J37: 0 | K37: 0 | L37: 144 | N37: 0 | P37: =+I37*C37 -> 0 | Q37: =+J37*C37 -> 0 | R37: =+K37*C37 -> 0 | S37: =+L37*C37 -> 2916 | T37: =+M37*C37 -> 0 | U37: =+N37*C37 -> 0 | W37: 184 | X37: 225 | Y37: 126 | Z37: 183 | AA37: 150 | AB37: 129 | AD37: =+IFERROR(W37/F37,"") -> 0.22088836 | AE37: =+IFERROR(X37/F37,"") -> 0.27010804 | AF37: =+IFERROR(Y37/F37,"") -> 0.1512605 | AG37: =+IFERROR(Z37/F37,"") -> 0.21968788 | AH37: =+IFERROR(AA37/F37,"") -> 0.18007203 | AI37: =+IFERROR(AB37/F37,"") -> 0.15486194 | AK37: 5948.84 | AL37: 5925.44 | AM37: 5925.44 | AN37: 2791.88 | AO37: 3921.34 | AP37: 2540.44 | AR37: Above 11% | AT37: 0 | AU37: 0 | AV37: 0 | AW37: 3079.78 | AX37: 0 | AY37: 0
A38: 5679 | B38: Zyprexa 20mg Velotabs 28 | C38: 20.1 | D38: 93.2 | E38: =D38/2 -> 46.6 | F38: 102 | G38: =+E38/F38 -> 0.45686275 | I38: 100 | J38: 0 | K38: 0 | L38: 0 | N38: 0 | P38: =+I38*C38 -> 2010 | Q38: =+J38*C38 -> 0 | R38: =+K38*C38 -> 0 | S38: =+L38*C38 -> 0 | T38: =+M38*C38 -> 0 | U38: =+N38*C38 -> 0 | W38: 103 | X38: 44 | Y38: 31 | Z38: 33 | AA38: 22 | AB38: 18 | AD38: =+IFERROR(W38/F38,"") -> 1.0098039 | AE38: =+IFERROR(X38/F38,"") -> 0.43137255 | AF38: =+IFERROR(Y38/F38,"") -> 0.30392157 | AG38: =+IFERROR(Z38/F38,"") -> 0.32352941 | AH38: =+IFERROR(AA38/F38,"") -> 0.21568627 | AI38: =+IFERROR(AB38/F38,"") -> 0.17647059 | AK38: 3054.22 | AL38: 1223.83 | AM38: 1223.83 | AN38: 827.66 | AO38: 971.14 | AP38: 364.14 | AR38: Above 11% | AT38: 3125 | AU38: 0 | AV38: 0 | AW38: 0 | AX38: 0 | AY38: 0
A39: 5251J | B39: EPILIM CHRONO MR 750MG GRAN SACH 30 | C39: 18.78 | D39: 600 | E39: =D39/2 -> 300 | F39: 176 | G39: =+E39/F39 -> 1.7045455 | I39: 0 | J39: 0 | K39: 0 | L39: 213 | N39: 0 | P39: =+I39*C39 -> 0 | Q39: =+J39*C39 -> 0 | R39: =+K39*C39 -> 0 | S39: =+L39*C39 -> 4000.14 | T39: =+M39*C39 -> 0 | U39: =+N39*C39 -> 0 | W39: 16 | X39: 305 | Y39: 61 | Z39: 0 | AA39: 38 | AB39: 140 | AD39: =+IFERROR(W39/F39,"") -> 0.090909091 | AE39: =+IFERROR(X39/F39,"") -> 1.7329545 | AF39: =+IFERROR(Y39/F39,"") -> 0.34659091 | AG39: =+IFERROR(Z39/F39,"") -> 0 | AH39: =+IFERROR(AA39/F39,"") -> 0.21590909 | AI39: =+IFERROR(AB39/F39,"") -> 0.79545455 | AK39: 255.76 | AL39: 2809.92 | AM39: 2809.92 | AN39: 1138.8 | AO39: 713.64 | AP39: 2559.06 | AR39: Above 11% | AT39: 0 | AU39: 0 | AV39: 0 | AW39: 2066.25 | AX39: 0 | AY39: 0
A40: 5092 | B40: Briviact F/C 50mg Tablets 56s | C40: 18.23 | D40: 1500 | E40: =D40/2 -> 750 | F40: 4846 | G40: =+E40/F40 -> 0.15476682 | I40: 398.18182 | J40: 0 | K40: 245 | L40: 144 | M40: 490 | N40: 475 | P40: =+I40*C40 -> 7258.8545 | Q40: =+J40*C40 -> 0 | R40: =+K40*C40 -> 4466.35 | S40: =+L40*C40 -> 2625.12 | T40: =+M40*C40 -> 8932.7 | U40: =+N40*C40 -> 8659.25 | W40: 1008 | X40: 542 | Y40: 49 | Z40: 975 | AA40: 1524 | AB40: 1130 | AD40: =+IFERROR(W40/F40,"") -> 0.2080066 | AE40: =+IFERROR(X40/F40,"") -> 0.11184482 | AF40: =+IFERROR(Y40/F40,"") -> 0.010111432 | AG40: =+IFERROR(Z40/F40,"") -> 0.20119686 | AH40: =+IFERROR(AA40/F40,"") -> 0.31448617 | AI40: =+IFERROR(AB40/F40,"") -> 0.23318201 | AK40: 2197.37 | AL40: 2838.07 | AM40: 2838.07 | AN40: 2158.22 | AO40: 42398.23 | AP40: 16181.12 | AR40: Above 11% | AT40: 5674.5 | AU40: 0 | AV40: 17369.15 | AW40: 10195.2 | AX40: 34846.55 | AY40: 33335.5
A41: 5427 | B41: Maxalt 10mg Tablets 6 | C41: 18.11 | D41: 58.2 | E41: =D41/2 -> 29.1 | F41: 291 | G41: =+E41/F41 -> 0.1 | I41: 0 | J41: 0 | K41: 0 | L41: 0 | N41: 0 | P41: =+I41*C41 -> 0 | Q41: =+J41*C41 -> 0 | R41: =+K41*C41 -> 0 | S41: =+L41*C41 -> 0 | T41: =+M41*C41 -> 0 | U41: =+N41*C41 -> 0 | W41: 0 | X41: 0 | Y41: 0 | Z41: 0 | AA41: 0 | AB41: 0 | AD41: =+IFERROR(W41/F41,"") -> 0 | AE41: =+IFERROR(X41/F41,"") -> 0 | AF41: =+IFERROR(Y41/F41,"") -> 0 | AG41: =+IFERROR(Z41/F41,"") -> 0 | AH41: =+IFERROR(AA41/F41,"") -> 0 | AI41: =+IFERROR(AB41/F41,"") -> 0 | AK41: 0 | AL41: 0 | AM41: 0 | AN41: 0 | AO41: 0 | AP41: 0 | AR41: Above 11% | AT41: 0 | AU41: 0 | AV41: 0 | AW41: 0 | AX41: 0 | AY41: 0
A42: 5284D | B42: Buccolam 7.5Mg/1.5ml oral syringe 4s | C42: 17.67 | D42: 500 | E42: =D42/2 -> 250 | F42: 469 | G42: =+E42/F42 -> 0.53304904 | I42: 0 | J42: 0 | K42: 50 | L42: 192 | N42: 0 | P42: =+I42*C42 -> 0 | Q42: =+J42*C42 -> 0 | R42: =+K42*C42 -> 883.5 | S42: =+L42*C42 -> 3392.64 | T42: =+M42*C42 -> 0 | U42: =+N42*C42 -> 0 | W42: 134 | X42: 168 | Y42: 138 | Z42: 147 | AA42: 106 | AB42: 196 | AD42: =+IFERROR(W42/F42,"") -> 0.28571429 | AE42: =+IFERROR(X42/F42,"") -> 0.35820896 | AF42: =+IFERROR(Y42/F42,"") -> 0.29424307 | AG42: =+IFERROR(Z42/F42,"") -> 0.31343284 | AH42: =+IFERROR(AA42/F42,"") -> 0.22601279 | AI42: =+IFERROR(AB42/F42,"") -> 0.41791045 | AK42: 626.55 | AL42: 767.84 | AM42: 767.84 | AN42: 875.43 | AO42: 824.52 | AP42: 3350 | AR42: Above 11% | AT42: 0 | AU42: 0 | AV42: 3009 | AW42: 11554.56 | AX42: 0 | AY42: 0
A43: 1050 | B43: Ursodeoxycholic Acid 150mg Tablets 60 | C43: 17.12 | D43: 1946.4 | E43: =D43/2 -> 973.2 | F43: 2199 | G43: =+E43/F43 -> 0.4425648 | I43: 0 | J43: 0 | K43: 0 | L43: 0 | M43: 160 | N43: 1016 | P43: =+I43*C43 -> 0 | Q43: =+J43*C43 -> 0 | R43: =+K43*C43 -> 0 | S43: =+L43*C43 -> 0 | T43: =+M43*C43 -> 2739.2 | U43: =+N43*C43 -> 17393.92 | W43: 587 | X43: 912 | Y43: 412 | Z43: 1995 | AA43: 960 | AB43: 633 | AD43: =+IFERROR(W43/F43,"") -> 0.26693952 | AE43: =+IFERROR(X43/F43,"") -> 0.41473397 | AF43: =+IFERROR(Y43/F43,"") -> 0.18735789 | AG43: =+IFERROR(Z43/F43,"") -> 0.90723056 | AH43: =+IFERROR(AA43/F43,"") -> 0.43656207 | AI43: =+IFERROR(AB43/F43,"") -> 0.28785812 | AK43: 2676 | AL43: 1728.66 | AM43: 1728.66 | AN43: 111.38 | AO43: 16435.2 | AP43: 6418.41 | AR43: Above 11% | AT43: 0 | AU43: 0 | AV43: 0 | AW43: 0 | AX43: 803.2 | AY43: 5169.51
A44: 360 | B44: Ontozry 50mg Tabs 28 | C44: 16.69 | D44: 1000 | E44: =D44/2 -> 500 | F44: 2287 | G44: =+E44/F44 -> 0.21862702 | I44: 0 | J44: 0 | K44: 0 | L44: 0 | M44: 60 | N44: 161 | P44: =+I44*C44 -> 0 | Q44: =+J44*C44 -> 0 | R44: =+K44*C44 -> 0 | S44: =+L44*C44 -> 0 | T44: =+M44*C44 -> 1001.4 | U44: =+N44*C44 -> 2687.09 | W44: 0 | X44: 0 | Y44: 0 | Z44: 0 | AA44: 0 | AB44: 0 | AD44: =+IFERROR(W44/F44,"") -> 0 | AE44: =+IFERROR(X44/F44,"") -> 0 | AF44: =+IFERROR(Y44/F44,"") -> 0 | AG44: =+IFERROR(Z44/F44,"") -> 0 | AH44: =+IFERROR(AA44/F44,"") -> 0 | AI44: =+IFERROR(AB44/F44,"") -> 0 | AK44: 0 | AL44: 0 | AM44: 0 | AN44: 0 | AO44: 0 | AP44: 0 | AR44: Below 11% | AT44: 0 | AU44: 0 | AV44: 0 | AW44: 0 | AX44: 4194.6 | AY44: 11265.98
A45: L9021B | B45: Inegy 10mg/20mg Tablets 30 | C45: 15.938362 | D45: 50 | E45: =D45/2 -> 25 | F45: 14 | G45: =+E45/F45 -> 1.7857143 | I45: 0 | J45: 0 | K45: 0 | L45: 0 | M45: 0 | N45: 90 | U45: =+N45*C45 -> 1434.4526 | AD45: =+IFERROR(W45/F45,"") -> 0 | AE45: =+IFERROR(X45/F45,"") -> 0 | AF45: =+IFERROR(Y45/F45,"") -> 0 | AG45: =+IFERROR(Z45/F45,"") -> 0 | AH45: =+IFERROR(AA45/F45,"") -> 0 | AI45: =+IFERROR(AB45/F45,"") -> 0 | AR45: Above 11% | AT45: 0 | AU45: 0 | AV45: 0 | AW45: 0 | AX45: 0 | AY45: 1017
A46: 5733B | B46: Zonegran 100mg Capsules 56 | C46: 14.07 | D46: 1000 | E46: =D46/2 -> 500 | F46: 1313 | G46: =+E46/F46 -> 0.38080731 | I46: 183 | J46: 564 | K46: 397 | L46: 243 | M46: 53 | N46: 127 | P46: =+I46*C46 -> 2574.81 | Q46: =+J46*C46 -> 7935.48 | R46: =+K46*C46 -> 5585.79 | S46: =+L46*C46 -> 3419.01 | T46: =+M46*C46 -> 745.71 | U46: =+N46*C46 -> 1786.89 | W46: 172 | X46: 506 | Y46: 487 | Z46: 249 | AA46: 608 | AB46: 168 | AD46: =+IFERROR(W46/F46,"") -> 0.13099772 | AE46: =+IFERROR(X46/F46,"") -> 0.385377 | AF46: =+IFERROR(Y46/F46,"") -> 0.37090632 | AG46: =+IFERROR(Z46/F46,"") -> 0.18964204 | AH46: =+IFERROR(AA46/F46,"") -> 0.46306169 | AI46: =+IFERROR(AB46/F46,"") -> 0.12795126 | AK46: 1868.82 | AL46: 4865.32 | AM46: 4865.32 | AN46: 4468.56 | AO46: 2282.35 | AP46: 2377.31 | AR46: Above 11% | AT46: 8301.66 | AU46: 26103.71 | AV46: 17782.46 | AW46: 9450.8 | AX46: 2110.46 | AY46: 5062.02
A47: 0211F | B47: Cabergoline 2mg Tablets 20 | C47: 14.02 | D47: 120 | E47: =D47/2 -> 60 | F47: 27 | G47: =+E47/F47 -> 2.2222222 | I47: 0 | J47: 0 | K47: 100 | L47: 95 | N47: 0 | P47: =+I47*C47 -> 0 | Q47: =+J47*C47 -> 0 | R47: =+K47*C47 -> 1402 | S47: =+L47*C47 -> 1331.9 | T47: =+M47*C47 -> 0 | U47: =+N47*C47 -> 0 | W47: 9 | X47: 11 | Y47: 3 | Z47: 3 | AA47: 9 | AB47: 30 | AD47: =+IFERROR(W47/F47,"") -> 0.33333333 | AE47: =+IFERROR(X47/F47,"") -> 0.40740741 | AF47: =+IFERROR(Y47/F47,"") -> 0.11111111 | AG47: =+IFERROR(Z47/F47,"") -> 0.11111111 | AH47: =+IFERROR(AA47/F47,"") -> 0.33333333 | AI47: =+IFERROR(AB47/F47,"") -> 1.1111111 | AK47: 122.14 | AL47: 117.83 | AM47: 117.83 | AN47: 55.8 | AO47: 32.66 | AP47: 325.34 | AR47: Above 11% | AT47: 0 | AU47: 0 | AV47: 1687 | AW47: 1608.35 | AX47: 0 | AY47: 0
A48: L9597B | B48: Neupro 6mg/24hr Transdermal Patches 28 | C48: 13.9 | D48: 600 | E48: =D48/2 -> 300 | F48: 1585 | G48: =+E48/F48 -> 0.18927445 | I48: 0 | J48: 50 | K48: 123 | L48: 149 | N48: 400 | P48: =+I48*C48 -> 0 | Q48: =+J48*C48 -> 695 | R48: =+K48*C48 -> 1709.7 | S48: =+L48*C48 -> 2071.1 | T48: =+M48*C48 -> 0 | U48: =+N48*C48 -> 5560 | W48: 172 | X48: 191 | Y48: 14 | Z48: 137 | AA48: 12 | AB48: 49 | AD48: =+IFERROR(W48/F48,"") -> 0.10851735 | AE48: =+IFERROR(X48/F48,"") -> 0.12050473 | AF48: =+IFERROR(Y48/F48,"") -> 0.0088328076 | AG48: =+IFERROR(Z48/F48,"") -> 0.086435331 | AH48: =+IFERROR(AA48/F48,"") -> 0.0075709779 | AI48: =+IFERROR(AB48/F48,"") -> 0.030914826 | AK48: 1779.1 | AL48: 2145.45 | AM48: 2145.45 | AN48: 199.95 | AO48: 1751.26 | AP48: 695.98 | AR48: Above 11% | AT48: 0 | AU48: 3141.5 | AV48: 7722.38 | AW48: 8757.02 | AX48: 0 | AY48: 23108.5
A49: 5040 | B49: Vesicare oral suspension 1mg/ml 1's | C49: 13.603612 | D49: 500 | E49: =D49/2 -> 250 | F49: 1202 | G49: =+E49/F49 -> 0.20798669 | I49: 0 | J49: 0 | K49: 0 | L49: 0 | M49: 0 | N49: 235 | U49: =+N49*C49 -> 3196.8488 | AD49: =+IFERROR(W49/F49,"") -> 0 | AE49: =+IFERROR(X49/F49,"") -> 0 | AF49: =+IFERROR(Y49/F49,"") -> 0 | AG49: =+IFERROR(Z49/F49,"") -> 0 | AH49: =+IFERROR(AA49/F49,"") -> 0 | AI49: =+IFERROR(AB49/F49,"") -> 0 | AR49: Above 11% | AT49: 0 | AU49: 0 | AV49: 0 | AW49: 0 | AX49: 0 | AY49: 3211.36
A50: 5949 | B50: Loprazolam 1mg Tablets 30 | C50: 13.29 | D50: 500 | E50: =D50/2 -> 250 | F50: 704 | G50: =+E50/F50 -> 0.35511364 | I50: 0 | J50: 0 | K50: 0 | L50: 0 | M50: 500 | N50: 0 | P50: =+I50*C50 -> 0 | Q50: =+J50*C50 -> 0 | R50: =+K50*C50 -> 0 | S50: =+L50*C50 -> 0 | T50: =+M50*C50 -> 6645 | U50: =+N50*C50 -> 0 | W50: 113 | X50: 18 | Y50: 105 | Z50: 77 | AA50: 0 | AB50: 108 | AD50: =+IFERROR(W50/F50,"") -> 0.16051136 | AE50: =+IFERROR(X50/F50,"") -> 0.025568182 | AF50: =+IFERROR(Y50/F50,"") -> 0.14914773 | AG50: =+IFERROR(Z50/F50,"") -> 0.109375 | AH50: =+IFERROR(AA50/F50,"") -> 0 | AI50: =+IFERROR(AB50/F50,"") -> 0.15340909 | AK50: 299.48 | AL50: 140.31 | AM50: 140.31 | AN50: 1182.11 | AO50: 372.1 | AP50: 1393.46 | AR50: Above 11% | AT50: 0 | AU50: 0 | AV50: 0 | AW50: 0 | AX50: 1190 | AY50: 0
A51: 5591 | B51: Tranylcypromine 10mg Tablets 28 | C51: 12.76 | D51: 400 | E51: =D51/2 -> 200 | F51: 265 | G51: =+E51/F51 -> 0.75471698 | I51: 0 | J51: 0 | K51: 0 | L51: 0 | M51: 11 | N51: 0 | P51: =+I51*C51 -> 0 | Q51: =+J51*C51 -> 0 | R51: =+K51*C51 -> 0 | S51: =+L51*C51 -> 0 | T51: =+M51*C51 -> 140.36 | U51: =+N51*C51 -> 0 | W51: 62 | X51: 107 | Y51: -4 | Z51: -5 | AA51: 20 | AB51: 0 | AD51: =+IFERROR(W51/F51,"") -> 0.23396226 | AE51: =+IFERROR(X51/F51,"") -> 0.40377358 | AF51: =+IFERROR(Y51/F51,"") -> -0.01509434 | AG51: =+IFERROR(Z51/F51,"") -> -0.018867925 | AH51: =+IFERROR(AA51/F51,"") -> 0.075471698 | AI51: =+IFERROR(AB51/F51,"") -> 0 | AK51: 375.09 | AL51: 329 | AM51: 329 | AN51: 0 | AO51: 255.2 | AP51: 0 | AR51: Below 11% | AT51: 0 | AU51: 0 | AV51: 0 | AW51: 0 | AX51: 181.72 | AY51: 0
A52: 5429A | B52: Nalcrom 100mg Capsules 100 | C52: 12.7 | D52: 1000 | E52: =D52/2 -> 500 | F52: 1449 | G52: =+E52/F52 -> 0.34506556 | I52: 1699.2 | J52: 1620 | K52: 1022.8 | L52: 1000 | M52: 2000 | N52: 4000 | P52: =+I52*C52 -> 21579.84 | Q52: =+J52*C52 -> 20574 | R52: =+K52*C52 -> 12989.56 | S52: =+L52*C52 -> 12700 | T52: =+M52*C52 -> 25400 | U52: =+N52*C52 -> 50800 | W52: 90 | X52: 49 | Y52: 0 | Z52: 399 | AA52: 297 | AB52: 712 | AD52: =+IFERROR(W52/F52,"") -> 0.062111801 | AE52: =+IFERROR(X52/F52,"") -> 0.033816425 | AF52: =+IFERROR(Y52/F52,"") -> 0 | AG52: =+IFERROR(Z52/F52,"") -> 0.27536232 | AH52: =+IFERROR(AA52/F52,"") -> 0.20496894 | AI52: =+IFERROR(AB52/F52,"") -> 0.49137336 | AK52: 715.63 | AL52: 372.71 | AM52: 372.71 | AN52: 5067.3 | AO52: 2399.2 | AP52: 5935.84 | AR52: Above 11% | AT52: 0 | AU52: 0 | AV52: 0 | AW52: 0 | AX52: 0 | AY52: 0
A53: 5680F | B53: Adartrel 0.5mg Tablets 84 | C53: 12.02 | D53: 2000 | E53: =D53/2 -> 1000 | F53: 8803 | G53: =+E53/F53 -> 0.11359764 | I53: 0 | J53: 2778.7879 | K53: 2906.0606 | L53: 3960.6061 | M53: 4057.5758 | N53: 750 | P53: =+I53*C53 -> 0 | Q53: =+J53*C53 -> 33401.03 | R53: =+K53*C53 -> 34930.848 | S53: =+L53*C53 -> 47606.485 | T53: =+M53*C53 -> 48772.061 | U53: =+N53*C53 -> 9015 | W53: 0 | X53: 0 | Y53: 0 | Z53: 0 | AA53: 0 | AB53: 0 | AD53: =+IFERROR(W53/F53,"") -> 0 | AE53: =+IFERROR(X53/F53,"") -> 0 | AF53: =+IFERROR(Y53/F53,"") -> 0 | AG53: =+IFERROR(Z53/F53,"") -> 0 | AH53: =+IFERROR(AA53/F53,"") -> 0 | AI53: =+IFERROR(AB53/F53,"") -> 0 | AK53: 0 | AL53: 0 | AM53: 0 | AN53: 0 | AO53: 0 | AP53: 0 | AR53: Above 11% | AT53: 1262.56 | AU53: 4259.8 | AV53: 4614.05 | AW53: 6252.79 | AX53: 6440.45 | AY53: 3624.14
A54: 5945 | B54: Innozide 20mg/12.5mg Tablets 28 | C54: 11.88 | D54: 1000 | E54: =D54/2 -> 500 | F54: 364 | G54: =+E54/F54 -> 1.3736264 | I54: 0 | J54: 0 | K54: 0 | L54: 301 | N54: 542 | P54: =+I54*C54 -> 0 | Q54: =+J54*C54 -> 0 | R54: =+K54*C54 -> 0 | S54: =+L54*C54 -> 3575.88 | T54: =+M54*C54 -> 0 | U54: =+N54*C54 -> 6438.96 | W54: 0 | X54: 8 | Y54: 0 | Z54: 0 | AA54: 7 | AB54: 100 | AD54: =+IFERROR(W54/F54,"") -> 0 | AE54: =+IFERROR(X54/F54,"") -> 0.021978022 | AF54: =+IFERROR(Y54/F54,"") -> 0 | AG54: =+IFERROR(Z54/F54,"") -> 0 | AH54: =+IFERROR(AA54/F54,"") -> 0.019230769 | AI54: =+IFERROR(AB54/F54,"") -> 0.27472527 | AK54: 0 | AL54: 14.16 | AM54: 14.16 | AN54: 0 | AO54: 83.16 | AP54: 354.93 | AR54: Above 11% | AT54: 0 | AU54: 0 | AV54: 0 | AW54: 370.23 | AX54: 0 | AY54: 659.32
A55: 5031 | B55: Xultophy solution for injection pre-filled pens 100iu/ml/3.6mg/ml | C55: 11.87 | D55: 400 | E55: =D55/2 -> 200 | F55: 849 | G55: =+E55/F55 -> 0.23557126 | I55: 0 | J55: 0 | K55: 120 | L55: 1000 | M55: 600 | N55: 0 | P55: =+I55*C55 -> 0 | Q55: =+J55*C55 -> 0 | R55: =+K55*C55 -> 1424.4 | S55: =+L55*C55 -> 11870 | T55: =+M55*C55 -> 7122 | U55: =+N55*C55 -> 0 | W55: 0 | X55: 79 | Y55: 255 | Z55: 274 | AA55: 956 | AB55: 206 | AD55: =+IFERROR(W55/F55,"") -> 0 | AE55: =+IFERROR(X55/F55,"") -> 0.093050648 | AF55: =+IFERROR(Y55/F55,"") -> 0.30035336 | AG55: =+IFERROR(Z55/F55,"") -> 0.32273263 | AH55: =+IFERROR(AA55/F55,"") -> 1.1260306 | AI55: =+IFERROR(AB55/F55,"") -> 0.2426384 | AK55: 0 | AL55: 230.6 | AM55: 230.6 | AN55: 800.48 | AO55: 866.46 | AP55: 1857.23 | AR55: Above 11% | AT55: 0 | AU55: 0 | AV55: 9643.2 | AW55: 79650 | AX55: 48216 | AY55: 0
A56: 5284C | B56: Buccolam 5Mg /1ml oral syringe 4s | C56: 11.75 | D56: 300 | E56: =D56/2 -> 150 | F56: 367 | G56: =+E56/F56 -> 0.40871935 | I56: 100 | J56: 0 | K56: 50 | L56: 135 | N56: 0 | P56: =+I56*C56 -> 1175 | Q56: =+J56*C56 -> 0 | R56: =+K56*C56 -> 587.5 | S56: =+L56*C56 -> 1586.25 | T56: =+M56*C56 -> 0 | U56: =+N56*C56 -> 0 | W56: 174 | X56: 235 | Y56: 123 | Z56: 166 | AA56: 187 | AB56: 184 | AD56: =+IFERROR(W56/F56,"") -> 0.47411444 | AE56: =+IFERROR(X56/F56,"") -> 0.64032698 | AF56: =+IFERROR(Y56/F56,"") -> 0.33514986 | AG56: =+IFERROR(Z56/F56,"") -> 0.45231608 | AH56: =+IFERROR(AA56/F56,"") -> 0.50953678 | AI56: =+IFERROR(AB56/F56,"") -> 0.5013624 | AK56: 822.51 | AL56: 1075.57 | AM56: 1075.57 | AN56: 418.41 | AO56: 1379.46 | AP56: 2109.49 | AR56: Above 11% | AT56: 7589 | AU56: 0 | AV56: 3009 | AW56: 8124.3 | AX56: 0 | AY56: 0
A57: 5427A | B57: Maxalt 5mg Tablets 6 | C57: 11.52 | D57: 66.8 | E57: =D57/2 -> 33.4 | F57: 109 | G57: =+E57/F57 -> 0.30642202 | I57: 78 | J57: 0 | K57: 0 | L57: 0 | N57: 0 | P57: =+I57*C57 -> 898.56 | Q57: =+J57*C57 -> 0 | R57: =+K57*C57 -> 0 | S57: =+L57*C57 -> 0 | T57: =+M57*C57 -> 0 | U57: =+N57*C57 -> 0 | W57: 0 | X57: 102 | Y57: 65 | Z57: 0 | AA57: 0 | AB57: 0 | AD57: =+IFERROR(W57/F57,"") -> 0 | AE57: =+IFERROR(X57/F57,"") -> 0.93577982 | AF57: =+IFERROR(Y57/F57,"") -> 0.59633028 | AG57: =+IFERROR(Z57/F57,"") -> 0 | AH57: =+IFERROR(AA57/F57,"") -> 0 | AI57: =+IFERROR(AB57/F57,"") -> 0 | AK57: 0 | AL57: 293.54 | AM57: 293.54 | AN57: 686.46 | AO57: 0 | AP57: 0 | AR57: Above 11% | AT57: 673.48 | AU57: 0 | AV57: 0 | AW57: 0 | AX57: 0 | AY57: 0
A58: 5934D | B58: Xarelto 20mg Tablets 28 | C58: 11.52 | D58: 700 | E58: =D58/2 -> 350 | F58: 695 | G58: =+E58/F58 -> 0.50359712 | I58: 1285.7143 | J58: 178.57143 | K58: 0 | L58: 0 | N58: 450 | P58: =+I58*C58 -> 14811.429 | Q58: =+J58*C58 -> 2057.1429 | R58: =+K58*C58 -> 0 | S58: =+L58*C58 -> 0 | T58: =+M58*C58 -> 0 | U58: =+N58*C58 -> 5184 | W58: 116 | X58: 238 | Y58: 546 | Z58: 337 | AA58: 760 | AB58: 461 | AD58: =+IFERROR(W58/F58,"") -> 0.16690647 | AE58: =+IFERROR(X58/F58,"") -> 0.34244604 | AF58: =+IFERROR(Y58/F58,"") -> 0.78561151 | AG58: =+IFERROR(Z58/F58,"") -> 0.48489209 | AH58: =+IFERROR(AA58/F58,"") -> 1.0935252 | AI58: =+IFERROR(AB58/F58,"") -> 0.66330935 | AK58: 293.85 | AL58: 2579.79 | AM58: 2579.79 | AN58: 5996.62 | AO58: 3958.27 | AP58: 5051.39 | AR58: Above 11% | AT58: 41169.56 | AU58: 4464.5 | AV58: 0 | AW58: 0 | AX58: 0 | AY58: 11842.5
A59: 5250F | B59: Targinact 10mg/5mg Modified Release Tablets 56 | C59: 11.01 | D59: 200 | E59: =D59/2 -> 100 | F59: 547 | G59: =+E59/F59 -> 0.18281536 | I59: 0 | J59: 500 | K59: 594 | L59: 0 | N59: 0 | P59: =+I59*C59 -> 0 | Q59: =+J59*C59 -> 5505 | R59: =+K59*C59 -> 6539.94 | S59: =+L59*C59 -> 0 | T59: =+M59*C59 -> 0 | U59: =+N59*C59 -> 0 | W59: 93 | X59: 0 | Y59: 98 | Z59: 107 | AA59: 90 | AB59: 85 | AD59: =+IFERROR(W59/F59,"") -> 0.17001828 | AE59: =+IFERROR(X59/F59,"") -> 0 | AF59: =+IFERROR(Y59/F59,"") -> 0.17915905 | AG59: =+IFERROR(Z59/F59,"") -> 0.19561243 | AH59: =+IFERROR(AA59/F59,"") -> 0.16453382 | AI59: =+IFERROR(AB59/F59,"") -> 0.15539305 | AK59: 360.89 | AL59: 0 | AM59: 1078.98 | AN59: 341.09 | AO59: 444.39 | AP59: 888.58 | AR59: Above 11% | AT59: 0 | AU59: 7810 | AV59: 9201.06 | AW59: 0 | AX59: 0 | AY59: 0
A60: 5754 | B60: Zyprexa 10mg (Olanzepine) Tablets 28 | C60: 10.96 | D60: 70 | E60: =D60/2 -> 35 | F60: 148 | G60: =+E60/F60 -> 0.23648649 | I60: 100 | J60: 0 | K60: 0 | L60: 0 | N60: 0 | P60: =+I60*C60 -> 1096 | Q60: =+J60*C60 -> 0 | R60: =+K60*C60 -> 0 | S60: =+L60*C60 -> 0 | T60: =+M60*C60 -> 0 | U60: =+N60*C60 -> 0 | W60: 0 | X60: 0 | Y60: 0 | Z60: 0 | AA60: 55 | AB60: 64 | AD60: =+IFERROR(W60/F60,"") -> 0 | AE60: =+IFERROR(X60/F60,"") -> 0 | AF60: =+IFERROR(Y60/F60,"") -> 0 | AG60: =+IFERROR(Z60/F60,"") -> 0 | AH60: =+IFERROR(AA60/F60,"") -> 0.37162162 | AI60: =+IFERROR(AB60/F60,"") -> 0.43243243 | AK60: 0 | AL60: 0 | AM60: 0 | AN60: 0 | AO60: 602.8 | AP60: 1206.68 | AR60: Above 11% | AT60: 1250 | AU60: 0 | AV60: 0 | AW60: 0 | AX60: 0 | AY60: 0
A61: 5774 | B61: Relpax 40mg Tablets 6 | C61: 10.7 | D61: 500 | E61: =D61/2 -> 250 | F61: 1821 | G61: =+E61/F61 -> 0.1372872 | I61: 0 | J61: 100 | K61: 0 | L61: 0 | M61: 89 | N61: 0 | P61: =+I61*C61 -> 0 | Q61: =+J61*C61 -> 1070 | R61: =+K61*C61 -> 0 | S61: =+L61*C61 -> 0 | T61: =+M61*C61 -> 952.3 | U61: =+N61*C61 -> 0 | W61: 52 | X61: 269 | Y61: 1 | Z61: 0 | AA61: 0 | AB61: 1 | AD61: =+IFERROR(W61/F61,"") -> 0.028555739 | AE61: =+IFERROR(X61/F61,"") -> 0.14772103 | AF61: =+IFERROR(Y61/F61,"") -> 0.00054914882 | AG61: =+IFERROR(Z61/F61,"") -> 0 | AH61: =+IFERROR(AA61/F61,"") -> 0 | AI61: =+IFERROR(AB61/F61,"") -> 0.00054914882 | AK61: 23.55 | AL61: 220.65 | AM61: 220.65 | AN61: 0.07 | AO61: 0 | AP61: 10.7 | AR61: Above 11% | AT61: 0 | AU61: 1205 | AV61: 0 | AW61: 0 | AX61: 942.68 | AY61: 0
A62: L9117 | B62: Exforge 10mg/160mg Tablets 28 | C62: 10.35 | D62: 1000 | E62: =D62/2 -> 500 | F62: 782 | G62: =+E62/F62 -> 0.63938619 | I62: 377 | J62: 711 | K62: 272 | L62: 494 | M62: 530 | N62: 303 | P62: =+I62*C62 -> 3901.95 | Q62: =+J62*C62 -> 7358.85 | R62: =+K62*C62 -> 2815.2 | S62: =+L62*C62 -> 5112.9 | T62: =+M62*C62 -> 5485.5 | U62: =+N62*C62 -> 3136.05 | W62: 53 | X62: 66 | Y62: 273 | Z62: 214 | AA62: 364 | AB62: 492 | AD62: =+IFERROR(W62/F62,"") -> 0.067774936 | AE62: =+IFERROR(X62/F62,"") -> 0.084398977 | AF62: =+IFERROR(Y62/F62,"") -> 0.34910486 | AG62: =+IFERROR(Z62/F62,"") -> 0.27365729 | AH62: =+IFERROR(AA62/F62,"") -> 0.46547315 | AI62: =+IFERROR(AB62/F62,"") -> 0.62915601 | AK62: 55.77 | AL62: 223.94 | AM62: 223.94 | AN62: 1342.73 | AO62: 1149.67 | AP62: 1071.21 | AR62: Above 11% | AT62: 3688.24 | AU62: 7008.7 | AV62: 2632.19 | AW62: 5097.06 | AX62: 5210.71 | AY62: 2956.68
A63: 4989D | B63: Co-Trimoxazole 40/200mg/5ml Oral Suspension SF 100ml | C63: 10.3 | D63: 1000 | E63: =D63/2 -> 500 | F63: 837 | G63: =+E63/F63 -> 0.59737157 | I63: 0 | J63: 520 | K63: 50 | L63: 0 | N63: 100 | P63: =+I63*C63 -> 0 | Q63: =+J63*C63 -> 5356 | R63: =+K63*C63 -> 515 | S63: =+L63*C63 -> 0 | T63: =+M63*C63 -> 0 | U63: =+N63*C63 -> 1030 | W63: 199 | X63: 4 | Y63: 0 | Z63: 0 | AA63: 0 | AB63: 0 | AD63: =+IFERROR(W63/F63,"") -> 0.23775388 | AE63: =+IFERROR(X63/F63,"") -> 0.0047789725 | AF63: =+IFERROR(Y63/F63,"") -> 0 | AG63: =+IFERROR(Z63/F63,"") -> 0 | AH63: =+IFERROR(AA63/F63,"") -> 0 | AI63: =+IFERROR(AB63/F63,"") -> 0 | AK63: 240.35 | AL63: 5.44 | AM63: 5.44 | AN63: 0 | AO63: 0 | AP63: 0 | AR63: Above 11% | AT63: 1744 | AU63: 2983 | AV63: 221 | AW63: 0 | AX63: 0 | AY63: 439
A64: 5879 | B64: Multaq 400mg Tablets 60 | C64: 10.07 | D64: 279.6 | E64: =D64/2 -> 139.8 | F64: 1290 | G64: =+E64/F64 -> 0.10837209 | I64: 200 | J64: 0 | K64: 0 | L64: 0 | N64: 0 | P64: =+I64*C64 -> 2014 | Q64: =+J64*C64 -> 0 | R64: =+K64*C64 -> 0 | S64: =+L64*C64 -> 0 | T64: =+M64*C64 -> 0 | U64: =+N64*C64 -> 0 | W64: 139 | X64: 184 | Y64: 125 | Z64: 40 | AA64: 211 | AB64: 84 | AD64: =+IFERROR(W64/F64,"") -> 0.10775194 | AE64: =+IFERROR(X64/F64,"") -> 0.14263566 | AF64: =+IFERROR(Y64/F64,"") -> 0.096899225 | AG64: =+IFERROR(Z64/F64,"") -> 0.031007752 | AH64: =+IFERROR(AA64/F64,"") -> 0.16356589 | AI64: =+IFERROR(AB64/F64,"") -> 0.065116279 | AK64: 611.49 | AL64: 1375.2 | AM64: 1375.2 | AN64: 1292.89 | AO64: 418 | AP64: -1021 | AR64: Below 11% | AT64: 4780 | AU64: 0 | AV64: 0 | AW64: 0 | AX64: 0 | AY64: 0
A65: 5854 | B65: Zyprexa 2.5mg (Olanzepine)Tablets 28 | C65: 10.01 | D65: 200 | E65: =D65/2 -> 100 | F65: 68 | G65: =+E65/F65 -> 1.4705882 | I65: 0 | J65: 0 | K65: 0 | L65: 0 | N65: 0 | P65: =+I65*C65 -> 0 | Q65: =+J65*C65 -> 0 | R65: =+K65*C65 -> 0 | S65: =+L65*C65 -> 0 | T65: =+M65*C65 -> 0 | U65: =+N65*C65 -> 0 | W65: 0 | X65: 0 | Y65: 0 | Z65: 0 | AA65: 0 | AB65: 0 | AD65: =+IFERROR(W65/F65,"") -> 0 | AE65: =+IFERROR(X65/F65,"") -> 0 | AF65: =+IFERROR(Y65/F65,"") -> 0 | AG65: =+IFERROR(Z65/F65,"") -> 0 | AH65: =+IFERROR(AA65/F65,"") -> 0 | AI65: =+IFERROR(AB65/F65,"") -> 0 | AK65: 0 | AL65: 0 | AM65: 0 | AN65: 0 | AO65: 0 | AP65: 0 | AR65: Above 11% | AT65: 0 | AU65: 0 | AV65: 0 | AW65: 0 | AX65: 0 | AY65: 0
A66: 5832 | B66: Topamax 200mg Tablets 60 | C66: 9.96 | D66: 400 | E66: =D66/2 -> 200 | F66: 334 | G66: =+E66/F66 -> 0.5988024 | I66: 90 | J66: 0 | K66: 0 | L66: 0 | N66: 31 | P66: =+I66*C66 -> 896.4 | Q66: =+J66*C66 -> 0 | R66: =+K66*C66 -> 0 | S66: =+L66*C66 -> 0 | T66: =+M66*C66 -> 0 | U66: =+N66*C66 -> 308.76 | W66: 13 | X66: 36 | Y66: 0 | Z66: 0 | AA66: 168 | AB66: 0 | AD66: =+IFERROR(W66/F66,"") -> 0.038922156 | AE66: =+IFERROR(X66/F66,"") -> 0.10778443 | AF66: =+IFERROR(Y66/F66,"") -> 0 | AG66: =+IFERROR(Z66/F66,"") -> 0 | AH66: =+IFERROR(AA66/F66,"") -> 0.50299401 | AI66: =+IFERROR(AB66/F66,"") -> 0 | AK66: 94.15 | AL66: 284.9 | AM66: 284.9 | AN66: 0 | AO66: 1673.28 | AP66: 0 | AR66: Above 11% | AT66: 3294.9 | AU66: 0 | AV66: 0 | AW66: 0 | AX66: 0 | AY66: 1152.27
A67: 5420L | B67: Mirapexin 1.05mg Prolonged-Release Tablets 30s | C67: 9.91 | D67: 50 | E67: =D67/2 -> 25 | F67: 27 | G67: =+E67/F67 -> 0.92592593 | I67: 0 | J67: 0 | K67: 0 | L67: 0 | M67: 50 | N67: 0 | P67: =+I67*C67 -> 0 | Q67: =+J67*C67 -> 0 | R67: =+K67*C67 -> 0 | S67: =+L67*C67 -> 0 | T67: =+M67*C67 -> 495.5 | U67: =+N67*C67 -> 0 | W67: 13 | X67: 22 | Y67: 13 | Z67: 9 | AA67: 12 | AB67: 11 | AD67: =+IFERROR(W67/F67,"") -> 0.48148148 | AE67: =+IFERROR(X67/F67,"") -> 0.81481481 | AF67: =+IFERROR(Y67/F67,"") -> 0.48148148 | AG67: =+IFERROR(Z67/F67,"") -> 0.33333333 | AH67: =+IFERROR(AA67/F67,"") -> 0.44444444 | AI67: =+IFERROR(AB67/F67,"") -> 0.40740741 | AK67: 280.87 | AL67: 427.23 | AM67: 427.23 | AN67: 254.04 | AO67: 154.16 | AP67: 151.46 | AR67: Above 11% | AT67: 0 | AU67: 0 | AV67: 0 | AW67: 0 | AX67: 661 | AY67: 0
